Workbook

Sheet LEIA_ME
A1: COMPARATIVO DE ORCAMENTOS - ENERGIA SOLAR + CARREGAMENTO DE BYD HIBRIDO
B2: Cliente: Henrique dos Santos Peite | UC Enel SP 0118487990 / 100242856108 | Classe B1 residencial, fornecimento MONOFASICO | Local da instalacao informado: Av. Cel. Sezefredo Fagundes, 8482 C2
B4: 1. OS QUATRO ORCAMENTOS ANALISADOS
B5: A) TecSolarSP - 12 modulos JA Solar 615 W = 7,38 kWp + Huawei 6 kW -> cotacao Belenergy WEB-006506779 = R$ 18.228,70
B6: B) TecSolarSP - 12 modulos Astronergy 605 W = 7,26 kWp + Huawei 6 kW -> cotacao Belenergy WEB-006512519 = R$ 17.307,90
B7: C) SunWash (Yuri) - 10 modulos TCL 620 W = 6,20 kWp + inversor AUXSOL 5 kW -> R$ 14.220,34 INSTALADO
B8: D) SunWash (Yuri) - 10 modulos TCL 620 W = 6,20 kWp + inversor HUAWEI 5 kW -> R$ 15.220,34 INSTALADO
B9: (a SunWash tambem anunciou kits Intelbras de 'ate 500 / 700 / 1000 kWh/mes' por R$ 12.459,81 / 16.190,48 / 20.777,81
B10: + R$ 1.800 de acrescimo regional. Sem quantidade nem potencia de modulo informadas - descartados da comparacao.)
B11: E) William - 10 modulos Maxeon 535 W = 5,35 kWp + Solis 4 kW -> R$ 18.848,91 INSTALADO (kit 11.158,91 + eng. 790 + instal. 6.900)
B12: F) Sun Coast (Alexandre) - 8 modulos RONMA 585 W = 4,68 kWp + AUXSOL 3 kW 1 MPPT -> R$ 12.387,64 INSTALADO
B13: Proposta 40436 de 11/08/2026, valida ate 20/08/2026. CNPJ 47.864.839/0001-31. Unica com garantias declaradas.
B14: G) SunWash (Yuri) - 10 modulos de 650 W = 6,50 kWp + 4 MICROINVERSORES de 2,25 kW -> R$ 16.780,54 INSTALADO
... B82: quantidade real de placas que cabem NAO foram avaliadas nesta analise.

Sheet ENTRADAS
A1: ENTRADAS - DADOS DE PARTIDA
A2: Edite apenas as celulas AMARELAS. Os dados da conta ja sao REAIS (extraidos da fatura). Os dados do BYD ainda sao estimativa.
B4: A) LOCAL E TELHADO
B5: Endereco da unidade consumidora | C5: Av Cel Sezefredo Fagundes 8482 CS 2 | E5: CONFIRMADO na fatura
B6: Bairro / Cidade / CEP | C6: Jardim das Pedras - SAO PAULO/SP - 02367-075 | E6: ALERTA: a peca da TecSolarSP diz 'Franco da Rocha'. A conta diz SAO PAULO capital. Corrigir antes da homologacao
B7: Distribuidora | C7: Enel SP (Eletropaulo Metropolitana) | E7: CONFIRMADO na fatura - CNPJ 61.xxx.xxx/xxxx-93
B8: Orientacao do telhado (azimute) | C8: Sudeste (SE) | E8: Declarado pela TecSolarSP. Penaliza a geracao no hemisferio sul
B9: Inclinacao do telhado | C9: 20 | D9: graus | E9: Declarado pela TecSolarSP
B10: Tipo de telha | C10: A CONFIRMAR | E10: ALERTA: TecSolarSP cotou FIBROCIMENTO e William cotou telha COLONIAL. Um dos dois nao viu o telhado
B11: Sombreamento | C11: NAO AVALIADO | E11: Nao foram enviadas fotos do telhado - area util e sombras nao foram verificadas
B13: B) CONTA DE ENERGIA (TODOS OS VALORES CONFIRMADOS NA FATURA DE JUL/2026)
B14: Classe / subgrupo / modalidade | C14: B1 Residencial Convencional | E14: CONFIRMADO: 'B - B1 - CONVENCIONAL - Residencial'
B15: Numero de fases do padrao ATUAL | C15: 1 | D15: fases | E15: CONFIRMADO na fatura: MONOFASICO (127 V na Enel SP)
B16: Numero de fases DEPOIS do projeto | C16: 2 | D16: fases | E16: ALERTA: todos os inversores cotados sao de 220 V e exigem 2 fases. Este e o valor usado nos calculos
B17: Custo de disponibilidade apos o projeto | C17: =IF(C16=1,30,IF(C16=2,50,100)) -> 50 | D17: kWh/mes | E17: Minimo faturado todo mes. Sobe de 30 para 50 kWh ao virar bifasico - custo permanente
B18: TARIFA EFETIVA TOTAL com tributos | C18: 1.02147 | D18: R$/kWh | E18: CONFIRMADO: R$ 551,59 de energia / 540 kWh. Inclui TUSD + TE + bandeira amarela + PIS/COFINS + ICMS 18%
B19: TUSD com tributos | C19: 0.59643 | D19: R$/kWh | E19: CONFIRMADO na fatura (tarifa sem tributos: R$ 0,46394)
B20: TE - Energia com tributos | C20: 0.40085 | D20: R$/kWh | E20: CONFIRMADO na fatura (tarifa sem tributos: R$ 0,31182)
B21: Adicional de bandeira (amarela em jul/26) | C21: 0.02419 | D21: R$/kWh | E21: CONFIRMADO: R$ 13,06 / 540 kWh. Em bandeira verde este valor e zero
B22: Parcela da TUSD que corresponde ao Fio B | C22: 0.6 | E22: ESTIMATIVA - a fatura nao detalha o Fio B. Pedir a planilha tarifaria da Enel/ANEEL. Faixa usual: 55% a 70% da TUSD
B23: TUSD Fio B com tributos | C23: =C19*C22 -> 0.357858 | D23: R$/kWh | E23: Base de cobranca sobre a energia compensada (Lei 14.300)
B24: % do Fio B faturado em 2026 | C24: 0.6 | E24: Lei 14.300/2022: 60% em 2026, 75% em 2027, 90% em 2028, 100% de 2029 em diante
B25: CUSTO EFETIVO DO FIO B HOJE | C25: =C23*C24 -> 0.2147148 | D25: R$/kWh | E25: E o que voce paga por cada kWh compensado com credito
B26: COSIP / iluminacao publica | C26: 21.11 | D26: R$/mes | E26: CONFIRMADO na fatura. NAO e compensada pela geracao solar
B27: Inflacao energetica anual | C27: 0.07 | D27: %/ano | E27: Premissa. A Enel aplicou +8,8% para residencial em 04/07/2026 (Res. Homologatoria 3.596/26)
B28: Custo da adequacao do padrao (mono -> bifasico) | C28: 2500 | D28: R$ | E28: ESTIMATIVA - nenhum orcamento incluiu. Pedir orcamento de eletricista + taxa Enel. Aplicado a TODAS as opcoes
B30: C) PREMISSAS TECNICAS DO SISTEMA FV
B31: Performance Ratio (PR) | C31: 0.79 | E31: Perdas de ~21%: temperatura, sujeira, cabos, inversor, mismatch
B32: PR do cenario conservador | C32: 0.72 | E32: Usado na linha de sensibilidade do COMPARATIVO. William usou 0,70 na proposta dele
B33: Degradacao no 1o ano | C33: 0.02 | E33: Tipico de modulo novo
B34: Degradacao dos anos seguintes | C34: 0.0045 | D34: %/ano | E34: N-type TOPCon ~0,40%/ano. PERC ~0,55%/ano - o modulo do William e PERC
B35: Manutencao / limpeza (O&M) | C35: 300 | D35: R$/ano | E35: Premissa: 2 limpezas por ano
B36: Provisao anual para troca do inversor | C36: 150 | D36: R$/ano | E36: Inversor dura ~12 a 15 anos, o modulo dura 25+
B37: Autoconsumo instantaneo | C37: 0.3 | E37: Parcela usada no mesmo instante da geracao. Sobe muito se o BYD carregar de dia
B39: D) BYD HIBRIDO >>> DADOS NAO INFORMADOS - TUDO AQUI E ESTIMATIVA <<<
B40: Modelo do veiculo | C40: BYD Song Pro DM-i GL | E40: INFORMADO pelo cliente
B41: Capacidade da bateria | C41: 12.9 | D41: kWh | E41: ESTIMATIVA para o Song Pro DM-i - CONFIRMAR no manual, pois a versao GL pode diferir
B42: Consumo eletrico do veiculo | C42: 16 | D42: kWh/100km | E42: ESTIMATIVA de uso real do Song Pro em modo eletrico. Faixa plausivel: 14 a 18 conforme trajeto e uso de ar-condicionado
B43: Distancia percorrida por dia | C43: 80 | D43: km/dia | E43: INFORMADO pelo cliente
B44: Dias de carregamento por mes | C44: 30 | D44: dias/mes | E44: INFORMADO pelo cliente: carrega todos os dias
B45: Eficiencia de carregamento (tomada -> bateria) | C45: 0.86 | E45: Perdas do carregador AC, do BMS e termicas. Faixa tecnica de 85% a 90%
B46: Potencia do carregador (kW = POTENCIA) | C46: 3.3 | D46: kW | E46: ESTIMATIVA: carregador AC embarcado do Song Pro DM-i. CONFIRMAR - define disjuntor e cabo
B47: Objetivo declarado | C47: RODAR TUDO NO ELETRICO | E47: INFORMADO pelo cliente. Exige DUAS cargas por dia - ver bloco 7 da aba BYD
B48: Margem de crescimento futuro do consumo | C48: 0.15 | E48: Premissa para o Cenario 3. A conta ja mostra alta de 22% em 6 meses e 39% ano a ano
B49: Reserva da bateria mantida para o modo hibrido | C49: 0.25 | E49: Os DM-i nao esvaziam a bateria: guardam uma reserva para operar como hibrido. ESTIMATIVA de 25%
B51: E) BASE DE DIMENSIONAMENTO (calculada da conta real)
B52: Base residencial PURA - 10 meses antes do degrau | C52: =CONTA!C77*30.4 -> 351.82709 | D52: kWh/mes | E52: 352 kWh/mes. E a base USADA nos cenarios, partindo do principio de que o degrau de maio ja e carga do carro
B53: Alternativa: consumo atual medido (com o degrau) | C53: =CONTA!C78*30.4 -> 467.6401 | D53: kWh/mes | E53: 468 kWh/mes. Use esta se o degrau for OUTRA carga nova e nao o carro - ver bloco 6 da aba BYD
B54: Custo marginal por modulo adicional (instalado) | C54: 900 | D54: R$/modulo | E54: ESTIMATIVA: modulo + estrutura + cabo + mao de obra, SEM inversor. Usado nas colunas de simulacao G12 e G14. PEDIR O VALOR REAL AO YURI
B56: F) PADRAO REAL DE CARREGAMENTO (informado pelo cliente)
B57: Reposicao media por carga | C57: 0.5 | D57: da bateria | E57: INFORMADO: recarrega em media 50% da bateria por sessao
B58: Cargas por dia | C58: 1 | D58: cargas/dia | E58: INFORMADO: uma carga por dia
B60: G) COMBUSTIVEL (para comparar eletrico x gasolina)
B61: Consumo em modo hibrido | C61: 16 | D61: km/litro | E61: ESTIMATIVA para o Song Pro DM-i rodando como hibrido. Faixa plausivel: 15 a 20 km/l
B62: Preco da gasolina | C62: 6.2 | D62: R$/litro | E62: ESTIMATIVA. Ajuste para o preco que voce paga

Sheet CONTA
A1: ANALISE DA CONTA DE ENERGIA - DADOS REAIS DA FATURA
A2: Fonte: fatura Enel SP no 599307231012, ref. 07/2026, UC 0118487990 / 100242856108, NF 085726810 emitida em 30/07/2026.
B4: HISTORICO DE 13 MESES (impresso na fatura) | G4: DECOMPOSICAO DA FATURA DE JUL/2026 (540 kWh)
B5: Mes/Ano | C5: Consumo (kWh) | D5: Dias | E5: Media (kWh/dia) | G5: USO DO SISTEMA DE DISTRIBUICAO (TUSD) | H5: 322.07 | I5: 540 kWh x R$ 0,59643 com tributos (tarifa base R$ 0,46394)
B6: Jul/25 | C6: 389 | D6: 32 | E6: =IFERROR(C6/D6,0) -> 12.15625 | G6: ENERGIA (TE) | H6: 216.46 | I6: 540 kWh x R$ 0,40085 com tributos (tarifa base R$ 0,31182)
B7: Ago/25 | C7: 364 | D7: 31 | E7: =IFERROR(C7/D7,0) -> 11.741935 | G7: ADICIONAL DE BANDEIRA AMARELA | H7: 13.06 | I7: Bandeira aplicada no mes: AMARELA. Em bandeira verde este item e zero
B8: Set/25 | C8: 290 | D8: 29 | E8: =IFERROR(C8/D8,0) -> 10 | G8: Subtotal de faturamento (energia) | H8: 551.59 | I8: Base de calculo do ICMS
B9: Out/25 | C9: 375 | D9: 32 | E9: =IFERROR(C9/D9,0) -> 11.71875 | G9: COSIP - iluminacao publica municipal | H9: 21.11 | I9: Cobrada pela Prefeitura. A geracao solar NAO reduz este item
B10: Nov/25 | C10: 337 | D10: 30 | E10: =IFERROR(C10/D10,0) -> 11.233333 | G10: TOTAL DA FATURA | H10: 572.7 | I10: Vencimento 14/08/2026
B11: Dez/25 | C11: 323 | D11: 29 | E11: =IFERROR(C11/D11,0) -> 11.137931 | G11: TARIFA EFETIVA = 551,59 / 540 | H11: =IFERROR(H8/540,0) -> 1.021463 | I11: R$ 1,0215/kWh. E a tarifa usada em toda a planilha.
B12: Jan/26 | C12: 372 | D12: 32 | E12: =IFERROR(C12/D12,0) -> 11.625
B13: Fev/26 | C13: 348 | D13: 30 | E13: =IFERROR(C13/D13,0) -> 11.6 | G13: TRIBUTOS EMBUTIDOS NA FATURA
B14: Mar/26 | C14: 354 | D14: 29 | E14: =IFERROR(C14/D14,0) -> 12.206897 | G14: PIS/PASEP - base R$ 452,31 a 0,92% | H14: 4.14 | I14: Incide antes do ICMS
B15: Abr/26 | C15: 394 | D15: 32 | E15: =IFERROR(C15/D15,0) -> 12.3125 | G15: COFINS - base R$ 452,31 a 4,23% | H15: 19.12 | I15: Incide antes do ICMS
B16: Mai/26 | C16: 457 | D16: 30 | E16: =IFERROR(C16/D16,0) -> 15.233333 | G16: ICMS - base R$ 551,59 a 18% | H16: 99.28 | I16: Maior tributo da conta
B17: Jun/26 | C17: 422 | D17: 29 | E17: =IFERROR(C17/D17,0) -> 14.551724 | G17: TOTAL DE TRIBUTOS | H17: 122.54 | I17: 21,4% do valor total da fatura
B18: Jul/26 | C18: 540 | D18: 33 | E18: =IFERROR(C18/D18,0) -> 16.363636
B19: Linha 6 = Jul/25 (mes mais antigo). Linha 18 = Jul/26 (mes atual). Verde = menor consumo. Vermelho = maior consumo. | G19: DADOS DA UNIDADE CONSUMIDORA
G20: Distribuidora | H20: Enel SP - Eletropaulo Metropolitana
B21: ESTATISTICAS DOS 12 MESES MAIS RECENTES (Ago/25 a Jul/26) | G21: Unidade consumidora | H21: 0118487990 / 100242856108
B22: TOTAL ANUAL | C22: =SUM(C7:C18) -> 4576 | D22: kWh/ano | G22: Numero do cliente | H22: 24186384
B23: CONSUMO MEDIO MENSAL = soma / 12 | C23: =C22/12 -> 381.33333 | D23: kWh/mes | G23: Classe / subgrupo / modalidade | H23: B - B1 - Convencional - Residencial
B24: Total de dias faturados | C24: =SUM(D7:D18) -> 366 | D24: dias | G24: TIPO DE LIGACAO | H24: MONOFASICO
B25: Consumo medio diario | C25: =IFERROR(C22/C24,0) -> 12.502732 | D25: kWh/dia | G25: Bandeira tarifaria do mes | H25: AMARELA
B26: MAIOR CONSUMO (Jul/26) | C26: =MAX(C7:C18) -> 540 | D26: kWh | G26: Periodo de leitura | H26: 26/06/2026 a 29/07/2026 - 33 dias
B27: MENOR CONSUMO (Set/25) | C27: =MIN(C7:C18) -> 290 | D27: kWh | G27: Proxima leitura prevista | H27: 27/08/2026
B28: Amplitude maior / menor | C28: =IFERROR(C26/C27-1,0) -> 0.86206897 | G28: Medidor | H28: UQM9HDN25C01281527
B29: Consumo do mes atual (Jul/26) | C29: =C18 -> 540 | D29: kWh | G29: Leitura anterior / atual | H29: 3.458 -> 3.998 (constante 1,0)
B30: Mes atual x media dos 12 meses | C30: =IFERROR(C29/C23-1,0) -> 0.41608392 | G30: Reajuste tarifario vigente | H30: +8,8% residencial em 04/07/2026 (Res. Hom. ANEEL 3.596/26)
B31: Media dos 6 meses mais antigos (Ago/25 a Jan/26) | C31: =AVERAGE(C7:C12) -> 343.5 | D31: kWh/mes | G31: Custo de disponibilidade hoje (monofasico) | H31: 30 kWh/mes
B32: Media dos 6 meses mais recentes (Fev/26 a Jul/26) | C32: =AVERAGE(C13:C18) -> 419.16667 | D32: kWh/mes | G32: Custo de disponibilidade se virar bifasico | H32: 50 kWh/mes
B33: TENDENCIA - recentes x antigos | C33: =IFERROR(C32/C31-1,0) -> 0.22028142 | D33: semestre contra semestre | G33: DEC / FEC do conjunto (ano) | H33: DEC 7,46 h / FEC 4,25 interrupcoes
B34: MESMO MES, ANO ANTERIOR: Jul/25 x Jul/26 | C34: =IFERROR(C18/C6-1,0) -> 0.38817481 | D34: compara so julho com julho
B36: TABELA EM ORDEM DE CALENDARIO (usada na aba SIMULACAO_MENSAL)
B37: Mes | C37: Consumo (kWh) | D37: Referencia
B38: Jan | C38: =C12 -> 372 | D38: Jan/26
B39: Fev | C39: =C13 -> 348 | D39: Fev/26
B40: Mar | C40: =C14 -> 354 | D40: Mar/26
B41: Abr | C41: =C15 -> 394 | D41: Abr/26
B42: Mai | C42: =C16 -> 457 | D42: Mai/26
B43: Jun | C43: =C17 -> 422 | D43: Jun/26
B44: Jul | C44: =C18 -> 540 | D44: Jul/26
B45: Ago | C45: =C7 -> 364 | D45: Ago/25
B46: Set | C46: =C8 -> 290 | D46: Set/25
B47: Out | C47: =C9 -> 375 | D47: Out/25
B48: Nov | C48: =C10 -> 337 | D48: Nov/25
B49: Dez | C49: =C11 -> 323 | D49: Dez/25
B50: TOTAL | C50: =SUM(C38:C49) -> 4576
B52: GASTO ATUAL COM ENERGIA
B53: Gasto anual atual (sem BYD, sem solar) | C53: =C22*H11+H9*12 -> 4927.5345
B54: Gasto medio mensal atual | C54: =C53/12 -> 410.62788
B55: Gasto do mes de maior consumo (Jul/26) | C55: =H10 -> 572.7
B57: CONCLUSOES DA ANALISE DA CONTA:
B58: 1. Media de 381,3 kWh/mes nos 12 meses mais recentes (4.576 kWh no ano). Este e o CENARIO 1 e NAO deve ser a base do projeto.
B59: 2. TENDENCIA DE ALTA CONFIRMADA POR DOIS CAMINHOS DIFERENTES:
B60: - semestre contra semestre: os 6 meses mais recentes estao 22,0% acima dos 6 mais antigos;
B61: - julho contra julho: Jul/25 foram 389 kWh e Jul/26 foram 540 kWh, ou seja +38,8% no MESMO mes do ano anterior.
B62: O segundo numero elimina o efeito de estacao: o consumo esta crescendo de verdade, nao e so inverno.
B63: 3. PERGUNTA IMPORTANTE: o BYD ja esta sendo carregado em casa? A curva Abr-Mai-Jun-Jul (394 / 457 / 422 / 540) e o salto
B64: de 39% ano a ano sao compativeis com a entrada de uma carga nova. Se o carro ja carrega em casa, o consumo futuro sera
B65: ainda maior do que o Cenario 2 desta planilha, e o dimensionamento precisa subir.
B66: 4. LIGACAO MONOFASICA CONFIRMADA NA FATURA. E o achado mais critico: os quatro orcamentos usam inversor de 220 V, que
B67: exige duas fases. Nenhum incluiu o custo da troca de padrao. Ao virar bifasico, o minimo faturado sobe de 30 para 50 kWh/mes.
B68: 5. Bandeira AMARELA no mes, somando R$ 13,06. Em bandeira verde a tarifa efetiva cai para cerca de R$ 0,997/kWh.
... B76: ANALISE FORENSE: JA EXISTE CARGA NOVA NA CONTA? (o medidor nao separa o carro, mas o padrao diario denuncia)
B77: Media diaria dos 10 meses estaveis (Jul/25 a Abr/26) | C77: =AVERAGE(E6:E15) -> 11.57326 | D77: kWh/dia | E77: Periodo em que o consumo diario ficou entre 10,0 e 12,3
B78: Media diaria dos 3 ultimos meses (Mai a Jul/26) | C78: =AVERAGE(E16:E18) -> 15.382898 | D78: kWh/dia | E78: Periodo apos o degrau
B79: DEGRAU DETECTADO | C79: =C78-C77 -> 3.8096383 | D79: kWh/dia | E79: Carga nova que apareceu por volta de maio de 2026
B80: DEGRAU EM BASE MENSAL | C80: =C79*30.4 -> 115.813 | D80: kWh/mes | E80: E este o valor que provavelmente e o carro - ou uma carga nova qualquer
B81: Aumento percentual | C81: =IFERROR(C78/C77-1,0) -> 0.32917591
B82: CONTROLE DE SAZONALIDADE - Jul/25 | C82: =E6 -> 12.15625 | D82: kWh/dia | E82: Julho de 2025 tambem foi inverno, com chuveiro eletrico ligado
B83: CONTROLE DE SAZONALIDADE - Jul/26 | C83: =E18 -> 16.363636 | D83: kWh/dia | E83: Mesmo mes, mesma estacao, um ano depois
B84: Diferenca julho contra julho | C84: =C83-C82 -> 4.2073864 | D84: kWh/dia | E84: ESTE e o numero mais confiavel: compara estacao com estacao
B85: Diferenca julho contra julho em base mensal | C85: =C84*30.4 -> 127.90455 | D85: kWh/mes | E85: Prova que o aumento NAO e sazonal
B86: Energia da rede por km rodado | C86: =ENTRADAS!C42/100/ENTRADAS!C45 -> 0.18604651 | D86: kWh/km | E86: Consumo do veiculo dividido pela eficiencia de carregamento
B87: SE O DEGRAU FOR O BYD, ISSO EQUIVALE A | C87: =IFERROR(C80/C86,0) -> 622.4949 | D87: km/mes | E87: Quilometragem eletrica compativel com o degrau medido
B88: o mesmo em km por dia | C88: =IFERROR(C87/30.4,0) -> 20.476806 | D88: km/dia
B89: Pelo controle julho x julho, equivale a | C89: =IFERROR(C85/C86,0) -> 687.48693 | D89: km/mes | E89: Segunda estimativa, pelo caminho independente
B91: COMO ESTA ANALISE FUNCIONA E PARA QUE SERVE:
B92: O medidor da Enel registra apenas o TOTAL da casa - nao existe forma de ler na conta quanto foi para o carro.
B93: Mas o consumo DIARIO (coluna E) revela um degrau claro: ficou entre 10,0 e 12,3 kWh/dia por dez meses seguidos,
B94: e saltou para 14,5 a 16,4 kWh/dia a partir de maio de 2026. Normalizar por dia e essencial porque os ciclos de
B95: faturamento variam de 29 a 33 dias - comparar kWh do mes direto induz a erro.
B97: O teste decisivo e julho contra julho: mesma estacao, mesmo uso de chuveiro eletrico, um ano de diferenca.
B98: Deu +4,2 kWh/dia. Isso praticamente elimina a hipotese de que o aumento seja apenas inverno.
B100: RESSALVAS HONESTAS: (a) nao ha dados de maio e junho de 2025 para comparar esses dois meses ano a ano;
B101: (b) o degrau pode ser outra carga nova - ar-condicionado, freezer, mais gente em casa - e nao o carro;
B102: (c) o mes de Nov/25 foi faturado como MED (media estimada), nao leitura real, o que adiciona um pouco de ruido;
B103: (d) a conversao para quilometragem usa o consumo estimado de 17 kWh/100 km, que ainda nao foi confirmado.
B105: POR ISSO A PERGUNTA IMPORTA TANTO: se o carro JA esta carregando desde maio, o consumo futuro e proximo dos
... B107: consumo sobe para a faixa de 590 a 765 kWh/mes. A diferenca entre os dois casos e de 2 a 3 placas.

Sheet GERACAO
A1: IRRADIACAO E GERACAO POR kWp - REGIAO METROPOLITANA NORTE DE SAO PAULO
A2: HSP estimada para a regiao. CONFIRMAR no CRESESB ou PVGIS com o CEP exato. Fatores de transposicao calculados para latitude -23,3 graus.
B4: Mes | C4: Dias | D4: HSP horizontal (kWh/m2.dia) | E4: Fator SE 20 graus | F4: HSP plano SE | G4: Fator Norte 20 graus | H4: HSP plano Norte | I4: Geracao/kWp SE (kWh/mes) | J4: Geracao/kWp Norte (kWh/mes) | K4: Perda por ser SE
B5: Jan | C5: 31 | D5: 5.3 | E5: 0.97 | F5: =D5*E5 -> 5.141 | G5: 1.02 | H5: =D5*G5 -> 5.406 | I5: =F5*C5*ENTRADAS!$C$31 -> 125.90309 | J5: =H5*C5*ENTRADAS!$C$31 -> 132.39294 | K5: =IFERROR(I5/J5-1,0) -> -0.049019608
B6: Fev | C6: 28 | D6: 5.4 | E6: 0.96 | F6: =D6*E6 -> 5.184 | G6: 1.04 | H6: =D6*G6 -> 5.616 | I6: =F6*C6*ENTRADAS!$C$31 -> 114.67008 | J6: =H6*C6*ENTRADAS!$C$31 -> 124.22592 | K6: =IFERROR(I6/J6-1,0) -> -0.076923077
B7: Mar | C7: 31 | D7: 4.9 | E7: 0.95 | F7: =D7*E7 -> 4.655 | G7: 1.07 | H7: =D7*G7 -> 5.243 | I7: =F7*C7*ENTRADAS!$C$31 -> 114.00095 | J7: =H7*C7*ENTRADAS!$C$31 -> 128.40107 | K7: =IFERROR(I7/J7-1,0) -> -0.11214953
B8: Abr | C8: 30 | D8: 4.4 | E8: 0.94 | F8: =D8*E8 -> 4.136 | G8: 1.11 | H8: =D8*G8 -> 4.884 | I8: =F8*C8*ENTRADAS!$C$31 -> 98.0232 | J8: =H8*C8*ENTRADAS!$C$31 -> 115.7508 | K8: =IFERROR(I8/J8-1,0) -> -0.15315315
B9: Mai | C9: 31 | D9: 3.7 | E9: 0.92 | F9: =D9*E9 -> 3.404 | G9: 1.14 | H9: =D9*G9 -> 4.218 | I9: =F9*C9*ENTRADAS!$C$31 -> 83.36396 | J9: =H9*C9*ENTRADAS!$C$31 -> 103.29882 | K9: =IFERROR(I9/J9-1,0) -> -0.19298246
B10: Jun | C10: 30 | D10: 3.5 | E10: 0.91 | F10: =D10*E10 -> 3.185 | G10: 1.16 | H10: =D10*G10 -> 4.06 | I10: =F10*C10*ENTRADAS!$C$31 -> 75.4845 | J10: =H10*C10*ENTRADAS!$C$31 -> 96.222 | K10: =IFERROR(I10/J10-1,0) -> -0.21551724
B11: Jul | C11: 31 | D11: 3.65 | E11: 0.91 | F11: =D11*E11 -> 3.3215 | G11: 1.15 | H11: =D11*G11 -> 4.1975 | I11: =F11*C11*ENTRADAS!$C$31 -> 81.343535 | J11: =H11*C11*ENTRADAS!$C$31 -> 102.79677 | K11: =IFERROR(I11/J11-1,0) -> -0.20869565
B12: Ago | C12: 31 | D12: 4.55 | E12: 0.93 | F12: =D12*E12 -> 4.2315 | G12: 1.11 | H12: =D12*G12 -> 5.0505 | I12: =F12*C12*ENTRADAS!$C$31 -> 103.62944 | J12: =H12*C12*ENTRADAS!$C$31 -> 123.68675 | K12: =IFERROR(I12/J12-1,0) -> -0.16216216
B13: Set | C13: 30 | D13: 4.45 | E13: 0.95 | F13: =D13*E13 -> 4.2275 | G13: 1.06 | H13: =D13*G13 -> 4.717 | I13: =F13*C13*ENTRADAS!$C$31 -> 100.19175 | J13: =H13*C13*ENTRADAS!$C$31 -> 111.7929 | K13: =IFERROR(I13/J13-1,0) -> -0.10377358
B14: Out | C14: 31 | D14: 4.9 | E14: 0.96 | F14: =D14*E14 -> 4.704 | G14: 1.02 | H14: =D14*G14 -> 4.998 | I14: =F14*C14*ENTRADAS!$C$31 -> 115.20096 | J14: =H14*C14*ENTRADAS!$C$31 -> 122.40102 | K14: =IFERROR(I14/J14-1,0) -> -0.058823529
B15: Nov | C15: 30 | D15: 5.35 | E15: 0.97 | F15: =D15*E15 -> 5.1895 | G15: 1 | H15: =D15*G15 -> 5.35 | I15: =F15*C15*ENTRADAS!$C$31 -> 122.99115 | J15: =H15*C15*ENTRADAS!$C$31 -> 126.795 | K15: =IFERROR(I15/J15-1,0) -> -0.03
B16: Dez | C16: 31 | D16: 5.45 | E16: 0.97 | F16: =D16*E16 -> 5.2865 | G16: 1 | H16: =D16*G16 -> 5.45 | I16: =F16*C16*ENTRADAS!$C$31 -> 129.46639 | J16: =H16*C16*ENTRADAS!$C$31 -> 133.4705 | K16: =IFERROR(I16/J16-1,0) -> -0.03
B17: ANO | C17: =SUM(C5:C16) -> 365 | D17: =AVERAGE(D5:D16) -> 4.6291667 | F17: =AVERAGE(F5:F16) -> 4.3887917 | H17: =AVERAGE(H5:H16) -> 4.9325 | I17: =SUM(I5:I16) -> 1264.269 | J17: =SUM(J5:J16) -> 1421.2345 | K17: =IFERROR(I17/J17-1,0) -> -0.11044307
B18: MEDIA MES | I18: =I17/12 -> 105.35575 | J18: =J17/12 -> 118.43621
B20: A COLUNA I E A CHAVE DE TODA A PLANILHA: quantos kWh cada 1 kWp gera por mes no SEU telhado (Sudeste, 20 graus).
B21: A coluna J mostra o que geraria num telhado Norte. A coluna K e a perda por estar voltado ao Sudeste.
B23: COMPARACAO DIRETA COM O QUE OS VENDEDORES PROMETERAM (celula I17 x J17):
B24: TecSolarSP: 10.554 kWh/ano / 7,38 kWp = 1.430 kWh por kWp. Praticamente identico ao valor NORTE (J17).
B25: Eles declaram o telhado como SUDESTE na propria peca publicitaria. A promessa nao fecha com a orientacao declarada.
B26: SunWash: o anuncio diz textualmente 'CALCULO CONSIDERANDO NORTE DO TELHADO' e vale para Ribeirao Preto ate 80 km.
B27: Ribeirao Preto tem irradiacao maior que Sao Paulo. Sao dois desvios somados a favor do vendedor.
B28: William: usou HSP fixa de 4,5 h/dia e 30% de perdas (PR 0,70), chegando a 1.150 kWh por kWp. E o mais CONSERVADOR
B29: dos tres - abaixo do valor calculado aqui. A proposta dele erra por seguranca, nao por exagero.
B31: CONSEQUENCIA PRATICA DO TELHADO SUDESTE: a geracao se concentra na MANHA e cai a tarde.
B32: Isso favorece carregar o BYD entre 8h e 14h. Desfavorece consumo concentrado no fim da tarde e na noite.
B34: SENSIBILIDADE: com PR de 0,72 (telhado mais sujo, mais quente ou com sombra parcial) a geracao cai cerca de 9%.
B35: A aba COMPARATIVO mostra as duas linhas - realista e conservadora - para voce ver o pior caso.

Sheet BYD
A1: CONSUMO DO BYD HIBRIDO, CARREGADOR E CENARIOS DE CONSUMO
A2: TODOS os dados do veiculo sao ESTIMATIVA - voce ainda nao informou modelo, km/dia nem horario. kW = potencia. kWh = energia.
B4: 1) ENERGIA QUE O CARRO PRECISA (na bateria)
B5: Distancia por dia | C5: =ENTRADAS!C43 -> 80 | D5: km/dia | H5: ESTIMATIVA - o dado que mais muda o resultado
B6: Consumo eletrico do veiculo | C6: =ENTRADAS!C42 -> 16 | D6: kWh/100km | H6: ESTIMATIVA de uso real em modo eletrico
B7: Energia na bateria por dia = MENOR entre o que voce roda e o que voce recarrega | C7: =MIN(C5*C6/100,ENTRADAS!C41*ENTRADAS!C57*ENTRADAS!C58) -> 6.45 | D7: kWh/dia | H7: Roda 80 km = demanda 12,80 kWh/dia. Uma carga de 50% repoe 6,45 kWh/dia. Vale o MENOR: o carro so usa da bateria o que foi reposto
B8: Dias de carregamento por mes | C8: =ENTRADAS!C44 -> 30 | D8: dias/mes | H8: ESTIMATIVA
B9: ENERGIA NECESSARIA PARA O VEICULO POR MES | C9: =C7*C8 -> 193.5 | D9: kWh/mes | H9: Energia UTIL na bateria, ANTES das perdas de carregamento
B11: 2) ENERGIA QUE SAI DA REDE (o que o medidor registra)
B12: Eficiencia de carregamento (tomada -> bateria) | C12: =ENTRADAS!C45 -> 0.86 | H12: 86% adotado: 14% se perde no carregador AC, no BMS e em calor
B13: ENERGIA EFETIVAMENTE CONSUMIDA DA REDE PARA CARREGAR | C13: =C9/C12 -> 225 | D13: kWh/mes | H13: ESTE e o numero que entra na conta de luz e no dimensionamento
B14: Perda de carregamento (energia paga que nao roda) | C14: =C13-C9 -> 31.5 | D14: kWh/mes | H14: Desperdicio inevitavel do processo de carga
B15: Custo do carro na conta de luz SEM solar | C15: =C13*ENTRADAS!C18 -> 229.83075 | D15: R$/mes | H15: Tarifa real de R$ 1,0215/kWh
B16: Custo anual do carro SEM solar | C16: =C15*12 -> 2757.969 | D16: R$/ano
B17: Custo do carro na conta COM solar (so o Fio B) | C17: =C13*ENTRADAS!C25 -> 48.31083 | D17: R$/mes | H17: Compensado por credito: paga-se apenas 60% da TUSD Fio B em 2026
B18: ECONOMIA MENSAL SO NO CARREGAMENTO DO BYD | C18: =C15-C17 -> 181.51992 | D18: R$/mes | H18: Este e o item de maior retorno do projeto
B19: Economia anual so no carregamento do BYD | C19: =C18*12 -> 2178.239 | D19: R$/ano
B20: Custo por km em modo eletrico SEM solar | C20: =IFERROR(C15/(C5*C8),0) -> 0.095762813 | D20: R$/km | H20: Comparar com o custo por km na gasolina
B21: Custo por km em modo eletrico COM solar | C21: =IFERROR(C17/(C5*C8),0) -> 0.020129512 | D21: R$/km | H21: Rodar praticamente de graca
B23: 3) POTENCIA x ENERGIA - CARREGADOR (nao confundir kW com kWh)
B24: Potencia do carregador | C24: =ENTRADAS!C46 -> 3.3 | D24: kW | H24: POTENCIA: define corrente, bitola do cabo e disjuntor
B25: Tempo de carga por dia = energia do dia / potencia | C25: =IFERROR(C13/C8/C24,0) -> 2.2727273 | D25: horas/dia | H25: ENERGIA (kWh) dividida por POTENCIA (kW) = TEMPO (h)
B26: Tempo para carga completa 0-100% | C26: =IFERROR(ENTRADAS!C41/ENTRADAS!C45/C24,0) -> 4.5454545 | D26: horas | H26: Bateria inteira partindo de vazia
B27: Corrente do carregador em 220 V | C27: =IFERROR(C24*1000/220,0) -> 15 | D27: A | H27: Corrente nominal de operacao
B28: Disjuntor do circuito (125% da corrente - NBR 5410) | C28: =IFERROR(C27*1.25,0) -> 18.75 | D28: A | H28: Carga continua: circuito dimensionado a 125%
B29: Energia entregue em 1 hora de carregador ligado | C29: =C24*1 -> 3.3 | D29: kWh | H29: EXEMPLO DA LOGICA: 7,4 kW x 3 h = 22,2 kWh
B31: 4) CENARIOS DE CONSUMO
B32: Cenario | C32: Residencia (kWh/mes) | D32: BYD (kWh/mes) | E32: Margem (kWh/mes) | F32: CONSUMO TOTAL (kWh/mes) | G32: Consumo anual (kWh)
B33: 1 - So a residencia (base pura, sem o carro) | C33: =ENTRADAS!C52 -> 351.82709 | D33: =0 -> 0 | E33: =0 -> 0 | F33: =C33+D33+E33 -> 351.82709 | G33: =F33*12 -> 4221.9251
B34: 2 - RESIDENCIA + BYD tudo no eletrico | C34: =ENTRADAS!C52 -> 351.82709 | D34: =C13 -> 225 | E34: =0 -> 0 | F34: =C34+D34+E34 -> 576.82709 | G34: =F34*12 -> 6921.9251
B35: 3 - RESIDENCIA + BYD + CRESCIMENTO | C35: =ENTRADAS!C52 -> 351.82709 | D35: =C13 -> 225 | E35: =(C35+D35)*ENTRADAS!C48 -> 86.524064 | F35: =C35+D35+E35 -> 663.35116 | G35: =F35*12 -> 7960.2139
C37: ="O BYD aumenta o consumo da residencia em "&TEXT(IFERROR(D34/C34,0),"0.0%")&" - de "&TEXT(C34,"0")&" para "&TEXT(F34,"0")&" kWh/mes." -> O BYD aumenta o consumo da residencia em 64.0% - de 352 para 577 kWh/mes.
C38: ="O Cenario 3 ("&TEXT(F35,"0")&" kWh/mes) e o que deve orientar o dimensionamento, NAO a media de "&TEXT(C33,"0")&" kWh/mes da conta." -> O Cenario 3 (663 kWh/mes) e o que deve orientar o dimensionamento, NAO a media de 352 kWh/mes da conta.
B40: 5) DIA x NOITE - ONDE CARREGAR COMPENSA MAIS
B41: Estrategia | C41: Como funciona | D41: Custo por kWh | E41: Custo mensal do carro | F41: Vantagem | G41: Desvantagem
B42: Carregar de DIA (8h as 14h) | C42: Autoconsumo instantaneo: a energia vai do painel direto para o carro | D42: =0 -> 0 | E42: =0 -> 0 | F42: Nao passa pelo medidor: nao paga Fio B, nao paga nada | G42: Precisa que o carro esteja em casa de manha. Telhado SE gera mais de manha - combina bem
B43: Carregar a NOITE | C43: A geracao do dia vira credito e a noite o credito e usado | D43: =ENTRADAS!C25 -> 0.2147148 | E43: =C13*ENTRADAS!C25 -> 48.31083 | F43: Comodidade: chega, pluga e dorme | G43: Paga o Fio B sobre tudo o que foi compensado. Em 2026 sao 60% da TUSD, em 2029 sera 100%
B44: Carregar SEM energia solar | C44: Tarifa cheia da Enel | D44: =ENTRADAS!C18 -> 1.02147 | E44: =C13*ENTRADAS!C18 -> 229.83075 | F44: Nenhuma | G44: Custo maximo
B45: Ganho anual de carregar de DIA em vez de a NOITE:
C46: =(E43-E42)*12 -> 579.72996 | D46: R$/ano. Parece pouco hoje porque o Fio B esta em 60%. Em 2029 sera 100% e esse ganho quase dobra.
B47: RECOMENDACAO: programar o carregamento do veiculo para iniciar entre 9h e 10h nos dias em que o carro ficar em casa.
B48: O app do BYD permite agendar horario de carga. Vale a pena usar, e o ganho cresce todo ano com a regra do Fio B.
B51: 6) QUAL VAI SER O MEU CONSUMO? OS DOIS CAMINHOS POSSIVEIS
B52: Base residencial PURA (10 meses estaveis, antes do degrau) | C52: =CONTA!C77*30.4 -> 351.82709 | D52: kWh/mes
B53: Consumo ATUAL medido (ultimos 3 meses, ja com o degrau) | C53: =CONTA!C78*30.4 -> 467.6401 | D53: kWh/mes
B54: Degrau detectado na conta | C54: =CONTA!C80 -> 115.813 | D54: kWh/mes
B55: Energia da rede por km rodado | C55: =CONTA!C86 -> 0.18604651 | D55: kWh/km
B57: Quilometragem do BYD | C57: km/dia aprox. | D57: kWh/mes da rede so do carro | E57: CASO A: o degrau JA e o carro -> total | F57: kWp necessario (+10%) | G57: CASO B: o carro ainda vai entrar -> total | H57: kWp necessario (+10%)
B58: 400 | C58: =B58/30.4 -> 13.157895 | D58: =B58*$C$55 -> 74.418605 | E58: =$C$52+D58 -> 426.2457 | F58: =E58*12/GERACAO!$I$17*1.1 -> 4.4503529 | G58: =$C$53+D58 -> 542.0587 | H58: =G58*12/GERACAO!$I$17*1.1 -> 5.6595352
B59: 600 | C59: =B59/30.4 -> 19.736842 | D59: =B59*$C$55 -> 111.62791 | E59: =$C$52+D59 -> 463.455 | F59: =E59*12/GERACAO!$I$17*1.1 -> 4.8388484 | G59: =$C$53+D59 -> 579.268 | H59: =G59*12/GERACAO!$I$17*1.1 -> 6.0480307
B60: 800 | C60: =B60/30.4 -> 26.315789 | D60: =B60*$C$55 -> 148.83721 | E60: =$C$52+D60 -> 500.6643 | F60: =E60*12/GERACAO!$I$17*1.1 -> 5.2273439 | G60: =$C$53+D60 -> 616.47731 | H60: =G60*12/GERACAO!$I$17*1.1 -> 6.4365262
B61: 1000 | C61: =B61/30.4 -> 32.894737 | D61: =B61*$C$55 -> 186.04651 | E61: =$C$52+D61 -> 537.8736 | F61: =E61*12/GERACAO!$I$17*1.1 -> 5.6158394 | G61: =$C$53+D61 -> 653.68661 | H61: =G61*12/GERACAO!$I$17*1.1 -> 6.8250216
B62: 1200 | C62: =B62/30.4 -> 39.473684 | D62: =B62*$C$55 -> 223.25581 | E62: =$C$52+D62 -> 575.08291 | F62: =E62*12/GERACAO!$I$17*1.1 -> 6.0043348 | G62: =$C$53+D62 -> 690.89591 | H62: =G62*12/GERACAO!$I$17*1.1 -> 7.2135171
B63: 1500 | C63: =B63/30.4 -> 49.342105 | D63: =B63*$C$55 -> 279.06977 | E63: =$C$52+D63 -> 630.89686 | F63: =E63*12/GERACAO!$I$17*1.1 -> 6.5870781 | G63: =$C$53+D63 -> 746.70986 | H63: =G63*12/GERACAO!$I$17*1.1 -> 7.7962603
B65: CASO A (coluna E): o degrau de maio/26 JA e o carregamento do carro. Entao a residencia pura consome 352 kWh/mes
B66: e o total futuro e 352 + o carro na quilometragem que voce realmente rodar. NAO some o degrau duas vezes.
B67: CASO B (coluna G): o degrau foi outra carga (ar-condicionado, mais gente em casa) e o carro ainda vai entrar.
B68: Entao a base e o consumo atual de 468 kWh/mes e o carro soma por cima.
B70: A linha de 600 km/mes e a que corresponde ao degrau medido na conta. Se for esse o seu caso e o carro ja carrega,
B71: voce precisa de cerca de 4,9 kWp - e nao dos 6,2 a 6,8 kWp que os orcamentos estao oferecendo.
B72: Isso vale de 2 a 3 placas de diferenca, ou algo entre R$ 3 mil e R$ 5 mil.
B74: COMO RESOLVER SEM ADIVINHAR: o app do BYD mostra a quilometragem rodada e o consumo em modo eletrico.
B75: Olhe o total de km do mes e quanto rodou em eletrico. Com esse numero a coluna certa desta tabela aparece sozinha.
B78: 7) LIMITE FISICO DA BATERIA - DA PARA RODAR 80 km/dia SO NO ELETRICO?
B79: Bateria nominal do Song Pro DM-i | C79: =ENTRADAS!C41 -> 12.9 | D79: kWh | H79: ESTIMATIVA a confirmar no manual
B80: Reserva mantida para o modo hibrido | C80: =ENTRADAS!C49 -> 0.25 | H80: O DM-i nao esvazia a bateria - guarda reserva para rodar como hibrido
B81: Energia UTIL por carga (na bateria) | C81: =C79*(1-C80) -> 9.675 | D81: kWh | H81: E o que sobra para rodar em modo eletrico
B82: Energia da REDE por carga completa | C82: =IFERROR(C81/ENTRADAS!C45,0) -> 11.25 | D82: kWh | H82: Inclui as perdas de carregamento
B83: KM COBERTOS POR UMA CARGA | C83: =IFERROR(C81/(ENTRADAS!C42/100),0) -> 60.46875 | D83: km | H83: Autonomia eletrica real por carga
B84: km/dia que voce roda | C84: =ENTRADAS!C43 -> 80 | D84: km/dia | H84: Informado: 80 km/dia
B85: CARGAS NECESSARIAS POR DIA | C85: =IFERROR(C84/C83,0) -> 1.3229974 | D85: cargas/dia | H85: Acima de 1 significa que uma carga em casa NAO cobre o dia
B86: km/dia que ficam na GASOLINA com uma carga so | C86: =MAX(0,C84-C83) -> 19.53125 | D86: km/dia | H86: Energia que o sistema solar NAO substitui
B87: Tempo total de carga por dia no carregador de 3,3 kW | C87: =IFERROR(C84*ENTRADAS!C42/100/ENTRADAS!C45/ENTRADAS!C46,0) -> 4.5102185 | D87: horas/dia | H87: Somando as duas sessoes. Nao e o gargalo - o gargalo e o carro estar plugado duas vezes
C88: =IF(C85>1,"NAO COBRE COM UMA CARGA - sao necessarias "&TEXT(C85,"0.0")&" cargas por dia para rodar tudo no eletrico","Uma carga por dia cobre a quilometragem") -> NAO COBRE COM UMA CARGA - sao necessarias 1.3 cargas por dia para rodar tudo no eletrico
B90: 8) ESTRATEGIAS DE CARREGAMENTO E O SISTEMA QUE CADA UMA EXIGE
B91: Estrategia de carregamento | C91: kWh/dia da rede | D91: kWh/mes da rede | E91: Consumo TOTAL (base 352 + carro) | F91: kWp necessario (+10%) | G91: Modulos de 650 W
B92: 1 - Uma carga por dia em casa (limite da bateria) | C92: =C82 -> 11.25 | D92: =C92*ENTRADAS!C44 -> 337.5 | E92: =ENTRADAS!C52+D92 -> 689.32709 | F92: =IFERROR(E92*12/GERACAO!$I$17*1.1,0) -> 7.1971374 | G92: =IFERROR(ROUNDUP(F92*1000/650,0),0) -> 12 | H92: cobre ~60 dos 80 km; o resto na gasolina
B93: 2 - DUAS cargas por dia: 80 km TODO ELETRICO | C93: =ENTRADAS!C43*ENTRADAS!C42/100/ENTRADAS!C45 -> 14.883721 | D93: =C93*ENTRADAS!C44 -> 446.51163 | E93: =ENTRADAS!C52+D93 -> 798.33872 | F93: =IFERROR(E93*12/GERACAO!$I$17*1.1,0) -> 8.3353077 | G93: =IFERROR(ROUNDUP(F93*1000/650,0),0) -> 13 | H93: E O SEU OBJETIVO. Exige o carro plugado duas vezes ao dia
B94: 3 - Carga parcial de hoje (o degrau da conta) | C94: =IFERROR(CONTA!C80/ENTRADAS!C44,0) -> 3.8604335 | D94: =C94*ENTRADAS!C44 -> 115.813 | E94: =ENTRADAS!C52+D94 -> 467.6401 | F94: =IFERROR(E94*12/GERACAO!$I$17*1.1,0) -> 4.8825442 | G94: =IFERROR(ROUNDUP(F94*1000/650,0),0) -> 8 | H94: E o que a conta mostra acontecendo hoje: so ~19 km/dia de carga
B95: 4 - SEU PADRAO REAL: 1 carga/dia repondo 50%, 30 dias | C95: =C13/ENTRADAS!C44 -> 7.5 | D95: =C95*ENTRADAS!C44 -> 225 | E95: =ENTRADAS!C52+D95 -> 576.82709 | F95: =IFERROR(E95*12/GERACAO!$I$17*1.1,0) -> 6.0225456 | G95: =IFERROR(ROUNDUP(F95*1000/650,0),0) -> 10 | H95: E O CENARIO ADOTADO NA PLANILHA. Cobre ~40 dos 80 km/dia; o resto vai na gasolina
B96: O ACHADO MAIS IMPORTANTE DESTE BLOCO:
B97: O Song Pro DM-i tem bateria de 12,9 kWh. Descontando a reserva que o carro guarda para operar como hibrido,
B98: sobram cerca de 9,7 kWh uteis por carga, o que rende aproximadamente 60 km de autonomia eletrica.
B99: Voce roda 80 km/dia. Portanto UMA carga em casa NAO cobre o seu dia - faltam uns 20 km, que vao na gasolina.
B101: Para rodar TUDO no eletrico voce precisa de DUAS sessoes de carga por dia. Isso significa uma destas rotinas:
B102: (a) carregar de madrugada e novamente quando voltar para casa no meio do dia; ou
B103: (b) carregar em casa e uma segunda vez no trabalho ou em eletroposto.
B104: O tempo nao e o problema: 4,5 h somadas no carregador de 3,3 kW. O problema e o carro estar plugado duas vezes.
B105: SE A SUA ROTINA E SAIR E SO VOLTAR NO FIM DO DIA, os 80 km todo eletrico NAO sao possiveis carregando so em casa,
B106: por mais placas que voce instale. Nesse caso o cenario realista e a Estrategia 1, com ~20 km/dia na gasolina.
B108: CONSEQUENCIA PARA O DIMENSIONAMENTO: a Estrategia 2 exige de 12 a 13 modulos de 650 W (cerca de 7,7 a 8,5 kWp).
B109: TODOS os dez orcamentos da planilha estao subdimensionados para esse objetivo - o maior deles tem 7,38 kWp.
... B120: 9) ELETRICO x GASOLINA - VALE A PENA CARREGAR DUAS VEZES POR DIA?
B121: Km rodados por mes | C121: =C5*C8 -> 2400 | D121: km/mes | H121: 80 km/dia x 30 dias
B122: Km rodados em modo ELETRICO por mes | C122: =IFERROR(C9/(C6/100),0) -> 1209.375 | D122: km/mes | H122: Limitado pela energia reposta nas cargas
B123: Km rodados na GASOLINA por mes | C123: =MAX(0,C121-C122) -> 1190.625 | D123: km/mes | H123: O que a bateria nao cobriu
B124: Percentual do trajeto em modo eletrico | C124: =IFERROR(C122/C121,0) -> 0.50390625 | H124: Com uma carga de 50% por dia fica em torno da metade
B125: Litros de gasolina por mes | C125: =IFERROR(C123/ENTRADAS!C61,0) -> 74.414062 | D125: litros | H125: ESTIMATIVA: 16 km/l em modo hibrido
B126: CUSTO MENSAL DE GASOLINA | C126: =C125*ENTRADAS!C62 -> 461.36719 | D126: R$/mes | H126: ESTIMATIVA. Este custo o sistema solar NAO reduz
B128: Energia da rede se carregasse 2x/dia (tudo eletrico) | C128: =C121*C6/100/ENTRADAS!C45 -> 446.51163 | D128: kWh/mes | H128: Cobre os 2.400 km no eletrico
...

Sheet DIMENSIONAMENTO
A1: DIMENSIONAMENTO CORRETO - QUANTO VOCE REALMENTE PRECISA
A2: Calculado a partir do consumo projetado, da irradiacao local, das perdas do sistema e da margem tecnica. Nao por regra de bolo.
B4: A) MEMORIA DE CALCULO
B5: Geracao anual por kWp no seu telhado SE | C5: =GERACAO!I17 -> 1264.269 | D5: kWh por kWp por ano
B6: Geracao mensal por kWp no seu telhado SE | C6: =C5/12 -> 105.35575 | D6: kWh por kWp por mes
B7: Formula usada | C7: ="kWp necessario = consumo anual / "&TEXT(C5,"0")&" kWh por kWp" -> kWp necessario = consumo anual / 1264 kWh por kWp
B9: B) kWp NECESSARIO EM CADA CENARIO
B10: Cenario | C10: Consumo (kWh/mes) | D10: Consumo (kWh/ano) | E10: kWp necessario | F10: Modulos de 615 W
B11: 1 - Atual (so residencia) | C11: =BYD!F33 -> 351.82709 | D11: =C11*12 -> 4221.9251 | E11: =IFERROR(D11/$C$5,0) -> 3.33942 | F11: =IFERROR(ROUNDUP(E11*1000/615,0),0) -> 6
B12: 2 - Residencia + BYD | C12: =BYD!F34 -> 576.82709 | D12: =C12*12 -> 6921.9251 | E12: =IFERROR(D12/$C$5,0) -> 5.4750414 | F12: =IFERROR(ROUNDUP(E12*1000/615,0),0) -> 9
B13: 3 - Residencia + BYD + crescimento | C13: =BYD!F35 -> 663.35116 | D13: =C13*12 -> 7960.2139 | E13: =IFERROR(D13/$C$5,0) -> 6.2962976 | F13: =IFERROR(ROUNDUP(E13*1000/615,0),0) -> 11
B15: C) AS TRES OPCOES DE PROJETO (com modulos de 615 W)
C16: OPCAO A - ECONOMICO | D16: OPCAO B - IDEAL | E16: OPCAO C - COM EXPANSAO
B17: Meta de atendimento | C17: ="100% do Cenario 2" -> 100% do Cenario 2 | D17: ="105% do Cenario 3" -> 105% do Cenario 3 | E17: ="Cenario 3 + folga para dobrar a km do carro" -> Cenario 3 + folga para dobrar a km do carro
B18: kWp alvo | C18: =E12 -> 5.4750414 | D18: =E13*1.05 -> 6.6111125 | E18: =E13*1.25 -> 7.870372
B19: Quantidade de modulos de 615 W | C19: =ROUNDUP(C18*1000/615,0) -> 9 | D19: =ROUNDUP(D18*1000/615,0) -> 11 | E19: =ROUNDUP(E18*1000/615,0) -> 13
B20: Potencia instalada real (kWp) | C20: =C19*615/1000 -> 5.535 | D20: =D19*615/1000 -> 6.765 | E20: =E19*615/1000 -> 7.995
B21: Inversor recomendado (kW) | C21: =5 -> 5 | D21: =6 -> 6 | E21: =7.5 -> 7.5
B22: Relacao DC/AC | C22: =IFERROR(C20/C21,0) -> 1.107 | D22: =IFERROR(D20/D21,0) -> 1.1275 | E22: =IFERROR(E20/E21,0) -> 1.066
B23: Geracao anual estimada (kWh) | C23: =C20*$C$5 -> 6997.7289 | D23: =D20*$C$5 -> 8552.7798 | E23: =E20*$C$5 -> 10107.831
B24: Geracao media mensal (kWh) | C24: =C23/12 -> 583.14407 | D24: =D23/12 -> 712.73165 | E24: =E23/12 -> 842.31922
B25: % do Cenario 2 atendido | C25: =IFERROR(C23/$D$12,0) -> 1.0109513 | D25: =IFERROR(D23/$D$12,0) -> 1.2356071 | E25: =IFERROR(E23/$D$12,0) -> 1.4602629
B26: % do Cenario 3 atendido | C26: =IFERROR(C23/$D$13,0) -> 0.87908805 | D26: =IFERROR(D23/$D$13,0) -> 1.0744409 | E26: =IFERROR(E23/$D$13,0) -> 1.2697938
B27: Excedente anual desperdicado (kWh) | C27: =MAX(0,C23-$D$13) -> 0 | D27: =MAX(0,D23-$D$13) -> 592.56587 | E27: =MAX(0,E23-$D$13) -> 2147.6167
B30: D) RECOMENDACAO DE DIMENSIONAMENTO
B31: A OPCAO B e a recomendada. Motivos tecnicos:
B32: 1. Ela atende o Cenario 3, que e o unico realista: residencia + carro + margem. A Opcao A cobre o carro de hoje mas
B33: nao sobra nada para o crescimento que a propria conta ja mostra (+22% em 6 meses).
B34: 2. Ela nao joga dinheiro fora. Passar do Cenario 3 gera excedente que vira credito e expira em 60 meses - a linha 27
B35: mostra esse desperdicio. Cada kWh gerado acima do consumo tem retorno praticamente zero.
B36: 3. O inversor de 6 kW da Opcao B ainda aceita cerca de 8,1 kWp (limite DC/AC de 1,35), ou seja, permite acrescentar
B37: modulos depois sem trocar o inversor e sem refazer a homologacao. Isso e a expansao futura barata.
B38: 4. A Opcao C so se justifica se voce souber HOJE que a quilometragem do carro vai crescer muito, ou se pretende
B39: instalar ar-condicionado, piscina aquecida ou um segundo veiculo eletrico.
B41: ATENCAO: os numeros acima dependem de km/dia do BYD, que ainda e ESTIMATIVA. Se voce rodar 20 km/dia em vez de 40,
B42: o kWp necessario cai cerca de 1,3 kWp (2 modulos). Se rodar 60 km/dia, sobe cerca de 1,3 kWp. Informe a km real.

Sheet COMPARATIVO
A1: COMPARATIVO DOS ORCAMENTOS - QUADRO PRINCIPAL
A2: Contatos nas linhas 5 a 7. Colunas A e B: TecSolarSP, preco de MATERIAL. As demais: preco INSTALADO. A linha do PRECO TOTAL INSTALADO e a unica comparavel entre todos.
B4: ITEM | C4: A) TecSolarSP JA Solar 615W Huawei 6 kW | D4: B) TecSolarSP Astronergy 605W Huawei 6 kW | E4: C) SunWash TCL 620W AUXSOL 5 kW | F4: D) SunWash TCL 620W HUAWEI 5 kW | G4: E) William Maxeon 535W Solis 4 kW | H4: F) Sun Coast v1 RONMA 585W AUXSOL 3 kW (SUPERADA) | I4: G) SunWash MICRO 10x650W 4x 2,25 kW | J4: H) Sfero (Renato) Longi/DAH 590W 2x micro 2,5 kW | K4: I) Sun Coast v2 TCL 620W x11 AUXSOL 7,5 kW | L4: J) AD BioSolar JA Solar 615W x10 Huawei SUN2000-6KTL-L1 | M4: SIMULACAO G12 MICRO 12x650W 4x Deye 2,25 kW | N4: SIMULACAO G14 MICRO 14x650W 4x Deye 2,25 kW | O4: M) Bruno G4 (a receber) | P4: OBSERVACOES / ALERTAS
B5: EMPRESA / razao social | C5: TecSolarSP | D5: TecSolarSP | E5: SunWash Energia Solar e Ar-Condicionado | F5: SunWash Energia Solar e Ar-Condicionado | G5: nao informada na proposta | H5: Sun Coast Materiais Eletricos e Energia Solar | I5: SunWash Energia Solar e Ar-Condicionado | J5: Sfero | K5: Sun Coast Materiais Eletricos e Energia Solar | L5: AD BioSolar | M5: SunWash - SIMULACAO, preco a confirmar | N5: SunWash - SIMULACAO, preco a confirmar | O5: G4 (razao social a confirmar) | P5: ALERTA: SunWash, William e Sfero nao informaram razao social. Sem empresa identificada nao existe garantia exigivel.
B6: NOME DO RESPONSAVEL | C6: nao informado (razao social: Edijane Gomes dos Santos) | D6: nao informado (razao social: Edijane Gomes dos Santos) | E6: Yuri | F6: Yuri | G6: William | H6: Alexandre | I6: Yuri | J6: nao informado (indicacao do Renato) | K6: Alexandre | L6: Adriano Melo (proposta) / Carlos (negociacao) | M6: Yuri | N6: Yuri | O6: Bruno | P6: Quem falou com voce. Peca sempre que a proposta saia com nome e CNPJ da empresa, nao apenas o contato pessoal.
B7: TELEFONE DE CONTATO | C7: (11) 97365-9192 | D7: (11) 97365-9192 | E7: (16) 99353-4346 | F7: (16) 99353-4346 | G7: (11) 99636-5333 | H7: (11) 91544-8947 | I7: (16) 99353-4346 | J7: (11) 99705-1311 (Renato) | K7: (11) 91544-8947 | L7: (11) 97350-3103 / Carlos (11) 91408-8892 | M7: (16) 99353-4346 | N7: (16) 99353-4346 | O7: (11) 96861-7830 | P7: A Sfero chegou por indicacao do Renato - o telefone e dele, nao da empresa. Pedir o contato direto da Sfero.
B8: CNPJ informado na proposta | C8: 29.775.600/0001-03 | D8: 29.775.600/0001-03 | E8: NAO INFORMADO | F8: NAO INFORMADO | G8: NAO INFORMADO | H8: 47.864.839/0001-31 | I8: NAO INFORMADO | J8: NAO INFORMADO na proposta | K8: 47.864.839/0001-31 | L8: 64.313.573/0001-58 | M8: NAO INFORMADO | N8: NAO INFORMADO | P8: ALERTA: so Sun Coast, AD BioSolar e TecSolarSP (via cotacao do distribuidor) tem CNPJ identificado.
B9: Documento recebido | C9: Cotacao Belenergy WEB-006506779 | D9: Cotacao Belenergy WEB-006512519 | E9: WhatsApp 10/08/2026 | F9: WhatsApp 10/08/2026 | G9: Proposta tecnica de 7 paginas | H9: Proposta 40436 de 11/08/2026 (val. 20/08) | I9: WhatsApp 10/08/2026 17:45 | J9: Proposta 0664/2026 de 11/08/2026 (val. 10 dias) | K9: Proposta 40438 de 11/08/2026 (val. 20/08) | L9: Proposta #01237 de 12/08/2026 (val. 27/08) - substitui a #01225 | M9: SIMULACAO: opcao G escalada para 12 modulos | N9: SIMULACAO: opcao G escalada para 14 modulos | O9: Nada recebido | P9: ALERTA: orcamento por WhatsApp nao e proposta comercial. Sfero, Sun Coast, AD BioSolar e William entregaram documento formal.
B10: TIPO DE PRECO | C10: MATERIAL apenas | D10: MATERIAL apenas | E10: INSTALADO (turnkey) | F10: INSTALADO (turnkey) | G10: INSTALADO (turnkey) | H10: INSTALADO (turnkey) | I10: INSTALADO (turnkey) | J10: INSTALADO (turnkey) | K10: INSTALADO (turnkey) | L10: INSTALADO (turnkey) | M10: INSTALADO (turnkey) | N10: INSTALADO (turnkey) | O10: ? | P10: ALERTA: comparar MATERIAL com INSTALADO e o erro mais comum. As linhas de homologacao e instalacao corrigem isso.
B11: Quantidade de modulos | C11: 12 | D11: 12 | E11: 10 | F11: 10 | G11: 10 | H11: 8 | I11: 10 | J11: 10 | K11: 11 | L11: 10 | M11: 12 | N11: 14 | P11: Informada por cada fornecedor.
B12: Potencia por modulo (W) | C12: 615 | D12: 605 | E12: 620 | F12: 620 | G12: 535 | H12: 585 | I12: 650 | J12: 590 | K12: 620 | L12: 615 | M12: 650 | N12: 650 | P12: A SunWash escreveu '620kw' e '650w' - erro de digitacao para watts.
B13: Fabricante / tecnologia do modulo | C13: JA Solar bifacial N-type | D13: Astronergy bifacial N-type | E13: TCL 620 W (tecnologia a confirmar) | F13: TCL 620 W (tecnologia a confirmar) | G13: Maxeon bifacial PERC | H13: RONMA SOLAR bifacial N-type 144 cel | I13: ZNShine ZXNR-MD132-650 N-type (Tier 1 BNEF) | J13: Longi ou DAH Solar (Tier 1 de verdade) | K13: TCL Solar bifacial N-type 132 cel | L13: JA Solar bifacial N-type 132 cel - TIER 1 | M13: ZNShine ZXNR-MD132-650 N-type (Tier 1 BNEF) | N13: ZNShine ZXNR-MD132-650 N-type (Tier 1 BNEF) | P13: ALERTA: Maxeon do William e PERC, uma geracao atras. TCL e RONMA tem pouquissima rede de assistencia no Brasil. JA Solar, Longi e DAH sao Tier 1 com representacao aqui.
B14: POTENCIA DC (kWp) | C14: =C11*C12/1000 -> 7.38 | D14: =D11*D12/1000 -> 7.26 | E14: =E11*E12/1000 -> 6.2 | F14: =F11*F12/1000 -> 6.2 | G14: =G11*G12/1000 -> 5.35 | H14: =H11*H12/1000 -> 4.68 | I14: =I11*I12/1000 -> 6.5 | J14: =J11*J12/1000 -> 5.9 | ... N14: =N11*N12/1000 -> 9.1 | P14: Quantidade x potencia do modulo / 1000.
B15: Inversor | C15: Huawei 6 kW mono 220V 2 MPPT | D15: Huawei 6 kW mono 220V 2 MPPT | E15: AUXSOL 5 kW (modelo nao informado) | F15: HUAWEI 5 kW (modelo nao informado) | G15: Solis 4 kW mono 220V 2 MPPT | H15: AUXSOL 3 kW mono 220V 1 MPPT | I15: 4x DEYE SUN-S225G4-EU-Q0 2,25 kW = 9,0 kW AC | J15: 2x microinversor 2,5 kW = 5,0 kW AC - Solis ou Growatt | K15: AUXSOL 7,5 kW mono 220V 2 MPPT (100% over) | L15: HUAWEI SUN2000-6KTL-L1 6.000 W (modelo EXATO informado) | M15: 4x DEYE SUN-S225G4-EU-Q0 = 9,0 kW AC (12 dos 16 canais) | N15: 4x DEYE SUN-S225G4-EU-Q0 = 9,0 kW AC (14 dos 16 canais) | P15: ALERTA: AUXSOL tem baixa penetracao no Brasil. Huawei, Solis e Growatt tem assistencia estabelecida. So a AD BioSolar informou o MODELO EXATO.
B16: Potencia AC do inversor (kW) | C16: 6 | D16: 6 | E16: 5 | F16: 5 | G16: 4 | H16: 3 | I16: 9 | J16: 5 | K16: 7.5 | L16: 6 | M16: 9 | N16: 9 | P16: Exigir o codigo exato do modelo, como fez a AD BioSolar (SUN2000-5KTL-L1).
B17: Numero de MPPTs | C17: 2 | D17: 2 | E17: a confirmar | F17: a confirmar | G17: 2 | H17: 1 | I17: 4 por micro = 16 canais (10 usados, 6 livres) | J17: 1 por modulo (10 MPPTs) | K17: 2 | L17: 2 (a confirmar) | M17: 4 por micro = 16 canais (12 usados, 4 livres) | N17: 4 por micro = 16 canais (14 usados, 2 livres) | P17: ALERTA: Sun Coast v1 usava 1 MPPT UNICO para 8 modulos. As opcoes com microinversor dao 1 MPPT POR MODULO: sombra em um modulo nao afeta os outros e permite usar mais de uma agua do telhado.
B18: RELACAO DC/AC | C18: =IFERROR(C14/C16,0) -> 1.23 | D18: =IFERROR(D14/D16,0) -> 1.21 | E18: =IFERROR(E14/E16,0) -> 1.24 | F18: =IFERROR(F14/F16,0) -> 1.24 | G18: =IFERROR(G14/G16,0) -> 1.3375 | H18: =IFERROR(H14/H16,0) -> 1.56 | I18: =IFERROR(I14/I16,0) -> 0.72222222 | J18: =IFERROR(J14/J16,0) -> 1.18 | ... N18: =IFERROR(N14/N16,0) -> 1.0111111 | P18: ALERTA: faixa saudavel de 1,10 a 1,35. Sun Coast v1 em 1,56 = clipping e risco de perder garantia. Abaixo de 1,10 voce pagou por inversor que nao vai usar - aceitavel se for folga proposital para expansao.
B19: Tensao de operacao | C19: 220 V (2 fases) | D19: 220 V (2 fases) | E19: 220 V (a confirmar) | F19: 220 V (a confirmar) | G19: 220 V (2 fases) | H19: 220 V (2 fases) | I19: 220 V (a confirmar) | J19: 220 V (a confirmar) | K19: 220 V (2 fases) | L19: 220 V (2 fases) | M19: 220 V (a confirmar) | N19: 220 V (a confirmar) | P19: ALERTA MAIOR: sua ligacao e MONOFASICA (127 V na Enel SP). TODOS exigem mudanca para bifasico.
B20: Tipo de telha que o orcamento considerou | C20: Fibrocimento | D20: Fibrocimento | E20: nao informada | F20: nao informada | G20: Colonial | H20: Colonial | I20: nao informada | J20: Ceramico / colonial | K20: Colonial | L20: nao informada | M20: nao informada | N20: nao informada | P20: ALERTA: William, Sun Coast e Sfero dizem CERAMICA/COLONIAL; a TecSolarSP diz FIBROCIMENTO. Tres contra um. Se for ceramica, a estrutura das duas cotacoes da TecSolarSP esta errada. Uma foto resolve.
B21: Area de telhado necessaria (m2) | C21: =C11*C12*0.00452 -> 33.3576 | D21: =D11*D12*0.00452 -> 32.8152 | E21: =E11*E12*0.00452 -> 28.024 | F21: =F11*F12*0.00452 -> 28.024 | G21: =G11*G12*0.00452 -> 24.182 | H21: 21.12 | I21: =I11*I12*0.00452 -> 29.38 | J21: 28 | K21: 30.58 | L21: 32.41 | M21: =M11*M12*0.00452 -> 35.256 | N21: =N11*N12*0.00452 -> 41.132 | P21: Valores em azul foram DECLARADOS pelo fornecedor; os demais estimados a 0,00452 m2 por watt. Sem fotos do telhado NAO foi verificado se essa area existe na agua Sudeste.
B22: Garantia declarada do modulo | C22: nao informada | D22: nao informada | E22: nao informada | F22: nao informada | G22: nao informada | H22: 25 anos eficiencia / 15 anos defeito | I22: nao declarada pelo vendedor - exigir por escrito (N-type costuma dar 12/25 a 30 anos) | J22: 12 anos produto / 25 anos eficiencia | K22: 25 anos eficiencia / 15 anos defeito | L22: 15 anos defeito / 30 anos eficiencia | M22: exigir por escrito | N22: exigir por escrito | P22: AD BioSolar tem a melhor: 30 anos de eficiencia e 15 de defeito. TecSolarSP, SunWash e William nao declararam nada.
B23: Garantia declarada do inversor | C23: nao informada | D23: nao informada | E23: nao informada | F23: nao informada | G23: nao informada | H23: 10 a 25 anos | I23: nao declarada pelo vendedor - a Deye pratica 10 anos, exigir por escrito | J23: 7 a 10 anos | K23: 10 a 25 anos | L23: 10 anos | M23: exigir por escrito (Deye pratica 10 anos) | N23: exigir por escrito (Deye pratica 10 anos) | P23: AD BioSolar declara 10 anos para um modelo Huawei nomeado - e a unica verificavel. '10 a 25 anos' da Sun Coast e vago.
B24: Garantia de servico / seguro | C24: nao informada | D24: nao informada | E24: nao informada | F24: nao informada | G24: nao informada | H24: 12 meses | I24: nao informada | J24: 1 ano instalacao + SEGURO ALL RISK 1 ano + GARANTIA DE PERFORMANCE EM CONTRATO | K24: 12 meses | L24: vistoria tecnica, ART, licencas, gestao de obra e frete inclusos | M24: exigir por escrito | N24: exigir por escrito | P24: So a Sfero oferece seguro All Risk e garantia de performance em contrato. Isso vale dinheiro em risco.
B25: Exclusoes declaradas na proposta | C25: nao informadas | D25: nao informadas | E25: nao informadas | F25: nao informadas | G25: nao informadas | H25: padrao de entrada, obras civis, telhado, eletrodutos, ART estrutural | I25: nao informadas | J25: obras civis, reformas no telhado/laje e no PADRAO DE ENTRADA | K25: padrao de entrada, obras civis, telhado, eletrodutos, ART estrutural | L25: alvenaria, reforco estrutural e alteracoes na rede pedidas pela concessionaria | M25: exigir por escrito | N25: exigir por escrito | P25: ALERTA: Sun Coast, Sfero e AD BioSolar excluem por escrito a adequacao do padrao. E honesto declarar, mas o custo e seu. Quem nao declarou exclusao tambem nao incluiu - so nao avisou.
B26: Condicao de pagamento declarada | C26: PIX (cotacao de material) | D26: PIX (cotacao de material) | E26: a vista ou 21x COM juros | F26: a vista ou 21x COM juros | G26: PIX no kit; restante nao informado | H26: a vista, cartao 12x/21x COM juros ou financiamento 36x | I26: 18x de R$ 932,25 SEM JUROS (= preco a vista) | J26: 3x: 60% entrada / 20% montado / 20% ligado; ou Santander 60x R$ 553 ou 72x R$ 507 | K26: a vista, cartao 12x/21x COM juros ou financiamento 36x ate 120x | L26: R$ 16.200 NEGOCIADO (o PDF traz R$ 21.289 - EXIGIR O DESCONTO POR ESCRITO) | M26: pedir preco e parcelamento para esta configuracao | N26: pedir preco e parcelamento para esta configuracao | P26: ATENCAO: 18x SEM JUROS pelo valor a vista (SunWash micro) e vantagem real. Ja o financiamento Sfero em 72x custa cerca de R$ 17,8 mil de juros sobre R$ 18,7 mil - quase dobra o preco.
B28: PRECOS
B29: Preco BASE informado (R$) | C29: 18228.7 | D29: 17307.9 | E29: 14220.34 | F29: 15220.34 | G29: 11158.91 | H29: 12387.64 | I29: 16780.54 | J29: 18733 | K29: 16890 | L29: 16200 | M29: =I29+2*ENTRADAS!$C$54 -> 18580.54 | N29: =I29+4*ENTRADAS!$C$54 -> 20380.54 | P29: A, B e E: valor do KIT/material. As demais: projeto completo, ja com instalacao. ALERTA na coluna J: o PDF da AD BioSolar traz R$ 21.289,00 e o valor de R$ 16.200,00 foi negociado verbalmente - um desconto de R$ 5.089 (24%) que PRECISA constar em proposta assinada, senao pode evaporar na hora de fechar.
B30: Acrescimo regional a confirmar (R$) | C30: 0 | D30: 0 | E30: 1800 | F30: 1800 | G30: 0 | H30: 0 | I30: 1800 | J30: 0 | K30: 0 | L30: 0 | M30: 1800 | N30: 1800 | P30: ALERTA: a SunWash citou +R$ 1.800 pela sua regiao no kit Intelbras e nao repetiu nos demais. Mantido por PRUDENCIA. Se nao incidir, zere e o payback melhora.
B31: Homologacao / engenharia / ART (R$) | C31: 790 | D31: 790 | E31: 0 | F31: 0 | G31: 790 | H31: 0 | I31: 0 | J31: 0 | K31: 0 | L31: 0 | M31: 0 | N31: 0 | P31: E: R$ 790 declarado pelo William. A e B: mesmo valor como ESTIMATIVA - a TecSolarSP nunca informou o preco de venda.
B32: Instalacao / mao de obra (R$) | C32: =6900/10*C11 -> 8280 | D32: =6900/10*D11 -> 8280 | E32: 0 | F32: 0 | G32: 6900 | H32: 0 | I32: 0 | J32: 0 | K32: 0 | L32: 0 | M32: 0 | N32: 0 | P32: ALERTA: E = R$ 6.900 declarado pelo William para 10 modulos. A e B usam esse valor escalado por modulo, como ESTIMATIVA.
B33: Adequacao do padrao mono -> bifasico (R$) | C33: =ENTRADAS!$C$28 -> 2500 | D33: =ENTRADAS!$C$28 -> 2500 | E33: =ENTRADAS!$C$28 -> 2500 | F33: =ENTRADAS!$C$28 -> 2500 | G33: =ENTRADAS!$C$28 -> 2500 | H33: =ENTRADAS!$C$28 -> 2500 | I33: =ENTRADAS!$C$28 -> 2500 | J33: =ENTRADAS!$C$28 -> 2500 | ... N33: =ENTRADAS!$C$28 -> 2500 | P33: ALERTA: NENHUM dos orcamentos incluiu. Necessario para qualquer inversor de 220 V. Editavel em ENTRADAS!C28.
B34: PRECO TOTAL INSTALADO (R$) | C34: =SUM(C29:C33) -> 29798.7 | D34: =SUM(D29:D33) -> 28877.9 | E34: =SUM(E29:E33) -> 18520.34 | F34: =SUM(F29:F33) -> 19520.34 | G34: =SUM(G29:G33) -> 21348.91 | H34: =SUM(H29:H33) -> 14887.64 | I34: =SUM(I29:I33) -> 21080.54 | J34: =SUM(J29:J33) -> 21233 | ... N34: =SUM(N29:N33) -> 24680.54 | P34: O UNICO numero comparavel entre fornecedores.
B35: R$ por Wp instalado | C35: =IFERROR(C34/(C14*1000),0) -> 4.0377642 | D35: =IFERROR(D34/(D14*1000),0) -> 3.9776722 | E35: =IFERROR(E34/(E14*1000),0) -> 2.9871516 | F35: =IFERROR(F34/(F14*1000),0) -> 3.1484419 | G35: =IFERROR(G34/(G14*1000),0) -> 3.9904505 | H35: =IFERROR(H34/(H14*1000),0) -> 3.1811197 | I35: =IFERROR(I34/(I14*1000),0) -> 3.24316 | J35: =IFERROR(J34/(J14*1000),0) -> 3.5988136 | ... N35: =IFERROR(N34/(N14*1000),0) -> 2.7121473 | P35: Metrica de mercado, valida so entre precos de mesmo escopo.
B36: R$ por Wp somente de material | C36: =IFERROR(C29/(C14*1000),0) -> 2.4700136 | D36: =IFERROR(D29/(D14*1000),0) -> 2.3840083 | E36: n/d | F36: n/d | G36: =IFERROR(G29/(G14*1000),0) -> 2.0857776 | H36: n/d | I36: n/d | J36: n/d | K36: n/d | L36: n/d | M36: n/d | N36: n/d | P36: Mede a margem. A TecSolarSP paga R$ 2,47/Wp de material: use isso para negociar o preco de venda dela.
B38: GERACAO - REALIDADE x PROMESSA
B39: Geracao anual realista - telhado SE (kWh) | C39: =C14*GERACAO!$I$17 -> 9330.3052 | D39: =D14*GERACAO!$I$17 -> 9178.5929 | E39: =E14*GERACAO!$I$17 -> 7838.4678 | F39: =F14*GERACAO!$I$17 -> 7838.4678 | G39: =G14*GERACAO!$I$17 -> 6763.8391 | H39: =H14*GERACAO!$I$17 -> 5916.7789 | I39: =I14*GERACAO!$I$17 -> 8217.7485 | J39: =J14*GERACAO!$I$17 -> 7459.1871 | ... N39: =N14*GERACAO!$I$17 -> 11504.848 | P39: Irradiacao de Sao Paulo, telhado Sudeste 20 graus, PR de 79%.
B40: Geracao media mensal realista (kWh/mes) | C40: =C39/12 -> 777.52543 | D40: =D39/12 -> 764.88274 | E40: =E39/12 -> 653.20565 | F40: =F39/12 -> 653.20565 | G40: =G39/12 -> 563.65326 | H40: =H39/12 -> 493.06491 | I40: =I39/12 -> 684.81237 | J40: =J39/12 -> 621.59892 | ... N40: =N39/12 -> 958.73732
B41: Geracao no cenario CONSERVADOR (PR 72%) | C41: =C39/ENTRADAS!$C$31*ENTRADAS!$C$32 -> 8503.5693 | D41: =D39/ENTRADAS!$C$31*ENTRADAS!$C$32 -> 8365.2999 | E41: =E39/ENTRADAS!$C$31*ENTRADAS!$C$32 -> 7143.92 | F41: =F39/ENTRADAS!$C$31*ENTRADAS!$C$32 -> 7143.92 | G41: =G39/ENTRADAS!$C$31*ENTRADAS!$C$32 -> 6164.5116 | H41: =H39/ENTRADAS!$C$31*ENTRADAS!$C$32 -> 5392.5073 | I41: =I39/ENTRADAS!$C$31*ENTRADAS!$C$32 -> 7489.5935 | J41: =J39/ENTRADAS!$C$31*ENTRADAS!$C$32 -> 6798.2464 | ... N41: =N39/ENTRADAS!$C$31*ENTRADAS!$C$32 -> 10485.431 | P41: Pior caso: telhado mais sujo, mais quente ou com sombra parcial.
B42: Geracao PROMETIDA pelo vendedor (kWh/ano) | C42: 10554 | D42: 0 | E42: 8400 | F42: 8400 | G42: 6151 | H42: 6367.5 | I42: 8400 | J42: 7329.96 | K42: 9279.13 | L42: 7981.26 | M42: 0 | N42: 0 | P42: A: 10.554. C, D e G: 700 kWh/mes x 12. E: 6.151. F: 6.367,50. H: 7.329,96. I: 9.279,13. J: 7.981,26. B: nao informada.
B43: DESVIO DA PROMESSA | C43: =IFERROR(C39/C42-1,0) -> -0.11594607 | D43: =IFERROR(D39/D42-1,0) -> 0 | E43: =IFERROR(E39/E42-1,0) -> -0.066849075 | F43: =IFERROR(F39/F42-1,0) -> -0.066849075 | G43: =IFERROR(G39/G42-1,0) -> 0.099632438 | H43: =IFERROR(H39/H42-1,0) -> -0.070784626 | I43: =IFERROR(I39/I42-1,0) -> -0.021696611 | J43: =IFERROR(J39/J42-1,0) -> 0.017629983 | ... N43: =IFERROR(N39/N42-1,0) -> 0 | P43: ALERTA: negativo = o vendedor promete mais do que o telhado entrega. Positivo = foi conservador. Sfero e a unica positiva.
B44: Geracao se o telhado fosse NORTE (kWh) | C44: =C14*GERACAO!$J$17 -> 10488.711 | D44: =D14*GERACAO!$J$17 -> 10318.162 | E44: =E14*GERACAO!$J$17 -> 8811.6538 | F44: =F14*GERACAO!$J$17 -> 8811.6538 | G44: =G14*GERACAO!$J$17 -> 7603.6045 | H44: =H14*GERACAO!$J$17 -> 6651.3774 | I44: =I14*GERACAO!$J$17 -> 9238.0242 | J44: =J14*GERACAO!$J$17 -> 8385.2835 | ... N44: =N14*GERACAO!$J$17 -> 12933.234 | P44: Compare com a linha da promessa: e daqui que saem os numeros otimistas.
B46: ATENDIMENTO DO CONSUMO
B47: % atendido SEM o BYD (Cenario 1) | C47: =IFERROR(C39/(BYD!$F$33*12),0) -> 2.2099646 | D47: =IFERROR(D39/(BYD!$F$33*12),0) -> 2.1740302 | E47: =IFERROR(E39/(BYD!$F$33*12),0) -> 1.8566099 | F47: =IFERROR(F39/(BYD!$F$33*12),0) -> 1.8566099 | G47: =IFERROR(G39/(BYD!$F$33*12),0) -> 1.6020746 | H47: =IFERROR(H39/(BYD!$F$33*12),0) -> 1.401441 | I47: =IFERROR(I39/(BYD!$F$33*12),0) -> 1.9464458 | J47: =IFERROR(J39/(BYD!$F$33*12),0) -> 1.7667739 | ... N47: =IFERROR(N39/(BYD!$F$33*12),0) -> 2.7250241 | P47: Todos parecem otimos aqui - e por isso que os vendedores acham que acertaram o tamanho.
B48: % atendido COM o BYD (Cenario 2) | C48: =IFERROR(C39/(BYD!$F$34*12),0) -> 1.347935 | D48: =IFERROR(D39/(BYD!$F$34*12),0) -> 1.3260174 | E48: =IFERROR(E39/(BYD!$F$34*12),0) -> 1.1324115 | F48: =IFERROR(F39/(BYD!$F$34*12),0) -> 1.1324115 | G48: =IFERROR(G39/(BYD!$F$34*12),0) -> 0.97716156 | H48: =IFERROR(H39/(BYD!$F$34*12),0) -> 0.85478805 | I48: =IFERROR(I39/(BYD!$F$34*12),0) -> 1.1872056 | J48: =IFERROR(J39/(BYD!$F$34*12),0) -> 1.0776174 | ... N48: =IFERROR(N39/(BYD!$F$34*12),0) -> 1.6620879
B49: % atendido no CENARIO 3 | C49: =IFERROR(C39/(BYD!$F$35*12),0) -> 1.1721174 | D49: =IFERROR(D39/(BYD!$F$35*12),0) -> 1.1530586 | E49: =IFERROR(E39/(BYD!$F$35*12),0) -> 0.98470567 | F49: =IFERROR(F39/(BYD!$F$35*12),0) -> 0.98470567 | G49: =IFERROR(G39/(BYD!$F$35*12),0) -> 0.8497057 | H49: =IFERROR(H39/(BYD!$F$35*12),0) -> 0.74329396 | I49: =IFERROR(I39/(BYD!$F$35*12),0) -> 1.0323527 | J49: =IFERROR(J39/(BYD!$F$35*12),0) -> 0.93705862 | ... N49: =IFERROR(N39/(BYD!$F$35*12),0) -> 1.4452938 | P49: ESTE e o criterio de dimensionamento. Alvo: 95% a 110%. Abaixo de 90% = subdimensionado.
B50: Deficit / excedente anual (kWh) | C50: =C39-BYD!$G$35 -> 1370.0913 | D50: =D39-BYD!$G$35 -> 1218.379 | E50: =E39-BYD!$G$35 -> -121.74612 | F50: =F39-BYD!$G$35 -> -121.74612 | G50: =G39-BYD!$G$35 -> -1196.3748 | H50: =H39-BYD!$G$35 -> -2043.435 | I50: =I39-BYD!$G$35 -> 257.53458 | J50: =J39-BYD!$G$35 -> -501.02681 | ... N50: =N39-BYD!$G$35 -> 3544.634 | P50: Negativo = continua comprando energia todo mes. Muito positivo = credito que expira em 60 meses.
B51: Modulos que faltam para o Cenario 3 | C51: =IFERROR(ROUNDUP(MAX(0,BYD!$G$35-C39)/GERACAO!$I$17*1000/C12,0),0) -> 0 | D51: =IFERROR(ROUNDUP(MAX(0,BYD!$G$35-D39)/GERACAO!$I$17*1000/D12,0),0) -> 0 | E51: =IFERROR(ROUNDUP(MAX(0,BYD!$G$35-E39)/GERACAO!$I$17*1000/E12,0),0) -> 1 | F51: =IFERROR(ROUNDUP(MAX(0,BYD!$G$35-F39)/GERACAO!$I$17*1000/F12,0),0) -> 1 | G51: =IFERROR(ROUNDUP(MAX(0,BYD!$G$35-G39)/GERACAO!$I$17*1000/G12,0),0) -> 2 | H51: =IFERROR(ROUNDUP(MAX(0,BYD!$G$35-H39)/GERACAO!$I$17*1000/H12,0),0) -> 3 | I51: =IFERROR(ROUNDUP(MAX(0,BYD!$G$35-I39)/GERACAO!$I$17*1000/I12,0),0) -> 0 | J51: =IFERROR(ROUNDUP(MAX(0,BYD!$G$35-J39)/GERACAO!$I$17*1000/J12,0),0) -> 1 | ... N51: =IFERROR(ROUNDUP(MAX(0,BYD!$G$35-N39)/GERACAO!$I$17*1000/N12,0),0) -> 0
B52: Modulos atribuiveis SO ao BYD | C52: =IFERROR(ROUNDUP(BYD!$C$13*12/GERACAO!$I$17*1000/C12,0),0) -> 4 | D52: =IFERROR(ROUNDUP(BYD!$C$13*12/GERACAO!$I$17*1000/D12,0),0) -> 4 | E52: =IFERROR(ROUNDUP(BYD!$C$13*12/GERACAO!$I$17*1000/E12,0),0) -> 4 | F52: =IFERROR(ROUNDUP(BYD!$C$13*12/GERACAO!$I$17*1000/F12,0),0) -> 4 | G52: =IFERROR(ROUNDUP(BYD!$C$13*12/GERACAO!$I$17*1000/G12,0),0) -> 4 | H52: =IFERROR(ROUNDUP(BYD!$C$13*12/GERACAO!$I$17*1000/H12,0),0) -> 4 | I52: =IFERROR(ROUNDUP(BYD!$C$13*12/GERACAO!$I$17*1000/I12,0),0) -> 4 | J52: =IFERROR(ROUNDUP(BYD!$C$13*12/GERACAO!$I$17*1000/J12,0),0) -> 4 | ... N52: =IFERROR(ROUNDUP(BYD!$C$13*12/GERACAO!$I$17*1000/N12,0),0) -> 4 | P52: Placas que existem no projeto apenas para compensar o carregamento do carro.
B53: Potencia AC a declarar na homologacao e corrente em 220 V | C53: =C16&" kW = "&TEXT(C16*1000/220,"0")&" A" -> 6 kW = 27 A | D53: =D16&" kW = "&TEXT(D16*1000/220,"0")&" A" -> 6 kW = 27 A | E53: =E16&" kW = "&TEXT(E16*1000/220,"0")&" A" -> 5 kW = 23 A | F53: =F16&" kW = "&TEXT(F16*1000/220,"0")&" A" -> 5 kW = 23 A | G53: =G16&" kW = "&TEXT(G16*1000/220,"0")&" A" -> 4 kW = 18 A | H53: =H16&" kW = "&TEXT(H16*1000/220,"0")&" A" -> 3 kW = 14 A | I53: =I16&" kW = "&TEXT(I16*1000/220,"0")&" A" -> 9 kW = 41 A | J53: =J16&" kW = "&TEXT(J16*1000/220,"0")&" A" -> 5 kW = 23 A | ... N53: =N16&" kW = "&TEXT(N16*1000/220,"0")&" A" -> 9 kW = 41 A | P53: ALERTA POUCO OBVIO: a potencia declarada a Enel e a do INVERSOR (AC), nao a dos modulos. Quanto maior, maior o disjuntor e o padrao exigidos - e mais caro fica o item de adequacao do padrao.
B55: RESULTADO FINANCEIRO
B56: Conta mensal HOJE (sem solar, sem BYD) | C56: =CONTA!$C$54 -> 410.62788 | D56: =CONTA!$C$54 -> 410.62788 | E56: =CONTA!$C$54 -> 410.62788 | F56: =CONTA!$C$54 -> 410.62788 | G56: =CONTA!$C$54 -> 410.62788 | H56: =CONTA!$C$54 -> 410.62788 | I56: =CONTA!$C$54 -> 410.62788 | J56: =CONTA!$C$54 -> 410.62788 | ... N56: =CONTA!$C$54 -> 410.62788 | P56: Situacao atual real: R$ 410,63.
B57: Conta mensal SEM solar mas COM o BYD | C57: =ECONOMIA!C8/12 -> 698.70331 | D57: =ECONOMIA!D8/12 -> 698.70331 | E57: =ECONOMIA!E8/12 -> 698.70331 | F57: =ECONOMIA!F8/12 -> 698.70331 | G57: =ECONOMIA!G8/12 -> 698.70331 | H57: =ECONOMIA!H8/12 -> 698.70331 | I57: =ECONOMIA!I8/12 -> 698.70331 | J57: =ECONOMIA!J8/12 -> 698.70331 | ... N57: =ECONOMIA!N8/12 -> 698.70331 | P57: O que a conta vira se o carro chegar e nao houver solar.
B58: Conta mensal COM solar e COM o BYD | C58: =ECONOMIA!C19 -> 161.14968 | D58: =ECONOMIA!D19 -> 161.14968 | E58: =ECONOMIA!E19 -> 161.8032 | F58: =ECONOMIA!F19 -> 161.8032 | G58: =ECONOMIA!G19 -> 207.6657 | H58: =ECONOMIA!H19 -> 269.16013 | I58: =ECONOMIA!I19 -> 161.14968 | J58: =ECONOMIA!J19 -> 163.83912 | ... N58: =ECONOMIA!N19 -> 161.14968 | P58: ALERTA: nao vai a zero. Sobram disponibilidade, Fio B e COSIP.
B59: Economia liquida ano 1 (R$/ano) | C59: =ECONOMIA!C26 -> 6000.6435 | D59: =ECONOMIA!D26 -> 6000.6435 | E59: =ECONOMIA!E26 -> 5992.8013 | F59: =ECONOMIA!F26 -> 5992.8013 | G59: =ECONOMIA!G26 -> 5442.4513 | H59: =ECONOMIA!H26 -> 4704.5181 | I59: =ECONOMIA!I26 -> 6000.6435 | J59: =ECONOMIA!J26 -> 5968.3702 | ... N59: =ECONOMIA!N26 -> 6000.6435
B60: Economia liquida ano 1 (R$/mes) | C60: =C59/12 -> 500.05363 | D60: =D59/12 -> 500.05363 | E60: =E59/12 -> 499.40011 | F60: =F59/12 -> 499.40011 | G60: =G59/12 -> 453.53761 | H60: =H59/12 -> 392.04318 | I60: =I59/12 -> 500.05363 | J60: =J59/12 -> 497.36418 | ... N60: =N59/12 -> 500.05363
B61: PAYBACK SIMPLES (anos) | C61: =IFERROR(C34/C59,0) -> 4.9659174 | D61: =IFERROR(D34/D59,0) -> 4.8124672 | E61: =IFERROR(E34/E59,0) -> 3.0904312 | F61: =IFERROR(F34/F59,0) -> 3.257298 | G61: =IFERROR(G34/G59,0) -> 3.9226644 | H61: =IFERROR(H34/H59,0) -> 3.1645409 | I61: =IFERROR(I34/I59,0) -> 3.5130465 | J61: =IFERROR(J34/J59,0) -> 3.5575876 | ... N61: =IFERROR(N34/N59,0) -> 4.1129822 | P61: Investimento total dividido pela economia do ano 1. CUIDADO: payback bom nao significa melhor negocio - ver a linha do lucro em 20 anos.
B62: Economia acumulada em 5 anos (R$) | C62: =PROJECAO!E10 -> 34178.128 | D62: =PROJECAO!H10 -> 34178.128 | E62: =PROJECAO!K10 -> 34133.461 | F62: =PROJECAO!N10 -> 34133.461 | G62: =PROJECAO!Q10 -> 30998.808 | H62: =PROJECAO!T10 -> 26795.73 | I62: =PROJECAO!W10 -> 34178.128 | J62: =PROJECAO!Z10 -> 33994.307 | K62: =PROJECAO!AC10 -> 34178.128 | L62: =PROJECAO!AF10 -> 34110.269 | M62: =PROJECAO!AI10 -> 34178.128 | N62: =PROJECAO!AL10 -> 34178.128
B63: Economia acumulada em 10 anos (R$) | C63: =PROJECAO!E15 -> 81045.811 | D63: =PROJECAO!H15 -> 81045.811 | E63: =PROJECAO!K15 -> 80939.893 | F63: =PROJECAO!N15 -> 80939.893 | G63: =PROJECAO!Q15 -> 73506.762 | H63: =PROJECAO!T15 -> 63540.1 | I63: =PROJECAO!W15 -> 81045.811 | J63: =PROJECAO!Z15 -> 80609.921 | K63: =PROJECAO!AC15 -> 81045.811 | L63: =PROJECAO!AF15 -> 80884.898 | M63: =PROJECAO!AI15 -> 81045.811 | N63: =PROJECAO!AL15 -> 81045.811
B64: Economia acumulada em 20 anos (R$) | C64: =PROJECAO!E25 -> 233444.42 | D64: =PROJECAO!H25 -> 233444.42 | E64: =PROJECAO!K25 -> 233139.33 | F64: =PROJECAO!N25 -> 233139.33 | G64: =PROJECAO!Q25 -> 211728.94 | H64: =PROJECAO!T25 -> 183020.95 | I64: =PROJECAO!W25 -> 233444.42 | J64: =PROJECAO!Z25 -> 232188.88 | K64: =PROJECAO!AC25 -> 233444.42 | L64: =PROJECAO!AF25 -> 232980.92 | M64: =PROJECAO!AI25 -> 233444.42 | N64: =PROJECAO!AL25 -> 233444.42
B65: LUCRO LIQUIDO EM 20 ANOS (R$) | C65: =C64-C34 -> 203645.72 | D65: =D64-D34 -> 204566.52 | E65: =E64-E34 -> 214618.99 | F65: =F64-F34 -> 213618.99 | G65: =G64-G34 -> 190380.03 | H65: =H64-H34 -> 168133.31 | I65: =I64-I34 -> 212363.88 | J65: =J64-J34 -> 210955.88 | ... N65: =N64-N34 -> 208763.88 | P65: Economia de 20 anos menos o investimento. E O MELHOR CRITERIO DE DECISAO FINANCEIRA - melhor que o payback.
B66: Retorno sobre o investimento em 20 anos | C66: =IFERROR(C65/C34,0) -> 6.834047 | D66: =IFERROR(D65/D34,0) -> 7.0838432 | E66: =IFERROR(E65/E34,0) -> 11.588286 | F66: =IFERROR(F65/F34,0) -> 10.943405 | G66: =IFERROR(G65/G34,0) -> 8.9175525 | H66: =IFERROR(H65/H34,0) -> 11.293483 | I66: =IFERROR(I65/I34,0) -> 10.07393 | J66: =IFERROR(J65/J34,0) -> 9.9352837 | ... N66: =IFERROR(N65/N34,0) -> 8.458643
B68: EXPANSAO FUTURA
B69: kWp maximo com o mesmo inversor (DC/AC 1,35) | C69: =C16*1.35 -> 8.1 | D69: =D16*1.35 -> 8.1 | E69: =E16*1.35 -> 6.75 | F69: =F16*1.35 -> 6.75 | G69: =G16*1.35 -> 5.4 | H69: =H16*1.35 -> 4.05 | I69: =I16*1.35 -> 12.15 | J69: =J16*1.35 -> 6.75 | ... N69: =N16*1.35 -> 12.15
B70: Modulos que ainda cabem no inversor | C70: =MAX(0,ROUNDDOWN((C69-C14)*1000/C12,0)) -> 1 | D70: =MAX(0,ROUNDDOWN((D69-D14)*1000/D12,0)) -> 1 | E70: =MAX(0,ROUNDDOWN((E69-E14)*1000/E12,0)) -> 0 | F70: =MAX(0,ROUNDDOWN((F69-F14)*1000/F12,0)) -> 0 | G70: =MAX(0,ROUNDDOWN((G69-G14)*1000/G12,0)) -> 0 | H70: =MAX(0,ROUNDDOWN((H69-H14)*1000/H12,0)) -> 0 | I70: =MAX(0,ROUNDDOWN((I69-I14)*1000/I12,0)) -> 8 | J70: =MAX(0,ROUNDDOWN((J69-J14)*1000/J12,0)) -> 1 | ... N70: =MAX(0,ROUNDDOWN((N69-N14)*1000/N12,0)) -> 4 | P70: ALERTA: os inversores de 5 kW da SunWash (C e D) nao aceitam nenhum modulo a mais. Sun Coast v2 (+5) e a opcao com microinversores tem folga real - mas nos micros o limite verdadeiro e o numero de CANAIS livres, nao a potencia.
B71: LIMITE REAL de expansao (canais e estrutura) | C71: 1 modulo (limite de potencia) | D71: 1 modulo (limite de potencia) | E71: 0 - inversor no limite | F71: 0 - inversor no limite | G71: 0 - inversor no limite | H71: 0 - inversor sobrecarregado | I71: 6 MODULOS - canais livres nos 4 micros Deye | J71: 1 modulo; para 12 precisa de um 3o micro | K71: 5 modulos | L71: 2 a 3 modulos | M71: 4 modulos (canais livres) | N71: 2 modulos (canais livres) | P71: A linha acima calcula pela POTENCIA do inversor. Em microinversor o limite verdadeiro e o numero de CANAIS livres. Os 4 micros Deye SUN-S225G4-EU-Q0 tem 4 MPPTs cada = 16 canais para 10 modulos, ou seja 6 canais livres: da para ir a 10,4 kWp sem comprar inversor nenhum.
B72: Geracao extra possivel sem trocar inversor (kWh/ano) | C72: =C70*C12/1000*GERACAO!$I$17 -> 777.52543 | D72: =D70*D12/1000*GERACAO!$I$17 -> 764.88274 | E72: =E70*E12/1000*GERACAO!$I$17 -> 0 | F72: =F70*F12/1000*GERACAO!$I$17 -> 0 | G72: =G70*G12/1000*GERACAO!$I$17 -> 0 | H72: =H70*H12/1000*GERACAO!$I$17 -> 0 | I72: =I70*I12/1000*GERACAO!$I$17 -> 6574.1988 | J72: =J70*J12/1000*GERACAO!$I$17 -> 745.91871 | ... N72: =N70*N12/1000*GERACAO!$I$17 -> 3287.0994
B73: Situacao do inversor | C73: =IF(C18>1.35,"JA SOBRECARREGADO",IF(C18<1.1,"SUBAPROVEITADO","OK")) -> OK | D73: =IF(D18>1.35,"JA SOBRECARREGADO",IF(D18<1.1,"SUBAPROVEITADO","OK")) -> OK | E73: =IF(E18>1.35,"JA SOBRECARREGADO",IF(E18<1.1,"SUBAPROVEITADO","OK")) -> OK | F73: =IF(F18>1.35,"JA SOBRECARREGADO",IF(F18<1.1,"SUBAPROVEITADO","OK")) -> OK | G73: =IF(G18>1.35,"JA SOBRECARREGADO",IF(G18<1.1,"SUBAPROVEITADO","OK")) -> OK | H73: =IF(H18>1.35,"JA SOBRECARREGADO",IF(H18<1.1,"SUBAPROVEITADO","OK")) -> JA SOBRECARREGADO | I73: =IF(I18>1.35,"JA SOBRECARREGADO",IF(I18<1.1,"SUBAPROVEITADO","OK")) -> SUBAPROVEITADO | J73: =IF(J18>1.35,"JA SOBRECARREGADO",IF(J18<1.1,"SUBAPROVEITADO","OK")) -> OK | ... N73: =IF(N18>1.35,"JA SOBRECARREGADO",IF(N18<1.1,"SUBAPROVEITADO","OK")) -> SUBAPROVEITADO | P73: 'JA SOBRECARREGADO' = inversor pequeno para os modulos desde o dia 1 (perde geracao e garantia). 'SUBAPROVEITADO' = folga; boa se proposital para expansao, ruim se foi venda a mais.
B75: DECISAO ESPECIFICA: AUXSOL x HUAWEI NA PROPOSTA DA SUNWASH
B76: Diferenca de preco (Huawei - AUXSOL) | C76: =F29-E29 -> 1000
B77: Diferenca no payback, em anos | C77: =IFERROR(F61-E61,0) -> 0.16686687
B78: Diferenca no lucro de 20 anos | C78: =F65-E65 -> -1000
B80: RECOMENDACAO: entre as duas da SunWash com inversor string, pagar os R$ 1.000 e ficar com o HUAWEI.
B81: O inversor e o unico componente que quase certamente sera trocado dentro da vida do sistema. Huawei tem garantia de fabrica mais longa,
B82: assistencia estabelecida no Brasil, monitoramento maduro e valor de revenda. AUXSOL tem penetracao pequena: se a marca sair do mercado,
B83: voce fica com o sistema parado esperando peca. O atraso de cerca de 2 meses no payback nao paga esse risco.
B85: OBSERVACAO SOBRE PAYBACK x LUCRO: sistema pequeno se paga rapido e depois te deixa pagando conta para sempre.
B86: Payback ignora a energia que voce NAO compensou. Por isso o criterio correto e o LUCRO LIQUIDO EM 20 ANOS.

Sheet BOM_DETALHADO
A1: LISTA DE MATERIAIS - AS TRES COTACOES BELENERGY LADO A LADO
A2: Os tres orcamentos vem do MESMO distribuidor (Belenus/BelEnergy). Isso permite comparar escopo item por item.
B4: ITEM | C4: A) TecSolarSP JA Solar 615W WEB-006506779 | D4: B) TecSolarSP Astronergy 605W WEB-006512519 | E4: E) William Maxeon 535W WEB-006493952 | F4: ANALISE TECNICA
B5: Modulo fotovoltaico | C5: 12 pc JA Solar 615 W bifacial N-type | D5: 12 pc Astronergy 605 W bifacial N-type | E5: 10 pc Maxeon 535 W bifacial PERC | F5: A e B usam N-type TOPCon (geracao atual). E usa PERC, tecnologia anterior: menor eficiencia por m2 e degradacao maior.
B6: Inversor | C6: Huawei 6 kW mono 220 V 2 MPPT | D6: Huawei 6 kW mono 220 V 2 MPPT | E6: Solis 4 kW mono 220 V 2 MPPT | F6: TODOS de 220 V - incompativeis com o padrao monofasico atual sem adequacao. O Solis de 4 kW limita a expansao futura a zero.
B7: Estrutura - suporte de telhado | C7: 18 pc suporte pe em L FIBROCIMENTO | D7: 18 pc suporte pe em L FIBROCIMENTO | E7: 10 pc gancho telha COLONIAL c/ prolongador | F7: CONTRADICAO GRAVE: TecSolarSP cotou FIBROCIMENTO; William e Sun Coast cotaram TELHA COLONIAL. Dois contra um. Se for colonial, a estrutura das duas cotacoes da TecSolarSP esta errada. Resolver com uma foto antes de comprar.
B8: Haste / fixacao | C8: 18 pc haste 10x250 mm inox (madeira) | D8: 20 pc haste 10x250 mm inox | E8: incluso no gancho | F8: Fixacao por perfuracao exige vedacao com arruela EPDM. Exigir garantia contra infiltracao.
B9: Perfil de fixacao | C9: 24 pc de 2,70 m | D9: 24 pc de 2,70 m | E9: 10 pc de 2,28 m | F9: Compativel com a quantidade de modulos de cada projeto.
B10: Grampos final / intermediario | C10: 6 jg final + 6 jg intermediario | D10: 6 jg final + 6 jg intermediario | E10: 2 jg final + 10 jg intermediario | F10: Sem observacao relevante.
B11: Garra de aterramento | C11: 6 jg | D11: 3 jg | E11: 2 jg | F11: ALERTA: quantidade cai muito em B e E. Aterramento de moldura e estrutura precisa ser continuo em todas as fileiras.
B12: Cabo solar CC | C12: 30 m vermelho + 30 m preto de 6 mm2 | D12: 30 m vermelho + 30 m preto de 4 mm2 | E12: 25 m vermelho + 25 m preto de 4 mm2 | F12: Bitola de 4 mm2 atende em corrente, mas verificar queda de tensao no percurso real telhado-inversor.
B13: Cabo de aterramento / equipotencializacao | C13: 20 m de 4 mm2 verde | D13: NAO INCLUIDO | E13: 10 m de 6 mm2 verde | F13: ALERTA: a cotacao B nao tem condutor de equipotencializacao. Item de seguranca, nao e opcional.
B14: String box CC | C14: 1 pc 2E/2S 1000 V Clamper | D14: 1 pc 2E/2S 1000 V Clamper | E14: 1 pc 2-4E/2-4S 1000 V | F14: Verificar em todas se contem DPS CC e chave seccionadora sob carga.
B15: DPS do lado CA | C15: NAO INCLUIDO | D15: NAO INCLUIDO | E15: 3 pc Clamper classe II 275 V 15 kA | F15: ALERTA: so o William incluiu protecao contra surto no lado CA. Nas duas da TecSolarSP falta - e obrigatorio pela NBR 5410.
... B20: Garantia do distribuidor | C20: 1 ano Belenus | D20: 1 ano Belenus | E20: 1 ano Belenus | F20: A Belenus cobre 1 ano. Todo o resto (25 a 30 anos do modulo, 5 a 10 do inversor) e garantia do FABRICANTE, nao do integrador.
B22: FECHAMENTO FINANCEIRO DAS COTACOES DE MATERIAL
B23: Componente | C23: A) JA Solar 615W | D23: B) Astronergy 605W | E23: E) William Maxeon 535W
B24: Total de produtos | C24: 17344.82 | D24: 16588.37 | E24: 10565.21
B25: Frete | C25: 732.44 | D25: 719.53 | E25: 593.7
B26: Seguro | C26: 151.44 | D26: 0 | E26: 0
B27: ICMS / IPI / ST / DIFAL | C27: 0 | D27: 0 | E27: 0
B28: TOTAL DO KIT (material) | C28: =SUM(C24:C27) -> 18228.7 | D28: =SUM(D24:D27) -> 17307.9 | E28: =SUM(E24:E27) -> 11158.91
B30: Potencia do sistema (kWp) | C30: =COMPARATIVO!C14 -> 7.38 | D30: =COMPARATIVO!D14 -> 7.26 | E30: =COMPARATIVO!G14 -> 5.35
B31: Custo do material por Wp | C31: =IFERROR(C28/(C30*1000),0) -> 2.4700136 | D31: =IFERROR(D28/(D30*1000),0) -> 2.3840083 | E31: =IFERROR(E28/(E30*1000),0) -> 2.0857776
B33: Mao de obra + engenharia declarada pelo William | C33: R$ 7.690,00 para 10 modulos = R$ 769 por modulo, ou R$ 1,44 por Wp
B34: Margem que o William cobrou sobre o kit | C34: =IFERROR(7690/E28,0) -> 0.68913541 | D34: Referencia de mercado para negociar com a TecSolarSP: eles pagam R$ 18.228,70 de material.
B35: Preco de venda justo estimado para a opcao A | C35: =C28+790+6900/10*12 -> 27298.7 | D35: Se a TecSolarSP pedir muito acima disso, ha espaco para negociar - agora voce sabe o custo deles.
B37: A opcao A (615 W) vale os R$ 920,80 a mais que a opcao B (605 W)?
B38: Diferenca de preco do material | C38: =C28-D28 -> 920.8
B39: Geracao anual extra da opcao A (kWh) | C39: =COMPARATIVO!C39-COMPARATIVO!D39 -> 151.71228
B40: Valor dessa geracao extra por ano | C40: =C39*ENTRADAS!C18 -> 154.96954
B41: Anos para a geracao extra pagar a diferenca | C41: =IFERROR(C38/C40,0) -> 5.9418127 | D41: Se der acima de ~6 anos, a diferenca NAO se paga pela geracao: decida por marca, garantia e completude do kit (a opcao A tem aterramento completo, a B nao).

Sheet ECONOMIA
A1: MODELO DE ECONOMIA - ANO 1, PELAS REGRAS DA LEI 14.300/2022
A2: Base: Cenario 3 (residencia + BYD + margem). A conta NAO vai a zero: permanecem custo de disponibilidade, Fio B e COSIP.
B4: LINHA DE CALCULO | C4: A) TecSolarSP JA Solar 615W Huawei 6 kW | D4: B) TecSolarSP Astronergy 605W Huawei 6 kW | E4: C) SunWash TCL 620W AUXSOL 5 kW | F4: D) SunWash TCL 620W HUAWEI 5 kW | G4: E) William Maxeon 535W Solis 4 kW | H4: F) Sun Coast v1 RONMA 585W AUXSOL 3 kW (SUPERADA) | I4: G) SunWash MICRO 10x650W 4x 2,25 kW | J4: H) Sfero (Renato) Longi/DAH 590W 2x micro 2,5 kW | K4: I) Sun Coast v2 TCL 620W x11 AUXSOL 7,5 kW | L4: J) AD BioSolar JA Solar 615W x10 Huawei SUN2000-6KTL-L1 | M4: SIMULACAO G12 MICRO 12x650W 4x Deye 2,25 kW | N4: SIMULACAO G14 MICRO 14x650W 4x Deye 2,25 kW | O4: M) Bruno G4 (a receber) | P4: EXPLICACAO
B5: Consumo anual - Cenario 3 (kWh) | C5: =BYD!$G$35 -> 7960.2139 | D5: =BYD!$G$35 -> 7960.2139 | E5: =BYD!$G$35 -> 7960.2139 | F5: =BYD!$G$35 -> 7960.2139 | G5: =BYD!$G$35 -> 7960.2139 | H5: =BYD!$G$35 -> 7960.2139 | I5: =BYD!$G$35 -> 7960.2139 | J5: =BYD!$G$35 -> 7960.2139 | ... N5: =BYD!$G$35 -> 7960.2139 | P5: Residencia + BYD + margem de crescimento
B6: Geracao anual do sistema (kWh) | C6: =COMPARATIVO!C39 -> 9330.3052 | D6: =COMPARATIVO!D39 -> 9178.5929 | E6: =COMPARATIVO!E39 -> 7838.4678 | F6: =COMPARATIVO!F39 -> 7838.4678 | G6: =COMPARATIVO!G39 -> 6763.8391 | H6: =COMPARATIVO!H39 -> 5916.7789 | I6: =COMPARATIVO!I39 -> 8217.7485 | J6: =COMPARATIVO!J39 -> 7459.1871 | ... N6: =COMPARATIVO!N39 -> 11504.848 | P6: Geracao realista no telhado Sudeste
B7: Tarifa efetiva (R$/kWh) | C7: =ENTRADAS!$C$18 -> 1.02147 | D7: =ENTRADAS!$C$18 -> 1.02147 | E7: =ENTRADAS!$C$18 -> 1.02147 | F7: =ENTRADAS!$C$18 -> 1.02147 | G7: =ENTRADAS!$C$18 -> 1.02147 | H7: =ENTRADAS!$C$18 -> 1.02147 | I7: =ENTRADAS!$C$18 -> 1.02147 | J7: =ENTRADAS!$C$18 -> 1.02147 | ... N7: =ENTRADAS!$C$18 -> 1.02147 | P7: R$ 1,0215 - calculado da fatura real de jul/2026
B8: CONTA ANUAL SEM SOLAR, COM O BYD (R$) | C8: =C5*C7+ENTRADAS!$C$26*12 -> 8384.4397 | D8: =D5*D7+ENTRADAS!$C$26*12 -> 8384.4397 | E8: =E5*E7+ENTRADAS!$C$26*12 -> 8384.4397 | F8: =F5*F7+ENTRADAS!$C$26*12 -> 8384.4397 | G8: =G5*G7+ENTRADAS!$C$26*12 -> 8384.4397 | H8: =H5*H7+ENTRADAS!$C$26*12 -> 8384.4397 | I8: =I5*I7+ENTRADAS!$C$26*12 -> 8384.4397 | J8: =J5*J7+ENTRADAS!$C$26*12 -> 8384.4397 | ... N8: =N5*N7+ENTRADAS!$C$26*12 -> 8384.4397 | P8: O cenario que voce enfrenta se nao instalar nada e o carro chegar
B9: Autoconsumo instantaneo (kWh) | C9: =MIN(C5,C6)*ENTRADAS!$C$37 -> 2388.0642 | D9: =MIN(D5,D6)*ENTRADAS!$C$37 -> 2388.0642 | E9: =MIN(E5,E6)*ENTRADAS!$C$37 -> 2351.5403 | F9: =MIN(F5,F6)*ENTRADAS!$C$37 -> 2351.5403 | G9: =MIN(G5,G6)*ENTRADAS!$C$37 -> 2029.1517 | H9: =MIN(H5,H6)*ENTRADAS!$C$37 -> 1775.0337 | I9: =MIN(I5,I6)*ENTRADAS!$C$37 -> 2388.0642 | J9: =MIN(J5,J6)*ENTRADAS!$C$37 -> 2237.7561 | ... N9: =MIN(N5,N6)*ENTRADAS!$C$37 -> 2388.0642 | P9: Usado no instante da geracao: nao passa pelo medidor, nao paga nada
B10: Energia injetada na rede (kWh) | C10: =C6-C9 -> 6942.241 | D10: =D6-D9 -> 6790.5287 | E10: =E6-E9 -> 5486.9274 | F10: =F6-F9 -> 5486.9274 | G10: =G6-G9 -> 4734.6874 | H10: =H6-H9 -> 4141.7452 | I10: =I6-I9 -> 5829.6843 | J10: =J6-J9 -> 5221.4309 | ... N10: =N6-N9 -> 9116.7837 | P10: Vira credito de energia
B11: Consumo minimo faturavel - disponibilidade (kWh) | C11: =ENTRADAS!$C$17*12 -> 600 | D11: =ENTRADAS!$C$17*12 -> 600 | E11: =ENTRADAS!$C$17*12 -> 600 | F11: =ENTRADAS!$C$17*12 -> 600 | G11: =ENTRADAS!$C$17*12 -> 600 | H11: =ENTRADAS!$C$17*12 -> 600 | I11: =ENTRADAS!$C$17*12 -> 600 | J11: =ENTRADAS!$C$17*12 -> 600 | ... N11: =ENTRADAS!$C$17*12 -> 600 | P11: 50 kWh/mes apos virar bifasico. Nunca compensavel
B12: Energia compensada com creditos (kWh) | C12: =MAX(0,MIN(C10,C5-C9-C11)) -> 4972.1497 | D12: =MAX(0,MIN(D10,D5-D9-D11)) -> 4972.1497 | E12: =MAX(0,MIN(E10,E5-E9-E11)) -> 5008.6736 | F12: =MAX(0,MIN(F10,F5-F9-F11)) -> 5008.6736 | G12: =MAX(0,MIN(G10,G5-G9-G11)) -> 4734.6874 | H12: =MAX(0,MIN(H10,H5-H9-H11)) -> 4141.7452 | I12: =MAX(0,MIN(I10,I5-I9-I11)) -> 4972.1497 | J12: =MAX(0,MIN(J10,J5-J9-J11)) -> 5122.4578 | ... N12: =MAX(0,MIN(N10,N5-N9-N11)) -> 4972.1497 | P12: Limitada pelo consumo restante apos autoconsumo e disponibilidade
B13: Excedente que nao sera aproveitado (kWh) | C13: =C10-C12 -> 1970.0913 | D13: =D10-D12 -> 1818.379 | E13: =E10-E12 -> 478.25388 | F13: =F10-F12 -> 478.25388 | G13: =G10-G12 -> 0 | H13: =H10-H12 -> 0 | I13: =I10-I12 -> 857.53458 | J13: =J10-J12 -> 98.973186 | ... N13: =N10-N12 -> 4144.634 | P13: Credito com prazo de 60 meses. Sobredimensionar e desperdicio
B14: Energia ainda comprada da rede (kWh) | C14: =MAX(C11,C5-C9-C12) -> 600 | D14: =MAX(D11,D5-D9-D12) -> 600 | E14: =MAX(E11,E5-E9-E12) -> 600 | F14: =MAX(F11,F5-F9-F12) -> 600 | G14: =MAX(G11,G5-G9-G12) -> 1196.3748 | H14: =MAX(H11,H5-H9-H12) -> 2043.435 | I14: =MAX(I11,I5-I9-I12) -> 600 | J14: =MAX(J11,J5-J9-J12) -> 600 | ... N14: =MAX(N11,N5-N9-N12) -> 600 | P14: O que continua sendo faturado
B15: Custo da energia comprada (R$) | C15: =C14*C7 -> 612.882 | D15: =D14*D7 -> 612.882 | E15: =E14*E7 -> 612.882 | F15: =F14*F7 -> 612.882 | G15: =G14*G7 -> 1222.0609 | H15: =H14*H7 -> 2087.3075 | I15: =I14*I7 -> 612.882 | J15: =J14*J7 -> 612.882 | ... N15: =N14*N7 -> 612.882
B16: Custo do Fio B sobre a energia compensada (R$) | C16: =C12*ENTRADAS!$C$25 -> 1067.5941 | D16: =D12*ENTRADAS!$C$25 -> 1067.5941 | E16: =E12*ENTRADAS!$C$25 -> 1075.4363 | F16: =F12*ENTRADAS!$C$25 -> 1075.4363 | G16: =G12*ENTRADAS!$C$25 -> 1016.6075 | H16: =H12*ENTRADAS!$C$25 -> 889.294 | I16: =I12*ENTRADAS!$C$25 -> 1067.5941 | J16: =J12*ENTRADAS!$C$25 -> 1099.8675 | ... N16: =N12*ENTRADAS!$C$25 -> 1067.5941 | P16: Lei 14.300: 60% da TUSD Fio B em 2026, 100% a partir de 2029
B17: COSIP / iluminacao publica (R$) | C17: =ENTRADAS!$C$26*12 -> 253.32 | D17: =ENTRADAS!$C$26*12 -> 253.32 | E17: =ENTRADAS!$C$26*12 -> 253.32 | F17: =ENTRADAS!$C$26*12 -> 253.32 | G17: =ENTRADAS!$C$26*12 -> 253.32 | H17: =ENTRADAS!$C$26*12 -> 253.32 | I17: =ENTRADAS!$C$26*12 -> 253.32 | J17: =ENTRADAS!$C$26*12 -> 253.32 | ... N17: =ENTRADAS!$C$26*12 -> 253.32 | P17: R$ 21,11 por mes. A geracao nao afeta
B18: CONTA ANUAL COM SOLAR (R$) | C18: =C15+C16+C17 -> 1933.7961 | D18: =D15+D16+D17 -> 1933.7961 | E18: =E15+E16+E17 -> 1941.6383 | F18: =F15+F16+F17 -> 1941.6383 | G18: =G15+G16+G17 -> 2491.9884 | H18: =H15+H16+H17 -> 3229.9215 | I18: =I15+I16+I17 -> 1933.7961 | J18: =J15+J16+J17 -> 1966.0695 | ... N18: =N15+N16+N17 -> 1933.7961 | P18: O que voce continuara pagando por ano
B19: CONTA MEDIA MENSAL COM SOLAR (R$) | C19: =C18/12 -> 161.14968 | D19: =D18/12 -> 161.14968 | E19: =E18/12 -> 161.8032 | F19: =F18/12 -> 161.8032 | G19: =G18/12 -> 207.6657 | H19: =H18/12 -> 269.16013 | I19: =I18/12 -> 161.14968 | J19: =J18/12 -> 163.83912 | ... N19: =N18/12 -> 161.14968 | P19: A prova de que nao existe conta de R$ 0
B20: Reducao da conta | C20: =IFERROR(1-C18/C8,0) -> 0.76935893 | D20: =IFERROR(1-D18/D8,0) -> 0.76935893 | E20: =IFERROR(1-E18/E8,0) -> 0.7684236 | F20: =IFERROR(1-F18/F8,0) -> 0.7684236 | G20: =IFERROR(1-G18/G8,0) -> 0.70278415 | H20: =IFERROR(1-H18/H8,0) -> 0.61477193 | I20: =IFERROR(1-I18/I8,0) -> 0.76935893 | J20: =IFERROR(1-J18/J8,0) -> 0.76550973 | ... N20: =IFERROR(1-N18/N8,0) -> 0.76935893
B21: Economia bruta anual (R$) | C21: =C8-C18 -> 6450.6435 | D21: =D8-D18 -> 6450.6435 | E21: =E8-E18 -> 6442.8013 | F21: =F8-F18 -> 6442.8013 | G21: =G8-G18 -> 5892.4513 | H21: =H8-H18 -> 5154.5181 | I21: =I8-I18 -> 6450.6435 | J21: =J8-J18 -> 6418.3702 | ... N21: =N8-N18 -> 6450.6435
B22: Manutencao e limpeza (R$/ano) | C22: =ENTRADAS!$C$35 -> 300 | D22: =ENTRADAS!$C$35 -> 300 | E22: =ENTRADAS!$C$35 -> 300 | F22: =ENTRADAS!$C$35 -> 300 | G22: =ENTRADAS!$C$35 -> 300 | H22: =ENTRADAS!$C$35 -> 300 | I22: =ENTRADAS!$C$35 -> 300 | J22: =ENTRADAS!$C$35 -> 300 | ... N22: =ENTRADAS!$C$35 -> 300 | P22: Custo recorrente real
B23: Provisao para troca do inversor (R$/ano) | C23: =ENTRADAS!$C$36 -> 150 | D23: =ENTRADAS!$C$36 -> 150 | E23: =ENTRADAS!$C$36 -> 150 | F23: =ENTRADAS!$C$36 -> 150 | G23: =ENTRADAS!$C$36 -> 150 | H23: =ENTRADAS!$C$36 -> 150 | I23: =ENTRADAS!$C$36 -> 150 | J23: =ENTRADAS!$C$36 -> 150 | ... N23: =ENTRADAS!$C$36 -> 150 | P23: O inversor nao dura os 25 anos do modulo
B24: Reservado | C24: =0 -> 0 | D24: =0 -> 0 | E24: =0 -> 0 | F24: =0 -> 0 | G24: =0 -> 0 | H24: =0 -> 0 | I24: =0 -> 0 | J24: =0 -> 0 | ... N24: =0 -> 0 | P24: Degradacao ja tratada no fator de geracao da aba PROJECAO
B25: Subtotal de custos recorrentes (R$) | C25: =C22+C23 -> 450 | D25: =D22+D23 -> 450 | E25: =E22+E23 -> 450 | F25: =F22+F23 -> 450 | G25: =G22+G23 -> 450 | H25: =H22+H23 -> 450 | I25: =I22+I23 -> 450 | J25: =J22+J23 -> 450 | ... N25: =N22+N23 -> 450
B26: ECONOMIA LIQUIDA NO ANO 1 (R$) | C26: =C21-C25 -> 6000.6435 | D26: =D21-D25 -> 6000.6435 | E26: =E21-E25 -> 5992.8013 | F26: =F21-F25 -> 5992.8013 | G26: =G21-G25 -> 5442.4513 | H26: =H21-H25 -> 4704.5181 | I26: =I21-I25 -> 6000.6435 | J26: =J21-J25 -> 5968.3702 | ... N26: =N21-N25 -> 6000.6435 | P26: Base do payback e da projecao de 20 anos
B28: SIMULACAO SEM CARRO x COM CARRO (impacto isolado do BYD)
B29: Consumo anual SEM o BYD (kWh) | C29: =BYD!$F$33*12 -> 4221.9251 | P29: Media real da conta x 12
B30: Consumo anual COM o BYD (kWh) | C30: =BYD!$F$34*12 -> 6921.9251 | P30: Cenario 2
B31: Acrescimo de consumo causado pelo BYD (kWh/ano) | C31: =C30-C29 -> 2700 | P31: Inclui as perdas de carregamento
B32: Acrescimo percentual sobre o consumo atual | C32: =IFERROR(C30/C29-1,0) -> 0.63951869 | P32: Por isso a media da conta nao serve de base
B33: Conta anual SEM solar e SEM o BYD (R$) | C33: =C29*ENTRADAS!C18+ENTRADAS!C26*12 -> 4565.8898 | P33: Sua situacao de hoje
B34: Conta anual SEM solar e COM o BYD (R$) | C34: =C30*ENTRADAS!C18+ENTRADAS!C26*12 -> 7323.8588 | P34: O carro sozinho encarece a conta neste valor
B35: Custo anual so do BYD sem energia solar (R$) | C35: =C31*ENTRADAS!C18 -> 2757.969 | P35: Na tarifa cheia
B36: Custo anual so do BYD com energia solar (R$) | C36: =C31*ENTRADAS!C25 -> 579.72996 | P36: Compensado: paga-se apenas o Fio B
B37: ECONOMIA ANUAL SO NO CARREGAMENTO DO BYD (R$) | C37: =C35-C36 -> 2178.239 | P37: O melhor retorno marginal do projeto
B38: Numero de placas de 615 W dedicadas ao BYD | C38: =IFERROR(ROUNDUP(C31/GERACAO!I17*1000/615,0),0) -> 4 | P38: Placas que existem por causa do carro

Sheet PROJECAO
A1: PROJECAO DE 20 ANOS, ECONOMIA ACUMULADA E PAYBACK
A2: Economia do ano 1 corrigida por inflacao energetica e degradacao, menos O&M. 'Fluxo' = acumulado menos o investimento; fica positivo no ano do payback.
B4: Ano | C4: Fator geracao | D4: A) TecSolarSP Economia | E4: A) TecSolarSP Acumulado | F4: A) TecSolarSP Fluxo | G4: B) TecSolarSP Economia | H4: B) TecSolarSP Acumulado | I4: B) TecSolarSP Fluxo | J4: C) SunWash Economia | K4: C) SunWash Acumulado | L4: C) SunWash Fluxo | M4: D) SunWash Economia | N4: D) SunWash Acumulado | O4: D) SunWash Fluxo | P4: E) William Economia | Q4: E) William Acumulado | R4: E) William Fluxo | S4: F) Sun Coast v1 Economia | T4: F) Sun Coast v1 Acumulado | U4: F) Sun Coast v1 Fluxo | V4: G) SunWash Economia | W4: G) SunWash Acumulado | X4: G) SunWash Fluxo | Y4: H) Sfero (Renato) Economia | Z4: H) Sfero (Renato) Acumulado | AA4: H) Sfero (Renato) Fluxo | AB4: I) Sun Coast v2 Economia | AC4: I) Sun Coast v2 Acumulado | AD4: I) Sun Coast v2 Fluxo | AE4: J) AD BioSolar Economia | AF4: J) AD BioSolar Acumulado | AG4: J) AD BioSolar Fluxo | AH4: SIMULACAO G12 Economia | AI4: SIMULACAO G12 Acumulado | AJ4: SIMULACAO G12 Fluxo | AK4: SIMULACAO G14 Economia | AL4: SIMULACAO G14 Acumulado | AM4: SIMULACAO G14 Fluxo
B6: 1 | C6: =(1-ENTRADAS!$C$33)*(1-ENTRADAS!$C$34)^(1-1) -> 0.98 | D6: =ECONOMIA!C$26*C6/$C$6*(1+ENTRADAS!$C$27)^(1-1) -> 6000.6435 | E6: =D6 -> 6000.6435 | F6: =E6-COMPARATIVO!C$34 -> -23798.056 | G6: =ECONOMIA!D$26*C6/$C$6*(1+ENTRADAS!$C$27)^(1-1) -> 6000.6435 | H6: =G6 -> 6000.6435 | I6: =H6-COMPARATIVO!D$34 -> -22877.256 | J6: =ECONOMIA!E$26*C6/$C$6*(1+ENTRADAS!$C$27)^(1-1) -> 5992.8013 | K6: =J6 -> 5992.8013 | L6: =K6-COMPARATIVO!E$34 -> -12527.539 | M6: =ECONOMIA!F$26*C6/$C$6*(1+ENTRADAS!$C$27)^(1-1) -> 5992.8013 | N6: =M6 -> 5992.8013 | O6: =N6-COMPARATIVO!F$34 -> -13527.539 | P6: =ECONOMIA!G$26*C6/$C$6*(1+ENTRADAS!$C$27)^(1-1) -> 5442.4513 | Q6: =P6 -> 5442.4513 | R6: =Q6-COMPARATIVO!G$34 -> -15906.459 | S6: =ECONOMIA!H$26*C6/$C$6*(1+ENTRADAS!$C$27)^(1-1) -> 4704.5181 | T6: =S6 -> 4704.5181 | U6: =T6-COMPARATIVO!H$34 -> -10183.122 | V6: =ECONOMIA!I$26*C6/$C$6*(1+ENTRADAS!$C$27)^(1-1) -> 6000.6435 | W6: =V6 -> 6000.6435 | X6: =W6-COMPARATIVO!I$34 -> -15079.896 | Y6: =ECONOMIA!J$26*C6/$C$6*(1+ENTRADAS!$C$27)^(1-1) -> 5968.3702 | Z6: =Y6 -> 5968.3702 | AA6: =Z6-COMPARATIVO!J$34 -> -15264.63 | AB6: =ECONOMIA!K$26*C6/$C$6*(1+ENTRADAS!$C$27)^(1-1) -> 6000.6435 | AC6: =AB6 -> 6000.6435 | AD6: =AC6-COMPARATIVO!K$34 -> -13389.356 | AE6: =ECONOMIA!L$26*C6/$C$6*(1+ENTRADAS!$C$27)^(1-1) -> 5988.7295 | AF6: =AE6 -> 5988.7295 | AG6: =AF6-COMPARATIVO!L$34 -> -12711.271 | AH6: =ECONOMIA!M$26*C6/$C$6*(1+ENTRADAS!$C$27)^(1-1) -> 6000.6435 | AI6: =AH6 -> 6000.6435 | AJ6: =AI6-COMPARATIVO!M$34 -> -16879.896 | AK6: =ECONOMIA!N$26*C6/$C$6*(1+ENTRADAS!$C$27)^(1-1) -> 6000.6435 | AL6: =AK6 -> 6000.6435 | AM6: =AL6-COMPARATIVO!N$34 -> -18679.896
B7: 2 | C7: =(1-ENTRADAS!$C$33)*(1-ENTRADAS!$C$34)^(2-1) -> 0.97559 | D7: =ECONOMIA!C$26*C7/$C$6*(1+ENTRADAS!$C$27)^(2-1) -> 6391.7955 | E7: =E6+D7 -> 12392.439 | F7: =E7-COMPARATIVO!C$34 -> -17406.261 | G7: =ECONOMIA!D$26*C7/$C$6*(1+ENTRADAS!$C$27)^(2-1) -> 6391.7955 | H7: =H6+G7 -> 12392.439 | I7: =H7-COMPARATIVO!D$34 -> -16485.461 | J7: =ECONOMIA!E$26*C7/$C$6*(1+ENTRADAS!$C$27)^(2-1) -> 6383.4421 | K7: =K6+J7 -> 12376.243 | L7: =K7-COMPARATIVO!E$34 -> -6144.0966 | M7: =ECONOMIA!F$26*C7/$C$6*(1+ENTRADAS!$C$27)^(2-1) -> 6383.4421 | N7: =N6+M7 -> 12376.243 | O7: =N7-COMPARATIVO!F$34 -> -7144.0966 | P7: =ECONOMIA!G$26*C7/$C$6*(1+ENTRADAS!$C$27)^(2-1) -> 5797.2175 | Q7: =Q6+P7 -> 11239.669 | R7: =Q7-COMPARATIVO!G$34 -> -10109.241 | S7: =ECONOMIA!H$26*C7/$C$6*(1+ENTRADAS!$C$27)^(2-1) -> 5011.1822 | T7: =T6+S7 -> 9715.7003 | U7: =T7-COMPARATIVO!H$34 -> -5171.9397 | V7: =ECONOMIA!I$26*C7/$C$6*(1+ENTRADAS!$C$27)^(2-1) -> 6391.7955 | W7: =W6+V7 -> 12392.439 | X7: =W7-COMPARATIVO!I$34 -> -8688.101 | Y7: =ECONOMIA!J$26*C7/$C$6*(1+ENTRADAS!$C$27)^(2-1) -> 6357.4184 | Z7: =Z6+Y7 -> 12325.789 | AA7: =Z7-COMPARATIVO!J$34 -> -8907.2114 | AB7: =ECONOMIA!K$26*C7/$C$6*(1+ENTRADAS!$C$27)^(2-1) -> 6391.7955 | AC7: =AC6+AB7 -> 12392.439 | AD7: =AC7-COMPARATIVO!K$34 -> -6997.561 | AE7: =ECONOMIA!L$26*C7/$C$6*(1+ENTRADAS!$C$27)^(2-1) -> 6379.1048 | AF7: =AF6+AE7 -> 12367.834 | AG7: =AF7-COMPARATIVO!L$34 -> -6332.1657 | AH7: =ECONOMIA!M$26*C7/$C$6*(1+ENTRADAS!$C$27)^(2-1) -> 6391.7955 | AI7: =AI6+AH7 -> 12392.439 | AJ7: =AI7-COMPARATIVO!M$34 -> -10488.101 | AK7: =ECONOMIA!N$26*C7/$C$6*(1+ENTRADAS!$C$27)^(2-1) -> 6391.7955 | AL7: =AL6+AK7 -> 12392.439 | AM7: =AL7-COMPARATIVO!N$34 -> -12288.101
B8: 3 | C8: =(1-ENTRADAS!$C$33)*(1-ENTRADAS!$C$34)^(3-1) -> 0.97119985 | D8: =ECONOMIA!C$26*C8/$C$6*(1+ENTRADAS!$C$27)^(3-1) -> 6808.4447 | E8: =E7+D8 -> 19200.884 | F8: =E8-COMPARATIVO!C$34 -> -10597.816 | G8: =ECONOMIA!D$26*C8/$C$6*(1+ENTRADAS!$C$27)^(3-1) -> 6808.4447 | H8: =H7+G8 -> 19200.884 | I8: =H8-COMPARATIVO!D$34 -> -9677.0163 | J8: =ECONOMIA!E$26*C8/$C$6*(1+ENTRADAS!$C$27)^(3-1) -> 6799.5468 | K8: =K7+J8 -> 19175.79 | L8: =K8-COMPARATIVO!E$34 -> 655.45019 | M8: =ECONOMIA!F$26*C8/$C$6*(1+ENTRADAS!$C$27)^(3-1) -> 6799.5468 | N8: =N7+M8 -> 19175.79 | O8: =N8-COMPARATIVO!F$34 -> -344.54981 | P8: =ECONOMIA!G$26*C8/$C$6*(1+ENTRADAS!$C$27)^(3-1) -> 6175.1091 | Q8: =Q7+P8 -> 17414.778 | R8: =Q8-COMPARATIVO!G$34 -> -3934.1321 | S8: =ECONOMIA!H$26*C8/$C$6*(1+ENTRADAS!$C$27)^(3-1) -> 5337.8361 | T8: =T7+S8 -> 15053.536 | U8: =T8-COMPARATIVO!H$34 -> 165.89636 | V8: =ECONOMIA!I$26*C8/$C$6*(1+ENTRADAS!$C$27)^(3-1) -> 6808.4447 | W8: =W7+V8 -> 19200.884 | X8: =W8-COMPARATIVO!I$34 -> -1879.6563 | Y8: =ECONOMIA!J$26*C8/$C$6*(1+ENTRADAS!$C$27)^(3-1) -> 6771.8267 | Z8: =Z7+Y8 -> 19097.615 | AA8: =Z8-COMPARATIVO!J$34 -> -2135.3847 | AB8: =ECONOMIA!K$26*C8/$C$6*(1+ENTRADAS!$C$27)^(3-1) -> 6808.4447 | AC8: =AC7+AB8 -> 19200.884 | AD8: =AC8-COMPARATIVO!K$34 -> -189.11628 | AE8: =ECONOMIA!L$26*C8/$C$6*(1+ENTRADAS!$C$27)^(3-1) -> 6794.9268 | AF8: =AF7+AE8 -> 19162.761 | AG8: =AF8-COMPARATIVO!L$34 -> 462.76104 | AH8: =ECONOMIA!M$26*C8/$C$6*(1+ENTRADAS!$C$27)^(3-1) -> 6808.4447 | AI8: =AI7+AH8 -> 19200.884 | AJ8: =AI8-COMPARATIVO!M$34 -> -3679.6563 | AK8: =ECONOMIA!N$26*C8/$C$6*(1+ENTRADAS!$C$27)^(3-1) -> 6808.4447 | AL8: =AL7+AK8 -> 19200.884 | AM8: =AL8-COMPARATIVO!N$34 -> -5479.6563
B9: 4 | C9: =(1-ENTRADAS!$C$33)*(1-ENTRADAS!$C$34)^(4-1) -> 0.96682945 | D9: =ECONOMIA!C$26*C9/$C$6*(1+ENTRADAS!$C$27)^(4-1) -> 7252.2531 | E9: =E8+D9 -> 26453.137 | F9: =E9-COMPARATIVO!C$34 -> -3345.5631 | G9: =ECONOMIA!D$26*C9/$C$6*(1+ENTRADAS!$C$27)^(4-1) -> 7252.2531 | H9: =H8+G9 -> 26453.137 | I9: =H9-COMPARATIVO!D$34 -> -2424.7631 | J9: =ECONOMIA!E$26*C9/$C$6*(1+ENTRADAS!$C$27)^(4-1) -> 7242.7752 | K9: =K8+J9 -> 26418.565 | L9: =K9-COMPARATIVO!E$34 -> 7898.2254 | M9: =ECONOMIA!F$26*C9/$C$6*(1+ENTRADAS!$C$27)^(4-1) -> 7242.7752 | N9: =N8+M9 -> 26418.565 | O9: =N9-COMPARATIVO!F$34 -> 6898.2254 | P9: =ECONOMIA!G$26*C9/$C$6*(1+ENTRADAS!$C$27)^(4-1) -> 6577.6336 | Q9: =Q8+P9 -> 23992.411 | R9: =Q9-COMPARATIVO!G$34 -> 2643.5015 | S9: =ECONOMIA!H$26*C9/$C$6*(1+ENTRADAS!$C$27)^(4-1) -> 5685.7829 | T9: =T8+S9 -> 20739.319 | U9: =T9-COMPARATIVO!H$34 -> 5851.6793 | V9: =ECONOMIA!I$26*C9/$C$6*(1+ENTRADAS!$C$27)^(4-1) -> 7252.2531 | W9: =W8+V9 -> 26453.137 | X9: =W9-COMPARATIVO!I$34 -> 5372.5969 | Y9: =ECONOMIA!J$26*C9/$C$6*(1+ENTRADAS!$C$27)^(4-1) -> 7213.2482 | Z9: =Z8+Y9 -> 26310.864 | AA9: =Z9-COMPARATIVO!J$34 -> 5077.8635 | AB9: =ECONOMIA!K$26*C9/$C$6*(1+ENTRADAS!$C$27)^(4-1) -> 7252.2531 | AC9: =AC8+AB9 -> 26453.137 | AD9: =AC9-COMPARATIVO!K$34 -> 7063.1369 | AE9: =ECONOMIA!L$26*C9/$C$6*(1+ENTRADAS!$C$27)^(4-1) -> 7237.8541 | AF9: =AF8+AE9 -> 26400.615 | AG9: =AF9-COMPARATIVO!L$34 -> 7700.6151 | AH9: =ECONOMIA!M$26*C9/$C$6*(1+ENTRADAS!$C$27)^(4-1) -> 7252.2531 | AI9: =AI8+AH9 -> 26453.137 | AJ9: =AI9-COMPARATIVO!M$34 -> 3572.5969 | AK9: =ECONOMIA!N$26*C9/$C$6*(1+ENTRADAS!$C$27)^(4-1) -> 7252.2531 | AL9: =AL8+AK9 -> 26453.137 | AM9: =AL9-COMPARATIVO!N$34 -> 1772.5969
B10: 5 | C10: =(1-ENTRADAS!$C$33)*(1-ENTRADAS!$C$34)^(5-1) -> 0.96247871 | D10: =ECONOMIA!C$26*C10/$C$6*(1+ENTRADAS!$C$27)^(5-1) -> 7724.9913 | E10: =E9+D10 -> 34178.128 | F10: =E10-COMPARATIVO!C$34 -> 4379.4281 | G10: =ECONOMIA!D$26*C10/$C$6*(1+ENTRADAS!$C$27)^(5-1) -> 7724.9913 | H10: =H9+G10 -> 34178.128 | I10: =H10-COMPARATIVO!D$34 -> 5300.2281 | J10: =ECONOMIA!E$26*C10/$C$6*(1+ENTRADAS!$C$27)^(5-1) -> 7714.8955 | K10: =K9+J10 -> 34133.461 | L10: =K10-COMPARATIVO!E$34 -> 15613.121 | M10: =ECONOMIA!F$26*C10/$C$6*(1+ENTRADAS!$C$27)^(5-1) -> 7714.8955 | N10: =N9+M10 -> 34133.461 | O10: =N10-COMPARATIVO!F$34 -> 14613.121 | P10: =ECONOMIA!G$26*C10/$C$6*(1+ENTRADAS!$C$27)^(5-1) -> 7006.3966 | Q10: =Q9+P10 -> 30998.808 | R10: =Q10-COMPARATIVO!G$34 -> 9649.8981 | S10: =ECONOMIA!H$26*C10/$C$6*(1+ENTRADAS!$C$27)^(5-1) -> 6056.4107 | T10: =T9+S10 -> 26795.73 | U10: =T10-COMPARATIVO!H$34 -> 11908.09 | V10: =ECONOMIA!I$26*C10/$C$6*(1+ENTRADAS!$C$27)^(5-1) -> 7724.9913 | W10: =W9+V10 -> 34178.128 | X10: =W10-COMPARATIVO!I$34 -> 13097.588 | Y10: =ECONOMIA!J$26*C10/$C$6*(1+ENTRADAS!$C$27)^(5-1) -> 7683.4438 | Z10: =Z9+Y10 -> 33994.307 | AA10: =Z10-COMPARATIVO!J$34 -> 12761.307 | AB10: =ECONOMIA!K$26*C10/$C$6*(1+ENTRADAS!$C$27)^(5-1) -> 7724.9913 | AC10: =AC9+AB10 -> 34178.128 | AD10: =AC10-COMPARATIVO!K$34 -> 14788.128 | AE10: =ECONOMIA!L$26*C10/$C$6*(1+ENTRADAS!$C$27)^(5-1) -> 7709.6536 | AF10: =AF9+AE10 -> 34110.269 | AG10: =AF10-COMPARATIVO!L$34 -> 15410.269 | AH10: =ECONOMIA!M$26*C10/$C$6*(1+ENTRADAS!$C$27)^(5-1) -> 7724.9913 | AI10: =AI9+AH10 -> 34178.128 | AJ10: =AI10-COMPARATIVO!M$34 -> 11297.588 | AK10: =ECONOMIA!N$26*C10/$C$6*(1+ENTRADAS!$C$27)^(5-1) -> 7724.9913 | AL10: =AL9+AK10 -> 34178.128 | AM10: =AL10-COMPARATIVO!N$34 -> 9497.5881
B11: 6 | C11: =(1-ENTRADAS!$C$33)*(1-ENTRADAS!$C$34)^(6-1) -> 0.95814756 | D11: =ECONOMIA!C$26*C11/$C$6*(1+ENTRADAS!$C$27)^(6-1) -> 8228.5448 | E11: =E10+D11 -> 42406.673 | F11: =E11-COMPARATIVO!C$34 -> 12607.973 | G11: =ECONOMIA!D$26*C11/$C$6*(1+ENTRADAS!$C$27)^(6-1) -> 8228.5448 | H11: =H10+G11 -> 42406.673 | I11: =H11-COMPARATIVO!D$34 -> 13528.773 | J11: =ECONOMIA!E$26*C11/$C$6*(1+ENTRADAS!$C$27)^(6-1) -> 8217.791 | K11: =K10+J11 -> 42351.252 | L11: =K11-COMPARATIVO!E$34 -> 23830.912 | M11: =ECONOMIA!F$26*C11/$C$6*(1+ENTRADAS!$C$27)^(6-1) -> 8217.791 | N11: =N10+M11 -> 42351.252 | O11: =N11-COMPARATIVO!F$34 -> 22830.912 | P11: =ECONOMIA!G$26*C11/$C$6*(1+ENTRADAS!$C$27)^(6-1) -> 7463.1086 | Q11: =Q10+P11 -> 38461.917 | R11: =Q11-COMPARATIVO!G$34 -> 17113.007 | S11: =ECONOMIA!H$26*C11/$C$6*(1+ENTRADAS!$C$27)^(6-1) -> 6451.1978 | T11: =T10+S11 -> 33246.928 | U11: =T11-COMPARATIVO!H$34 -> 18359.288 | V11: =ECONOMIA!I$26*C11/$C$6*(1+ENTRADAS!$C$27)^(6-1) -> 8228.5448 | W11: =W10+V11 -> 42406.673 | X11: =W11-COMPARATIVO!I$34 -> 21326.133 | Y11: =ECONOMIA!J$26*C11/$C$6*(1+ENTRADAS!$C$27)^(6-1) -> 8184.2891 | Z11: =Z10+Y11 -> 42178.596 | AA11: =Z11-COMPARATIVO!J$34 -> 20945.596 | AB11: =ECONOMIA!K$26*C11/$C$6*(1+ENTRADAS!$C$27)^(6-1) -> 8228.5448 | AC11: =AC10+AB11 -> 42406.673 | AD11: =AC11-COMPARATIVO!K$34 -> 23016.673 | AE11: =ECONOMIA!L$26*C11/$C$6*(1+ENTRADAS!$C$27)^(6-1) -> 8212.2073 | AF11: =AF10+AE11 -> 42322.476 | AG11: =AF11-COMPARATIVO!L$34 -> 23622.476 | AH11: =ECONOMIA!M$26*C11/$C$6*(1+ENTRADAS!$C$27)^(6-1) -> 8228.5448 | AI11: =AI10+AH11 -> 42406.673 | AJ11: =AI11-COMPARATIVO!M$34 -> 19526.133 | AK11: =ECONOMIA!N$26*C11/$C$6*(1+ENTRADAS!$C$27)^(6-1) -> 8228.5448 | AL11: =AL10+AK11 -> 42406.673 | AM11: =AL11-COMPARATIVO!N$34 -> 17726.133
B12: 7 | C12: =(1-ENTRADAS!$C$33)*(1-ENTRADAS!$C$34)^(7-1) -> 0.95383589 | D12: =ECONOMIA!C$26*C12/$C$6*(1+ENTRADAS!$C$27)^(7-1) -> 8764.9225 | E12: =E11+D12 -> 51171.595 | F12: =E12-COMPARATIVO!C$34 -> 21372.895 | G12: =ECONOMIA!D$26*C12/$C$6*(1+ENTRADAS!$C$27)^(7-1) -> 8764.9225 | H12: =H11+G12 -> 51171.595 | I12: =H12-COMPARATIVO!D$34 -> 22293.695 | J12: =ECONOMIA!E$26*C12/$C$6*(1+ENTRADAS!$C$27)^(7-1) -> 8753.4677 | K12: =K11+J12 -> 51104.72 | L12: =K12-COMPARATIVO!E$34 -> 32584.38 | M12: =ECONOMIA!F$26*C12/$C$6*(1+ENTRADAS!$C$27)^(7-1) -> 8753.4677 | N12: =N11+M12 -> 51104.72 | O12: =N12-COMPARATIVO!F$34 -> 31584.38 | P12: =ECONOMIA!G$26*C12/$C$6*(1+ENTRADAS!$C$27)^(7-1) -> 7949.5913 | Q12: =Q11+P12 -> 46411.508 | R12: =Q12-COMPARATIVO!G$34 -> 25062.598 | S12: =ECONOMIA!H$26*C12/$C$6*(1+ENTRADAS!$C$27)^(7-1) -> 6871.7191 | T12: =T11+S12 -> 40118.647 | U12: =T12-COMPARATIVO!H$34 -> 25231.007 | V12: =ECONOMIA!I$26*C12/$C$6*(1+ENTRADAS!$C$27)^(7-1) -> 8764.9225 | W12: =W11+V12 -> 51171.595 | X12: =W12-COMPARATIVO!I$34 -> 30091.055 | Y12: =ECONOMIA!J$26*C12/$C$6*(1+ENTRADAS!$C$27)^(7-1) -> 8717.782 | Z12: =Z11+Y12 -> 50896.378 | AA12: =Z12-COMPARATIVO!J$34 -> 29663.378 | AB12: =ECONOMIA!K$26*C12/$C$6*(1+ENTRADAS!$C$27)^(7-1) -> 8764.9225 | AC12: =AC11+AB12 -> 51171.595 | AD12: =AC12-COMPARATIVO!K$34 -> 31781.595 | AE12: =ECONOMIA!L$26*C12/$C$6*(1+ENTRADAS!$C$27)^(7-1) -> 8747.5201 | AF12: =AF11+AE12 -> 51069.996 | AG12: =AF12-COMPARATIVO!L$34 -> 32369.996 | AH12: =ECONOMIA!M$26*C12/$C$6*(1+ENTRADAS!$C$27)^(7-1) -> 8764.9225 | AI12: =AI11+AH12 -> 51171.595 | AJ12: =AI12-COMPARATIVO!M$34 -> 28291.055 | AK12: =ECONOMIA!N$26*C12/$C$6*(1+ENTRADAS!$C$27)^(7-1) -> 8764.9225 | AL12: =AL11+AK12 -> 51171.595 | AM12: =AL12-COMPARATIVO!N$34 -> 26491.055
B13: 8 | C13: =(1-ENTRADAS!$C$33)*(1-ENTRADAS!$C$34)^(8-1) -> 0.94954363 | D13: =ECONOMIA!C$26*C13/$C$6*(1+ENTRADAS!$C$27)^(8-1) -> 9336.264 | E13: =E12+D13 -> 60507.859 | F13: =E13-COMPARATIVO!C$34 -> 30709.159 | G13: =ECONOMIA!D$26*C13/$C$6*(1+ENTRADAS!$C$27)^(8-1) -> 9336.264 | H13: =H12+G13 -> 60507.859 | I13: =H13-COMPARATIVO!D$34 -> 31629.959 | J13: =ECONOMIA!E$26*C13/$C$6*(1+ENTRADAS!$C$27)^(8-1) -> 9324.0625 | K13: =K12+J13 -> 60428.782 | L13: =K13-COMPARATIVO!E$34 -> 41908.442 | M13: =ECONOMIA!F$26*C13/$C$6*(1+ENTRADAS!$C$27)^(8-1) -> 9324.0625 | N13: =N12+M13 -> 60428.782 | O13: =N13-COMPARATIVO!F$34 -> 40908.442 | P13: =ECONOMIA!G$26*C13/$C$6*(1+ENTRADAS!$C$27)^(8-1) -> 8467.7854 | Q13: =Q12+P13 -> 54879.293 | R13: =Q13-COMPARATIVO!G$34 -> 33530.383 | S13: =ECONOMIA!H$26*C13/$C$6*(1+ENTRADAS!$C$27)^(8-1) -> 7319.6521 | T13: =T12+S13 -> 47438.299 | U13: =T13-COMPARATIVO!H$34 -> 32550.659 | V13: =ECONOMIA!I$26*C13/$C$6*(1+ENTRADAS!$C$27)^(8-1) -> 9336.264 | W13: =W12+V13 -> 60507.859 | X13: =W13-COMPARATIVO!I$34 -> 39427.319 | Y13: =ECONOMIA!J$26*C13/$C$6*(1+ENTRADAS!$C$27)^(8-1) -> 9286.0506 | Z13: =Z12+Y13 -> 60182.429 | AA13: =Z13-COMPARATIVO!J$34 -> 38949.429 | AB13: =ECONOMIA!K$26*C13/$C$6*(1+ENTRADAS!$C$27)^(8-1) -> 9336.264 | AC13: =AC12+AB13 -> 60507.859 | AD13: =AC13-COMPARATIVO!K$34 -> 41117.859 | AE13: =ECONOMIA!L$26*C13/$C$6*(1+ENTRADAS!$C$27)^(8-1) -> 9317.7272 | AF13: =AF12+AE13 -> 60387.723 | AG13: =AF13-COMPARATIVO!L$34 -> 41687.723 | AH13: =ECONOMIA!M$26*C13/$C$6*(1+ENTRADAS!$C$27)^(8-1) -> 9336.264 | AI13: =AI12+AH13 -> 60507.859 | AJ13: =AI13-COMPARATIVO!M$34 -> 37627.319 | AK13: =ECONOMIA!N$26*C13/$C$6*(1+ENTRADAS!$C$27)^(8-1) -> 9336.264 | AL13: =AL12+AK13 -> 60507.859 | AM13: =AL13-COMPARATIVO!N$34 -> 35827.319
B14: 9 | C14: =(1-ENTRADAS!$C$33)*(1-ENTRADAS!$C$34)^(9-1) -> 0.94527069 | D14: =ECONOMIA!C$26*C14/$C$6*(1+ENTRADAS!$C$27)^(9-1) -> 9944.8484 | E14: =E13+D14 -> 70452.708 | F14: =E14-COMPARATIVO!C$34 -> 40654.008 | G14: =ECONOMIA!D$26*C14/$C$6*(1+ENTRADAS!$C$27)^(9-1) -> 9944.8484 | H14: =H13+G14 -> 70452.708 | I14: =H14-COMPARATIVO!D$34 -> 41574.808 | J14: =ECONOMIA!E$26*C14/$C$6*(1+ENTRADAS!$C$27)^(9-1) -> 9931.8515 | K14: =K13+J14 -> 70360.634 | L14: =K14-COMPARATIVO!E$34 -> 51840.294 | M14: =ECONOMIA!F$26*C14/$C$6*(1+ENTRADAS!$C$27)^(9-1) -> 9931.8515 | N14: =N13+M14 -> 70360.634 | O14: =N14-COMPARATIVO!F$34 -> 50840.294 | P14: =ECONOMIA!G$26*C14/$C$6*(1+ENTRADAS!$C$27)^(9-1) -> 9019.758 | Q14: =Q13+P14 -> 63899.052 | R14: =Q14-COMPARATIVO!G$34 -> 42550.142 | S14: =ECONOMIA!H$26*C14/$C$6*(1+ENTRADAS!$C$27)^(9-1) -> 7796.7837 | T14: =T13+S14 -> 55235.083 | U14: =T14-COMPARATIVO!H$34 -> 40347.443 | V14: =ECONOMIA!I$26*C14/$C$6*(1+ENTRADAS!$C$27)^(9-1) -> 9944.8484 | W14: =W13+V14 -> 70452.708 | X14: =W14-COMPARATIVO!I$34 -> 49372.168 | Y14: =ECONOMIA!J$26*C14/$C$6*(1+ENTRADAS!$C$27)^(9-1) -> 9891.3618 | Z14: =Z13+Y14 -> 70073.791 | AA14: =Z14-COMPARATIVO!J$34 -> 48840.791 | AB14: =ECONOMIA!K$26*C14/$C$6*(1+ENTRADAS!$C$27)^(9-1) -> 9944.8484 | AC14: =AC13+AB14 -> 70452.708 | AD14: =AC14-COMPARATIVO!K$34 -> 51062.708 | AE14: =ECONOMIA!L$26*C14/$C$6*(1+ENTRADAS!$C$27)^(9-1) -> 9925.1032 | AF14: =AF13+AE14 -> 70312.826 | AG14: =AF14-COMPARATIVO!L$34 -> 51612.826 | AH14: =ECONOMIA!M$26*C14/$C$6*(1+ENTRADAS!$C$27)^(9-1) -> 9944.8484 | AI14: =AI13+AH14 -> 70452.708 | AJ14: =AI14-COMPARATIVO!M$34 -> 47572.168 | AK14: =ECONOMIA!N$26*C14/$C$6*(1+ENTRADAS!$C$27)^(9-1) -> 9944.8484 | AL14: =AL13+AK14 -> 70452.708 | AM14: =AL14-COMPARATIVO!N$34 -> 45772.168
B15: 10 | C15: =(1-ENTRADAS!$C$33)*(1-ENTRADAS!$C$34)^(10-1) -> 0.94101697 | D15: =ECONOMIA!C$26*C15/$C$6*(1+ENTRADAS!$C$27)^(10-1) -> 10593.103 | E15: =E14+D15 -> 81045.811 | F15: =E15-COMPARATIVO!C$34 -> 51247.111 | G15: =ECONOMIA!D$26*C15/$C$6*(1+ENTRADAS!$C$27)^(10-1) -> 10593.103 | H15: =H14+G15 -> 81045.811 | I15: =H15-COMPARATIVO!D$34 -> 52167.911 | J15: =ECONOMIA!E$26*C15/$C$6*(1+ENTRADAS!$C$27)^(10-1) -> 10579.259 | K15: =K14+J15 -> 80939.893 | L15: =K15-COMPARATIVO!E$34 -> 62419.553 | M15: =ECONOMIA!F$26*C15/$C$6*(1+ENTRADAS!$C$27)^(10-1) -> 10579.259 | N15: =N14+M15 -> 80939.893 | O15: =N15-COMPARATIVO!F$34 -> 61419.553 | P15: =ECONOMIA!G$26*C15/$C$6*(1+ENTRADAS!$C$27)^(10-1) -> 9607.711 | Q15: =Q14+P15 -> 73506.762 | R15: =Q15-COMPARATIVO!G$34 -> 52157.852 | S15: =ECONOMIA!H$26*C15/$C$6*(1+ENTRADAS!$C$27)^(10-1) -> 8305.017 | T15: =T14+S15 -> 63540.1 | U15: =T15-COMPARATIVO!H$34 -> 48652.46 | V15: =ECONOMIA!I$26*C15/$C$6*(1+ENTRADAS!$C$27)^(10-1) -> 10593.103 | W15: =W14+V15 -> 81045.811 | X15: =W15-COMPARATIVO!I$34 -> 59965.271 | Y15: =ECONOMIA!J$26*C15/$C$6*(1+ENTRADAS!$C$27)^(10-1) -> 10536.13 | Z15: =Z14+Y15 -> 80609.921 | AA15: =Z15-COMPARATIVO!J$34 -> 59376.921 | AB15: =ECONOMIA!K$26*C15/$C$6*(1+ENTRADAS!$C$27)^(10-1) -> 10593.103 | AC15: =AC14+AB15 -> 81045.811 | AD15: =AC15-COMPARATIVO!K$34 -> 61655.811 | AE15: =ECONOMIA!L$26*C15/$C$6*(1+ENTRADAS!$C$27)^(10-1) -> 10572.071 | AF15: =AF14+AE15 -> 80884.898 | AG15: =AF15-COMPARATIVO!L$34 -> 62184.898 | AH15: =ECONOMIA!M$26*C15/$C$6*(1+ENTRADAS!$C$27)^(10-1) -> 10593.103 | AI15: =AI14+AH15 -> 81045.811 | AJ15: =AI15-COMPARATIVO!M$34 -> 58165.271 | AK15: =ECONOMIA!N$26*C15/$C$6*(1+ENTRADAS!$C$27)^(10-1) -> 10593.103 | AL15: =AL14+AK15 -> 81045.811 | AM15: =AL15-COMPARATIVO!N$34 -> 56365.271
B16: 11 | C16: =(1-ENTRADAS!$C$33)*(1-ENTRADAS!$C$34)^(11-1) -> 0.93678239 | D16: =ECONOMIA!C$26*C16/$C$6*(1+ENTRADAS!$C$27)^(11-1) -> 11283.615 | E16: =E15+D16 -> 92329.426 | F16: =E16-COMPARATIVO!C$34 -> 62530.726 | G16: =ECONOMIA!D$26*C16/$C$6*(1+ENTRADAS!$C$27)^(11-1) -> 11283.615 | H16: =H15+G16 -> 92329.426 | I16: =H16-COMPARATIVO!D$34 -> 63451.526 | J16: =ECONOMIA!E$26*C16/$C$6*(1+ENTRADAS!$C$27)^(11-1) -> 11268.868 | K16: =K15+J16 -> 92208.761 | L16: =K16-COMPARATIVO!E$34 -> 73688.421 | M16: =ECONOMIA!F$26*C16/$C$6*(1+ENTRADAS!$C$27)^(11-1) -> 11268.868 | N16: =N15+M16 -> 92208.761 | O16: =N16-COMPARATIVO!F$34 -> 72688.421 | P16: =ECONOMIA!G$26*C16/$C$6*(1+ENTRADAS!$C$27)^(11-1) -> 10233.99 | Q16: =Q15+P16 -> 83740.752 | R16: =Q16-COMPARATIVO!G$34 -> 62391.842 | S16: =ECONOMIA!H$26*C16/$C$6*(1+ENTRADAS!$C$27)^(11-1) -> 8846.3795 | T16: =T15+S16 -> 72386.479 | U16: =T16-COMPARATIVO!H$34 -> 57498.839 | V16: =ECONOMIA!I$26*C16/$C$6*(1+ENTRADAS!$C$27)^(11-1) -> 11283.615 | W16: =W15+V16 -> 92329.426 | X16: =W16-COMPARATIVO!I$34 -> 71248.886 | Y16: =ECONOMIA!J$26*C16/$C$6*(1+ENTRADAS!$C$27)^(11-1) -> 11222.928 | Z16: =Z15+Y16 -> 91832.849 | AA16: =Z16-COMPARATIVO!J$34 -> 70599.849 | AB16: =ECONOMIA!K$26*C16/$C$6*(1+ENTRADAS!$C$27)^(11-1) -> 11283.615 | AC16: =AC15+AB16 -> 92329.426 | AD16: =AC16-COMPARATIVO!K$34 -> 72939.426 | AE16: =ECONOMIA!L$26*C16/$C$6*(1+ENTRADAS!$C$27)^(11-1) -> 11261.212 | AF16: =AF15+AE16 -> 92146.109 | AG16: =AF16-COMPARATIVO!L$34 -> 73446.109 | AH16: =ECONOMIA!M$26*C16/$C$6*(1+ENTRADAS!$C$27)^(11-1) -> 11283.615 | AI16: =AI15+AH16 -> 92329.426 | AJ16: =AI16-COMPARATIVO!M$34 -> 69448.886 | AK16: =ECONOMIA!N$26*C16/$C$6*(1+ENTRADAS!$C$27)^(11-1) -> 11283.615 | AL16: =AL15+AK16 -> 92329.426 | AM16: =AL16-COMPARATIVO!N$34 -> 67648.886
B17: 12 | C17: =(1-ENTRADAS!$C$33)*(1-ENTRADAS!$C$34)^(12-1) -> 0.93256687 | D17: =ECONOMIA!C$26*C17/$C$6*(1+ENTRADAS!$C$27)^(12-1) -> 12019.137 | E17: =E16+D17 -> 104348.56 | F17: =E17-COMPARATIVO!C$34 -> 74549.863 | G17: =ECONOMIA!D$26*C17/$C$6*(1+ENTRADAS!$C$27)^(12-1) -> 12019.137 | H17: =H16+G17 -> 104348.56 | I17: =H17-COMPARATIVO!D$34 -> 75470.663 | J17: =ECONOMIA!E$26*C17/$C$6*(1+ENTRADAS!$C$27)^(12-1) -> 12003.429 | K17: =K16+J17 -> 104212.19 | L17: =K17-COMPARATIVO!E$34 -> 85691.851 | M17: =ECONOMIA!F$26*C17/$C$6*(1+ENTRADAS!$C$27)^(12-1) -> 12003.429 | N17: =N16+M17 -> 104212.19 | O17: =N17-COMPARATIVO!F$34 -> 84691.851 | P17: =ECONOMIA!G$26*C17/$C$6*(1+ENTRADAS!$C$27)^(12-1) -> 10901.092 | Q17: =Q16+P17 -> 94641.844 | R17: =Q17-COMPARATIVO!G$34 -> 73292.934 | S17: =ECONOMIA!H$26*C17/$C$6*(1+ENTRADAS!$C$27)^(12-1) -> 9423.0308 | T17: =T16+S17 -> 81809.51 | U17: =T17-COMPARATIVO!H$34 -> 66921.87 | V17: =ECONOMIA!I$26*C17/$C$6*(1+ENTRADAS!$C$27)^(12-1) -> 12019.137 | W17: =W16+V17 -> 104348.56 | X17: =W17-COMPARATIVO!I$34 -> 83268.023 | Y17: =ECONOMIA!J$26*C17/$C$6*(1+ENTRADAS!$C$27)^(12-1) -> 11954.494 | Z17: =Z16+Y17 -> 103787.34 | AA17: =Z17-COMPARATIVO!J$34 -> 82554.343 | AB17: =ECONOMIA!K$26*C17/$C$6*(1+ENTRADAS!$C$27)^(12-1) -> 12019.137 | AC17: =AC16+AB17 -> 104348.56 | AD17: =AC17-COMPARATIVO!K$34 -> 84958.563 | AE17: =ECONOMIA!L$26*C17/$C$6*(1+ENTRADAS!$C$27)^(12-1) -> 11995.274 | AF17: =AF16+AE17 -> 104141.38 | AG17: =AF17-COMPARATIVO!L$34 -> 85441.383 | AH17: =ECONOMIA!M$26*C17/$C$6*(1+ENTRADAS!$C$27)^(12-1) -> 12019.137 | AI17: =AI16+AH17 -> 104348.56 | AJ17: =AI17-COMPARATIVO!M$34 -> 81468.023 | AK17: =ECONOMIA!N$26*C17/$C$6*(1+ENTRADAS!$C$27)^(12-1) -> 12019.137 | AL17: =AL16+AK17 -> 104348.56 | AM17: =AL17-COMPARATIVO!N$34 -> 79668.023
B18: 13 | C18: =(1-ENTRADAS!$C$33)*(1-ENTRADAS!$C$34)^(13-1) -> 0.92837032 | D18: =ECONOMIA!C$26*C18/$C$6*(1+ENTRADAS!$C$27)^(13-1) -> 12802.605 | E18: =E17+D18 -> 117151.17 | F18: =E18-COMPARATIVO!C$34 -> 87352.468 | G18: =ECONOMIA!D$26*C18/$C$6*(1+ENTRADAS!$C$27)^(13-1) -> 12802.605 | H18: =H17+G18 -> 117151.17 | I18: =H18-COMPARATIVO!D$34 -> 88273.268 | J18: =ECONOMIA!E$26*C18/$C$6*(1+ENTRADAS!$C$27)^(13-1) -> 12785.873 | K18: =K17+J18 -> 116998.06 | L18: =K18-COMPARATIVO!E$34 -> 98477.723 | M18: =ECONOMIA!F$26*C18/$C$6*(1+ENTRADAS!$C$27)^(13-1) -> 12785.873 | N18: =N17+M18 -> 116998.06 | O18: =N18-COMPARATIVO!F$34 -> 97477.723 | P18: =ECONOMIA!G$26*C18/$C$6*(1+ENTRADAS!$C$27)^(13-1) -> 11611.68 | Q18: =Q17+P18 -> 106253.52 | R18: =Q18-COMPARATIVO!G$34 -> 84904.614 | S18: =ECONOMIA!H$26*C18/$C$6*(1+ENTRADAS!$C$27)^(13-1) -> 10037.271 | T18: =T17+S18 -> 91846.781 | U18: =T18-COMPARATIVO!H$34 -> 76959.141 | V18: =ECONOMIA!I$26*C18/$C$6*(1+ENTRADAS!$C$27)^(13-1) -> 12802.605 | W18: =W17+V18 -> 117151.17 | X18: =W18-COMPARATIVO!I$34 -> 96070.628 | Y18: =ECONOMIA!J$26*C18/$C$6*(1+ENTRADAS!$C$27)^(13-1) -> 12733.748 | Z18: =Z17+Y18 -> 116521.09 | AA18: =Z18-COMPARATIVO!J$34 -> 95288.092 | AB18: =ECONOMIA!K$26*C18/$C$6*(1+ENTRADAS!$C$27)^(13-1) -> 12802.605 | AC18: =AC17+AB18 -> 117151.17 | AD18: =AC18-COMPARATIVO!K$34 -> 97761.168 | AE18: =ECONOMIA!L$26*C18/$C$6*(1+ENTRADAS!$C$27)^(13-1) -> 12777.186 | AF18: =AF17+AE18 -> 116918.57 | AG18: =AF18-COMPARATIVO!L$34 -> 98218.568 | AH18: =ECONOMIA!M$26*C18/$C$6*(1+ENTRADAS!$C$27)^(13-1) -> 12802.605 | AI18: =AI17+AH18 -> 117151.17 | AJ18: =AI18-COMPARATIVO!M$34 -> 94270.628 | AK18: =ECONOMIA!N$26*C18/$C$6*(1+ENTRADAS!$C$27)^(13-1) -> 12802.605 | AL18: =AL17+AK18 -> 117151.17 | AM18: =AL18-COMPARATIVO!N$34 -> 92470.628
B19: 14 | C19: =(1-ENTRADAS!$C$33)*(1-ENTRADAS!$C$34)^(14-1) -> 0.92419265 | D19: =ECONOMIA!C$26*C19/$C$6*(1+ENTRADAS!$C$27)^(14-1) -> 13637.142 | E19: =E18+D19 -> 130788.31 | F19: =E19-COMPARATIVO!C$34 -> 100989.61 | G19: =ECONOMIA!D$26*C19/$C$6*(1+ENTRADAS!$C$27)^(14-1) -> 13637.142 | H19: =H18+G19 -> 130788.31 | I19: =H19-COMPARATIVO!D$34 -> 101910.41 | J19: =ECONOMIA!E$26*C19/$C$6*(1+ENTRADAS!$C$27)^(14-1) -> 13619.32 | K19: =K18+J19 -> 130617.38 | L19: =K19-COMPARATIVO!E$34 -> 112097.04 | M19: =ECONOMIA!F$26*C19/$C$6*(1+ENTRADAS!$C$27)^(14-1) -> 13619.32 | N19: =N18+M19 -> 130617.38 | O19: =N19-COMPARATIVO!F$34 -> 111097.04 | P19: =ECONOMIA!G$26*C19/$C$6*(1+ENTRADAS!$C$27)^(14-1) -> 12368.587 | Q19: =Q18+P19 -> 118622.11 | R19: =Q19-COMPARATIVO!G$34 -> 97273.202 | S19: =ECONOMIA!H$26*C19/$C$6*(1+ENTRADAS!$C$27)^(14-1) -> 10691.551 | T19: =T18+S19 -> 102538.33 | U19: =T19-COMPARATIVO!H$34 -> 87650.692 | V19: =ECONOMIA!I$26*C19/$C$6*(1+ENTRADAS!$C$27)^(14-1) -> 13637.142 | W19: =W18+V19 -> 130788.31 | X19: =W19-COMPARATIVO!I$34 -> 109707.77 | Y19: =ECONOMIA!J$26*C19/$C$6*(1+ENTRADAS!$C$27)^(14-1) -> 13563.798 | Z19: =Z18+Y19 -> 130084.89 | AA19: =Z19-COMPARATIVO!J$34 -> 108851.89 | AB19: =ECONOMIA!K$26*C19/$C$6*(1+ENTRADAS!$C$27)^(14-1) -> 13637.142 | AC19: =AC18+AB19 -> 130788.31 | AD19: =AC19-COMPARATIVO!K$34 -> 111398.31 | AE19: =ECONOMIA!L$26*C19/$C$6*(1+ENTRADAS!$C$27)^(14-1) -> 13610.066 | AF19: =AF18+AE19 -> 130528.63 | AG19: =AF19-COMPARATIVO!L$34 -> 111828.63 | AH19: =ECONOMIA!M$26*C19/$C$6*(1+ENTRADAS!$C$27)^(14-1) -> 13637.142 | AI19: =AI18+AH19 -> 130788.31 | AJ19: =AI19-COMPARATIVO!M$34 -> 107907.77 | AK19: =ECONOMIA!N$26*C19/$C$6*(1+ENTRADAS!$C$27)^(14-1) -> 13637.142 | AL19: =AL18+AK19 -> 130788.31 | AM19: =AL19-COMPARATIVO!N$34 -> 106107.77
B20: 15 | C20: =(1-ENTRADAS!$C$33)*(1-ENTRADAS!$C$34)^(15-1) -> 0.92003379 | D20: =ECONOMIA!C$26*C20/$C$6*(1+ENTRADAS!$C$27)^(15-1) -> 14526.08 | E20: =E19+D20 -> 145314.39 | F20: =E20-COMPARATIVO!C$34 -> 115515.69 | G20: =ECONOMIA!D$26*C20/$C$6*(1+ENTRADAS!$C$27)^(15-1) -> 14526.08 | H20: =H19+G20 -> 145314.39 | I20: =H20-COMPARATIVO!D$34 -> 116436.49 | J20: =ECONOMIA!E$26*C20/$C$6*(1+ENTRADAS!$C$27)^(15-1) -> 14507.095 | K20: =K19+J20 -> 145124.48 | L20: =K20-COMPARATIVO!E$34 -> 126604.14 | M20: =ECONOMIA!F$26*C20/$C$6*(1+ENTRADAS!$C$27)^(15-1) -> 14507.095 | N20: =N19+M20 -> 145124.48 | O20: =N20-COMPARATIVO!F$34 -> 125604.14 | P20: =ECONOMIA!G$26*C20/$C$6*(1+ENTRADAS!$C$27)^(15-1) -> 13174.834 | Q20: =Q19+P20 -> 131796.95 | R20: =Q20-COMPARATIVO!G$34 -> 110448.04 | S20: =ECONOMIA!H$26*C20/$C$6*(1+ENTRADAS!$C$27)^(15-1) -> 11388.479 | T20: =T19+S20 -> 113926.81 | U20: =T20-COMPARATIVO!H$34 -> 99039.171 | V20: =ECONOMIA!I$26*C20/$C$6*(1+ENTRADAS!$C$27)^(15-1) -> 14526.08 | W20: =W19+V20 -> 145314.39 | X20: =W20-COMPARATIVO!I$34 -> 124233.85 | Y20: =ECONOMIA!J$26*C20/$C$6*(1+ENTRADAS!$C$27)^(15-1) -> 14447.954 | Z20: =Z19+Y20 -> 144532.84 | AA20: =Z20-COMPARATIVO!J$34 -> 123299.84 | AB20: =ECONOMIA!K$26*C20/$C$6*(1+ENTRADAS!$C$27)^(15-1) -> 14526.08 | AC20: =AC19+AB20 -> 145314.39 | AD20: =AC20-COMPARATIVO!K$34 -> 125924.39 | AE20: =ECONOMIA!L$26*C20/$C$6*(1+ENTRADAS!$C$27)^(15-1) -> 14497.239 | AF20: =AF19+AE20 -> 145025.87 | AG20: =AF20-COMPARATIVO!L$34 -> 126325.87 | AH20: =ECONOMIA!M$26*C20/$C$6*(1+ENTRADAS!$C$27)^(15-1) -> 14526.08 | AI20: =AI19+AH20 -> 145314.39 | AJ20: =AI20-COMPARATIVO!M$34 -> 122433.85 | AK20: =ECONOMIA!N$26*C20/$C$6*(1+ENTRADAS!$C$27)^(15-1) -> 14526.08 | AL20: =AL19+AK20 -> 145314.39 | AM20: =AL20-COMPARATIVO!N$34 -> 120633.85
B21: 16 | C21: =(1-ENTRADAS!$C$33)*(1-ENTRADAS!$C$34)^(16-1) -> 0.91589364 | D21: =ECONOMIA!C$26*C21/$C$6*(1+ENTRADAS!$C$27)^(16-1) -> 15472.962 | E21: =E20+D21 -> 160787.35 | F21: =E21-COMPARATIVO!C$34 -> 130988.65 | G21: =ECONOMIA!D$26*C21/$C$6*(1+ENTRADAS!$C$27)^(16-1) -> 15472.962 | H21: =H20+G21 -> 160787.35 | I21: =H21-COMPARATIVO!D$34 -> 131909.45 | J21: =ECONOMIA!E$26*C21/$C$6*(1+ENTRADAS!$C$27)^(16-1) -> 15452.741 | K21: =K20+J21 -> 160577.22 | L21: =K21-COMPARATIVO!E$34 -> 142056.88 | M21: =ECONOMIA!F$26*C21/$C$6*(1+ENTRADAS!$C$27)^(16-1) -> 15452.741 | N21: =N20+M21 -> 160577.22 | O21: =N21-COMPARATIVO!F$34 -> 141056.88 | P21: =ECONOMIA!G$26*C21/$C$6*(1+ENTRADAS!$C$27)^(16-1) -> 14033.635 | Q21: =Q20+P21 -> 145830.58 | R21: =Q21-COMPARATIVO!G$34 -> 124481.67 | S21: =ECONOMIA!H$26*C21/$C$6*(1+ENTRADAS!$C$27)^(16-1) -> 12130.837 | T21: =T20+S21 -> 126057.65 | U21: =T21-COMPARATIVO!H$34 -> 111170.01 | V21: =ECONOMIA!I$26*C21/$C$6*(1+ENTRADAS!$C$27)^(16-1) -> 15472.962 | W21: =W20+V21 -> 160787.35 | X21: =W21-COMPARATIVO!I$34 -> 139706.81 | Y21: =ECONOMIA!J$26*C21/$C$6*(1+ENTRADAS!$C$27)^(16-1) -> 15389.744 | Z21: =Z20+Y21 -> 159922.59 | AA21: =Z21-COMPARATIVO!J$34 -> 138689.59 | AB21: =ECONOMIA!K$26*C21/$C$6*(1+ENTRADAS!$C$27)^(16-1) -> 15472.962 | AC21: =AC20+AB21 -> 160787.35 | AD21: =AC21-COMPARATIVO!K$34 -> 141397.35 | AE21: =ECONOMIA!L$26*C21/$C$6*(1+ENTRADAS!$C$27)^(16-1) -> 15442.241 | AF21: =AF20+AE21 -> 160468.11 | AG21: =AF21-COMPARATIVO!L$34 -> 141768.11 | AH21: =ECONOMIA!M$26*C21/$C$6*(1+ENTRADAS!$C$27)^(16-1) -> 15472.962 | AI21: =AI20+AH21 -> 160787.35 | AJ21: =AI21-COMPARATIVO!M$34 -> 137906.81 | AK21: =ECONOMIA!N$26*C21/$C$6*(1+ENTRADAS!$C$27)^(16-1) -> 15472.962 | AL21: =AL20+AK21 -> 160787.35 | AM21: =AL21-COMPARATIVO!N$34 -> 136106.81
B22: 17 | C22: =(1-ENTRADAS!$C$33)*(1-ENTRADAS!$C$34)^(17-1) -> 0.91177211 | D22: =ECONOMIA!C$26*C22/$C$6*(1+ENTRADAS!$C$27)^(17-1) -> 16481.567 | E22: =E21+D22 -> 177268.92 | F22: =E22-COMPARATIVO!C$34 -> 147470.22 | G22: =ECONOMIA!D$26*C22/$C$6*(1+ENTRADAS!$C$27)^(17-1) -> 16481.567 | H22: =H21+G22 -> 177268.92 | I22: =H22-COMPARATIVO!D$34 -> 148391.02 | J22: =ECONOMIA!E$26*C22/$C$6*(1+ENTRADAS!$C$27)^(17-1) -> 16460.027 | K22: =K21+J22 -> 177037.25 | L22: =K22-COMPARATIVO!E$34 -> 158516.91 | M22: =ECONOMIA!F$26*C22/$C$6*(1+ENTRADAS!$C$27)^(17-1) -> 16460.027 | N22: =N21+M22 -> 177037.25 | O22: =N22-COMPARATIVO!F$34 -> 157516.91 | P22: =ECONOMIA!G$26*C22/$C$6*(1+ENTRADAS!$C$27)^(17-1) -> 14948.418 | Q22: =Q21+P22 -> 160779 | R22: =Q22-COMPARATIVO!G$34 -> 139430.09 | S22: =ECONOMIA!H$26*C22/$C$6*(1+ENTRADAS!$C$27)^(17-1) -> 12921.586 | T22: =T21+S22 -> 138979.23 | U22: =T22-COMPARATIVO!H$34 -> 124091.59 | V22: =ECONOMIA!I$26*C22/$C$6*(1+ENTRADAS!$C$27)^(17-1) -> 16481.567 | W22: =W21+V22 -> 177268.92 | X22: =W22-COMPARATIVO!I$34 -> 156188.38 | Y22: =ECONOMIA!J$26*C22/$C$6*(1+ENTRADAS!$C$27)^(17-1) -> 16392.924 | Z22: =Z21+Y22 -> 176315.51 | AA22: =Z22-COMPARATIVO!J$34 -> 155082.51 | AB22: =ECONOMIA!K$26*C22/$C$6*(1+ENTRADAS!$C$27)^(17-1) -> 16481.567 | AC22: =AC21+AB22 -> 177268.92 | AD22: =AC22-COMPARATIVO!K$34 -> 157878.92 | AE22: =ECONOMIA!L$26*C22/$C$6*(1+ENTRADAS!$C$27)^(17-1) -> 16448.843 | AF22: =AF21+AE22 -> 176916.96 | AG22: =AF22-COMPARATIVO!L$34 -> 158216.96 | AH22: =ECONOMIA!M$26*C22/$C$6*(1+ENTRADAS!$C$27)^(17-1) -> 16481.567 | AI22: =AI21+AH22 -> 177268.92 | AJ22: =AI22-COMPARATIVO!M$34 -> 154388.38 | AK22: =ECONOMIA!N$26*C22/$C$6*(1+ENTRADAS!$C$27)^(17-1) -> 16481.567 | AL22: =AL21+AK22 -> 177268.92 | AM22: =AL22-COMPARATIVO!N$34 -> 152588.38
B23: 18 | C23: =(1-ENTRADAS!$C$33)*(1-ENTRADAS!$C$34)^(18-1) -> 0.90766914 | D23: =ECONOMIA!C$26*C23/$C$6*(1+ENTRADAS!$C$27)^(18-1) -> 17555.918 | E23: =E22+D23 -> 194824.84 | F23: =E23-COMPARATIVO!C$34 -> 165026.14 | G23: =ECONOMIA!D$26*C23/$C$6*(1+ENTRADAS!$C$27)^(18-1) -> 17555.918 | H23: =H22+G23 -> 194824.84 | I23: =H23-COMPARATIVO!D$34 -> 165946.94 | J23: =ECONOMIA!E$26*C23/$C$6*(1+ENTRADAS!$C$27)^(18-1) -> 17532.974 | K23: =K22+J23 -> 194570.22 | L23: =K23-COMPARATIVO!E$34 -> 176049.88 | M23: =ECONOMIA!F$26*C23/$C$6*(1+ENTRADAS!$C$27)^(18-1) -> 17532.974 | N23: =N22+M23 -> 194570.22 | O23: =N23-COMPARATIVO!F$34 -> 175049.88 | P23: =ECONOMIA!G$26*C23/$C$6*(1+ENTRADAS!$C$27)^(18-1) -> 15922.83 | Q23: =Q22+P23 -> 176701.83 | R23: =Q23-COMPARATIVO!G$34 -> 155352.92 | S23: =ECONOMIA!H$26*C23/$C$6*(1+ENTRADAS!$C$27)^(18-1) -> 13763.88 | T23: =T22+S23 -> 152743.11 | U23: =T23-COMPARATIVO!H$34 -> 137855.47 | V23: =ECONOMIA!I$26*C23/$C$6*(1+ENTRADAS!$C$27)^(18-1) -> 17555.918 | W23: =W22+V23 -> 194824.84 | X23: =W23-COMPARATIVO!I$34 -> 173744.3 | Y23: =ECONOMIA!J$26*C23/$C$6*(1+ENTRADAS!$C$27)^(18-1) -> 17461.497 | Z23: =Z22+Y23 -> 193777.01 | AA23: =Z23-COMPARATIVO!J$34 -> 172544.01 | AB23: =ECONOMIA!K$26*C23/$C$6*(1+ENTRADAS!$C$27)^(18-1) -> 17555.918 | AC23: =AC22+AB23 -> 194824.84 | AD23: =AC23-COMPARATIVO!K$34 -> 175434.84 | AE23: =ECONOMIA!L$26*C23/$C$6*(1+ENTRADAS!$C$27)^(18-1) -> 17521.061 | AF23: =AF22+AE23 -> 194438.02 | AG23: =AF23-COMPARATIVO!L$34 -> 175738.02 | AH23: =ECONOMIA!M$26*C23/$C$6*(1+ENTRADAS!$C$27)^(18-1) -> 17555.918 | AI23: =AI22+AH23 -> 194824.84 | AJ23: =AI23-COMPARATIVO!M$34 -> 171944.3 | AK23: =ECONOMIA!N$26*C23/$C$6*(1+ENTRADAS!$C$27)^(18-1) -> 17555.918 | AL23: =AL22+AK23 -> 194824.84 | AM23: =AL23-COMPARATIVO!N$34 -> 170144.3
B24: 19 | C24: =(1-ENTRADAS!$C$33)*(1-ENTRADAS!$C$34)^(19-1) -> 0.90358463 | D24: =ECONOMIA!C$26*C24/$C$6*(1+ENTRADAS!$C$27)^(19-1) -> 18700.301 | E24: =E23+D24 -> 213525.14 | F24: =E24-COMPARATIVO!C$34 -> 183726.44 | G24: =ECONOMIA!D$26*C24/$C$6*(1+ENTRADAS!$C$27)^(19-1) -> 18700.301 | H24: =H23+G24 -> 213525.14 | I24: =H24-COMPARATIVO!D$34 -> 184647.24 | J24: =ECONOMIA!E$26*C24/$C$6*(1+ENTRADAS!$C$27)^(19-1) -> 18675.861 | K24: =K23+J24 -> 213246.08 | L24: =K24-COMPARATIVO!E$34 -> 194725.74 | M24: =ECONOMIA!F$26*C24/$C$6*(1+ENTRADAS!$C$27)^(19-1) -> 18675.861 | N24: =N23+M24 -> 213246.08 | O24: =N24-COMPARATIVO!F$34 -> 193725.74 | P24: =ECONOMIA!G$26*C24/$C$6*(1+ENTRADAS!$C$27)^(19-1) -> 16960.76 | Q24: =Q23+P24 -> 193662.59 | R24: =Q24-COMPARATIVO!G$34 -> 172313.68 | S24: =ECONOMIA!H$26*C24/$C$6*(1+ENTRADAS!$C$27)^(19-1) -> 14661.078 | T24: =T23+S24 -> 167404.19 | U24: =T24-COMPARATIVO!H$34 -> 152516.55 | V24: =ECONOMIA!I$26*C24/$C$6*(1+ENTRADAS!$C$27)^(19-1) -> 18700.301 | W24: =W23+V24 -> 213525.14 | X24: =W24-COMPARATIVO!I$34 -> 192444.6 | Y24: =ECONOMIA!J$26*C24/$C$6*(1+ENTRADAS!$C$27)^(19-1) -> 18599.724 | Z24: =Z23+Y24 -> 212376.73 | AA24: =Z24-COMPARATIVO!J$34 -> 191143.73 | AB24: =ECONOMIA!K$26*C24/$C$6*(1+ENTRADAS!$C$27)^(19-1) -> 18700.301 | AC24: =AC23+AB24 -> 213525.14 | AD24: =AC24-COMPARATIVO!K$34 -> 194135.14 | AE24: =ECONOMIA!L$26*C24/$C$6*(1+ENTRADAS!$C$27)^(19-1) -> 18663.172 | AF24: =AF23+AE24 -> 213101.19 | AG24: =AF24-COMPARATIVO!L$34 -> 194401.19 | AH24: =ECONOMIA!M$26*C24/$C$6*(1+ENTRADAS!$C$27)^(19-1) -> 18700.301 | AI24: =AI23+AH24 -> 213525.14 | AJ24: =AI24-COMPARATIVO!M$34 -> 190644.6 | AK24: =ECONOMIA!N$26*C24/$C$6*(1+ENTRADAS!$C$27)^(19-1) -> 18700.301 | AL24: =AL23+AK24 -> 213525.14 | AM24: =AL24-COMPARATIVO!N$34 -> 188844.6
B25: 20 | C25: =(1-ENTRADAS!$C$33)*(1-ENTRADAS!$C$34)^(20-1) -> 0.8995185 | D25: =ECONOMIA!C$26*C25/$C$6*(1+ENTRADAS!$C$27)^(20-1) -> 19919.28 | E25: =E24+D25 -> 233444.42 | F25: =E25-COMPARATIVO!C$34 -> 203645.72 | G25: =ECONOMIA!D$26*C25/$C$6*(1+ENTRADAS!$C$27)^(20-1) -> 19919.28 | H25: =H24+G25 -> 233444.42 | I25: =H25-COMPARATIVO!D$34 -> 204566.52 | J25: =ECONOMIA!E$26*C25/$C$6*(1+ENTRADAS!$C$27)^(20-1) -> 19893.247 | K25: =K24+J25 -> 233139.33 | L25: =K25-COMPARATIVO!E$34 -> 214618.99 | M25: =ECONOMIA!F$26*C25/$C$6*(1+ENTRADAS!$C$27)^(20-1) -> 19893.247 | N25: =N24+M25 -> 233139.33 | O25: =N25-COMPARATIVO!F$34 -> 213618.99 | P25: =ECONOMIA!G$26*C25/$C$6*(1+ENTRADAS!$C$27)^(20-1) -> 18066.347 | Q25: =Q24+P25 -> 211728.94 | R25: =Q25-COMPARATIVO!G$34 -> 190380.03 | S25: =ECONOMIA!H$26*C25/$C$6*(1+ENTRADAS!$C$27)^(20-1) -> 15616.76 | T25: =T24+S25 -> 183020.95 | U25: =T25-COMPARATIVO!H$34 -> 168133.31 | V25: =ECONOMIA!I$26*C25/$C$6*(1+ENTRADAS!$C$27)^(20-1) -> 19919.28 | W25: =W24+V25 -> 233444.42 | X25: =W25-COMPARATIVO!I$34 -> 212363.88 | Y25: =ECONOMIA!J$26*C25/$C$6*(1+ENTRADAS!$C$27)^(20-1) -> 19812.147 | Z25: =Z24+Y25 -> 232188.88 | AA25: =Z25-COMPARATIVO!J$34 -> 210955.88 | AB25: =ECONOMIA!K$26*C25/$C$6*(1+ENTRADAS!$C$27)^(20-1) -> 19919.28 | AC25: =AC24+AB25 -> 233444.42 | AD25: =AC25-COMPARATIVO!K$34 -> 214054.42 | AE25: =ECONOMIA!L$26*C25/$C$6*(1+ENTRADAS!$C$27)^(20-1) -> 19879.731 | AF25: =AF24+AE25 -> 232980.92 | AG25: =AF25-COMPARATIVO!L$34 -> 214280.92 | AH25: =ECONOMIA!M$26*C25/$C$6*(1+ENTRADAS!$C$27)^(20-1) -> 19919.28 | AI25: =AI24+AH25 -> 233444.42 | AJ25: =AI25-COMPARATIVO!M$34 -> 210563.88 | AK25: =ECONOMIA!N$26*C25/$C$6*(1+ENTRADAS!$C$27)^(20-1) -> 19919.28 | AL25: =AL24+AK25 -> 233444.42 | AM25: =AL25-COMPARATIVO!N$34 -> 208763.88
B27: Anos 5, 10 e 20 destacados. As colunas 'Fluxo' viram positivas no ano do payback ja corrigido por inflacao e degradacao.
B28: Nao inclui: troca do inversor no ano ~13 (provisionada em R$ 150/ano na aba ECONOMIA), reajustes de bandeira tarifaria,
B29: nem a mudanca da regra do Fio B (60% em 2026 -> 100% em 2029), que reduz a economia dos anos seguintes.
B30: Por isso o payback real tende a ser um pouco pior que o calculado, e o carregamento diurno do BYD fica cada vez mais vantajoso.

Sheet SIMULACAO_MENSAL
A1: SIMULACAO MES A MES - CONSUMO x GERACAO x BANCO DE CREDITOS
A2: Consumo da residencia = historico REAL da conta. Geracao com sazonalidade real (nao e media achatada).
B4: Potencia simulada (kWp): | C4: 6.2 | D4: <- edite para testar outra potencia (6,20 = SunWash / 7,38 = TecSolarSP / 5,35 = William)
B6: Mes | C6: Residencia (kWh) | D6: BYD (kWh) | E6: Consumo total (kWh) | F6: Geracao solar (kWh) | G6: Saldo do mes (kWh) | H6: Banco de creditos (kWh) | I6: Situacao
B7: Jan | C7: =CONTA!C38 -> 372 | D7: =BYD!$C$13 -> 225 | E7: =C7+D7 -> 597 | F7: =$C$4*GERACAO!I5 -> 780.59916 | G7: =F7-E7 -> 183.59916 | H7: =MAX(0,G7) -> 183.59916 | I7: =IF(G7>=0,"Sobra - acumula credito","Falta - usa credito ou compra da rede") -> Sobra - acumula credito
B8: Fev | C8: =CONTA!C39 -> 348 | D8: =BYD!$C$13 -> 225 | E8: =C8+D8 -> 573 | F8: =$C$4*GERACAO!I6 -> 710.9545 | G8: =F8-E8 -> 137.9545 | H8: =MAX(0,H7+G8) -> 321.55365 | I8: =IF(G8>=0,"Sobra - acumula credito","Falta - usa credito ou compra da rede") -> Sobra - acumula credito
B9: Mar | C9: =CONTA!C40 -> 354 | D9: =BYD!$C$13 -> 225 | E9: =C9+D9 -> 579 | F9: =$C$4*GERACAO!I7 -> 706.80589 | G9: =F9-E9 -> 127.80589 | H9: =MAX(0,H8+G9) -> 449.35954 | I9: =IF(G9>=0,"Sobra - acumula credito","Falta - usa credito ou compra da rede") -> Sobra - acumula credito
B10: Abr | C10: =CONTA!C41 -> 394 | D10: =BYD!$C$13 -> 225 | E10: =C10+D10 -> 619 | F10: =$C$4*GERACAO!I8 -> 607.74384 | G10: =F10-E10 -> -11.25616 | H10: =MAX(0,H9+G10) -> 438.10338 | I10: =IF(G10>=0,"Sobra - acumula credito","Falta - usa credito ou compra da rede") -> Falta - usa credito ou compra da rede
B11: Mai | C11: =CONTA!C42 -> 457 | D11: =BYD!$C$13 -> 225 | E11: =C11+D11 -> 682 | F11: =$C$4*GERACAO!I9 -> 516.85655 | G11: =F11-E11 -> -165.14345 | H11: =MAX(0,H10+G11) -> 272.95994 | I11: =IF(G11>=0,"Sobra - acumula credito","Falta - usa credito ou compra da rede") -> Falta - usa credito ou compra da rede
B12: Jun | C12: =CONTA!C43 -> 422 | D12: =BYD!$C$13 -> 225 | E12: =C12+D12 -> 647 | F12: =$C$4*GERACAO!I10 -> 468.0039 | G12: =F12-E12 -> -178.9961 | H12: =MAX(0,H11+G12) -> 93.963836 | I12: =IF(G12>=0,"Sobra - acumula credito","Falta - usa credito ou compra da rede") -> Falta - usa credito ou compra da rede
B13: Jul | C13: =CONTA!C44 -> 540 | D13: =BYD!$C$13 -> 225 | E13: =C13+D13 -> 765 | F13: =$C$4*GERACAO!I11 -> 504.32992 | G13: =F13-E13 -> -260.67008 | H13: =MAX(0,H12+G13) -> 0 | I13: =IF(G13>=0,"Sobra - acumula credito","Falta - usa credito ou compra da rede") -> Falta - usa credito ou compra da rede
B14: Ago | C14: =CONTA!C45 -> 364 | D14: =BYD!$C$13 -> 225 | E14: =C14+D14 -> 589 | F14: =$C$4*GERACAO!I12 -> 642.5025 | G14: =F14-E14 -> 53.502497 | H14: =MAX(0,H13+G14) -> 53.502497 | I14: =IF(G14>=0,"Sobra - acumula credito","Falta - usa credito ou compra da rede") -> Sobra - acumula credito
B15: Set | C15: =CONTA!C46 -> 290 | D15: =BYD!$C$13 -> 225 | E15: =C15+D15 -> 515 | F15: =$C$4*GERACAO!I13 -> 621.18885 | G15: =F15-E15 -> 106.18885 | H15: =MAX(0,H14+G15) -> 159.69135 | I15: =IF(G15>=0,"Sobra - acumula credito","Falta - usa credito ou compra da rede") -> Sobra - acumula credito
B16: Out | C16: =CONTA!C47 -> 375 | D16: =BYD!$C$13 -> 225 | E16: =C16+D16 -> 600 | F16: =$C$4*GERACAO!I14 -> 714.24595 | G16: =F16-E16 -> 114.24595 | H16: =MAX(0,H15+G16) -> 273.9373 | I16: =IF(G16>=0,"Sobra - acumula credito","Falta - usa credito ou compra da rede") -> Sobra - acumula credito
B17: Nov | C17: =CONTA!C48 -> 337 | D17: =BYD!$C$13 -> 225 | E17: =C17+D17 -> 562 | F17: =$C$4*GERACAO!I15 -> 762.54513 | G17: =F17-E17 -> 200.54513 | H17: =MAX(0,H16+G17) -> 474.48243 | I17: =IF(G17>=0,"Sobra - acumula credito","Falta - usa credito ou compra da rede") -> Sobra - acumula credito
B18: Dez | C18: =CONTA!C49 -> 323 | D18: =BYD!$C$13 -> 225 | E18: =C18+D18 -> 548 | F18: =$C$4*GERACAO!I16 -> 802.69159 | G18: =F18-E18 -> 254.69159 | H18: =MAX(0,H17+G18) -> 729.17402 | I18: =IF(G18>=0,"Sobra - acumula credito","Falta - usa credito ou compra da rede") -> Sobra - acumula credito
B19: ANO | C19: =SUM(C7:C18) -> 4576 | D19: =SUM(D7:D18) -> 2700 | E19: =SUM(E7:E18) -> 7276 | F19: =SUM(F7:F18) -> 7838.4678 | G19: =SUM(G7:G18) -> 562.46777
B21: COMO LER ESTA ABA:
B22: Os meses de maio a julho ficam negativos - inverno somado a telhado Sudeste, que perde mais justamente no inverno.
B23: Isso e normal e esperado. O excedente de outubro a marco forma o banco de creditos que cobre o inverno.
B24: O que importa e o SALDO ANUAL da coluna G, linha 19, ficar proximo de zero ou levemente positivo.
B25: Saldo anual muito positivo = voce pagou por placas que geram credito que vai expirar em 60 meses sem ser usado.
B26: Saldo anual negativo = voce vai continuar comprando energia da Enel todo mes, com tarifa cheia.
B28: OBSERVACAO SOBRE O CONSUMO DA RESIDENCIA: os valores vem do historico real, que ja mostra tendencia de alta de ~22%.
B29: Se o consumo continuar subindo, o deficit dos meses de inverno sera maior do que o mostrado aqui.

Sheet CHECKLIST
A1: CHECKLIST - O QUE EXIGIR ANTES DE ASSINAR QUALQUER CONTRATO
A2: Itens em vermelho sao alertas ja identificados nos documentos recebidos. Preencha STATUS e a resposta de cada fornecedor.
B4: # | C4: PONTO A VERIFICAR | D4: STATUS | E4: RESPOSTA DO FORNECEDOR
C5: 1) BLOQUEADORES - RESOLVER ANTES DE QUALQUER COMPRA
B6: 1 | C6: PADRAO MONOFASICO x INVERSOR DE 220 V. A conta indica fornecimento monofasico (127 V na Enel SP) e os quatro orcamentos usam inversor de 220 V, que precisa de 2 fases. Exigir de cada fornecedor: quem faz o pedido de alteracao de padrao na Enel, quanto custa, quanto tempo leva e se esta no preco. | D6: Pendente
B7: 2 | C7: TIPO DA TELHA CONTRADITORIO. TecSolarSP cotou estrutura para FIBROCIMENTO e William cotou gancho para telha COLONIAL. Sao estruturas totalmente diferentes. Descobrir qual e a telha real - se um deles errou, nao visitou o telhado. | D7: Pendente
B8: 3 | C8: GERACAO CALCULADA COMO SE O TELHADO FOSSE NORTE. TecSolarSP promete 1.430 kWh/kWp em telhado que ela mesma declara Sudeste. SunWash escreve 'calculo considerando norte do telhado'. Exigir simulacao com o azimute e a inclinacao REAIS, em PVsol, PVsyst ou Solergo, com relatorio em PDF. | D8: Pendente
B9: 4 | C9: NENHUM ORCAMENTO CONSIDEROU O BYD. Informar a todos que havera carregamento diario do veiculo e pedir redimensionamento. A proposta do William (5,35 kWp) fica subdimensionada e o inversor Solis de 4 kW nao permite ampliar depois. | D9: Pendente
C10: 1-sexies) SOBRE A AD BIOSOLAR (opcao J) - E A VERIFICACAO MAIS IMPORTANTE DE TODAS
B11: 5 | C11: PONTOS FORTES: unica que informou o MODELO EXATO do inversor (Huawei SUN2000-5KTL-L1); modulo JA Solar Tier 1 com 30 anos de garantia de eficiencia e 15 de defeito; inversor com 10 anos de garantia; CNPJ na proposta; vistoria tecnica, ART, licencas, gestao de obra e frete no escopo; unica a informar o peso por m2 (8,33 kg/m2), dado que importa em telhado ceramico. | D11: Pendente
B12: 6 | C12: AGORA DA PARA FECHAR A CONTA QUE ESTAVA ABERTA: baixe a ficha tecnica do Huawei SUN2000-5KTL-L1 e a do modulo JA Solar de 615 W e compare a CORRENTE MAXIMA DE ENTRADA POR MPPT do inversor com a CORRENTE DE OPERACAO (Impp) do modulo. Modulos de 615 W nesse formato tem Impp na faixa de 16 A. Varias versoes da linha SUN2000-L1 aceitam de 12,5 a 13,5 A por MPPT. Se a corrente do modulo for maior que a do MPPT, o inversor NAO consegue extrair toda a potencia nas melhores horas do dia - perda permanente que nenhuma simulacao mostra. | D12: Pendente
B13: 7 | C13: ESSA MESMA VERIFICACAO VALE PARA AS OPCOES A, B, C, D e I, que usam modulos de 605 a 620 W. Exigir de cada fornecedor o PROJETO DE STRING por escrito: quantos modulos em serie por MPPT, tensao minima e maxima nas temperaturas extremas, e a corrente por MPPT comparada ao limite do inversor. Fornecedor que nao souber responder isso nao fez projeto - fez lista de compras. | D13: Pendente
B14: 8 | C14: AD BIOSOLAR CORRIGIU A PROPOSTA (#01237 de 12/08): subiu de 8 para 10 modulos e de 4,92 para 6,15 kWp, trocou o inversor do SUN2000-5KTL-L1 para o 6KTL-L1 de 6 kW, e passou a dimensionar com 650 kWh/mes em vez de 460. Com o valor negociado de R$ 16.200 ela sai a R$ 2,63/Wp - deixou de ser a mais cara e passou a ser uma das mais baratas, com o melhor equipamento do conjunto. | D14: Pendente
B15: 9 | C15: O DESCONTO DE R$ 5.089 PRECISA ESTAR NO PAPEL. O PDF #01237 traz R$ 21.289,00; o valor de R$ 16.200,00 veio da negociacao. Sao 24% de desconto. Exigir proposta reemitida com o valor final, ou o desconto pode nao existir na assinatura. | D15: Pendente
B16: 10 | C16: VERIFICACAO OBRIGATORIA NA AD BIOSOLAR: 10 modulos JA Solar de 615 W em um SUN2000-6KTL-L1 de 2 MPPTs dao 5 modulos por string. Confirmar na ficha tecnica do inversor a corrente maxima de entrada por MPPT e comparar com o Impp do modulo (~16 A). Se a do inversor for menor, perde-se geracao nas melhores horas. Pedir tambem a tensao da string nas temperaturas extremas. | D16: Pendente
B17: 11 | C17: NUMEROS DE MARKETING DA AD BIOSOLAR: 'Economia total em 25 anos R$ 419.713,53', 'ROI 24,06 vezes' e 'TIR 35,81%' usam reajuste de energia de 10% ao ano composto por 25 anos. Ignore. Alem disso a 'conta COM sistema de R$ 75,31/mes' vale para 460 kWh/mes SEM o carro - com o BYD o meu modelo da cerca de R$ 259/mes nessa potencia. | D17: Pendente
B18: 12 | C18: TRES VENDEDORES USARAM TRES CONSUMOS DIFERENTES: William usou 381 kWh/mes (a media real da conta), AD BioSolar usou 460 e Sfero usou 600. Nenhum deles explicou de onde veio o numero. Padronize: mande para TODOS o mesmo dado - 381 kWh/mes de historico MAIS 206 kWh/mes do BYD - e peca que refacam. So assim os orcamentos ficam comparaveis. | D18: Pendente
B20: 13 | C20: CORRENTE DO MODULO x CORRENTE MAXIMA DO MPPT. Modulos de 605 a 615 W tem corrente de operacao na faixa de 14 a 17 A. Inversores residenciais da linha Huawei SUN2000-L1 costumam aceitar de 12,5 a 13,5 A por MPPT. Se a corrente do modulo ultrapassar a do inversor, perde-se geracao nas melhores horas. Exigir as duas fichas tecnicas e o calculo da string. | D20: Pendente
B21: 14 | C21: STRING CURTA DE 6 MODULOS. A tensao de operacao fica na faixa de 200 a 225 V. Em dia quente a tensao cai e pode sair da faixa de potencia plena do MPPT. Exigir o projeto de string com temperatura minima e maxima. | D21: Pendente
B22: 15 | C22: FALTA PROTECAO CA nas duas cotacoes da TecSolarSP: sem DPS CA e sem disjuntor dedicado do inversor. So o William incluiu DPS (3 pecas Clamper classe II). Item obrigatorio pela NBR 5410. | D22: Pendente
B23: 16 | C23: FALTA CABO DE EQUIPOTENCIALIZACAO na cotacao Astronergy 605 W, e as garras de aterramento cairam de 6 para 3 jogos. Item de seguranca. | D23: Pendente
... B26: 19 | C26: 'INVERSOR HIBRIDO' NAO COMPROVADO. A peca publicitaria da TecSolarSP anuncia inversor HIBRIDO 6 kW, mas a cotacao traz 'INVHW-MO-220V-6KW'. Exigir o codigo completo do modelo e a confirmacao por escrito de que aceita bateria - hibrido e nao hibrido tem preco e funcao diferentes. | D26: Pendente
C27: 1-bis) PERGUNTAS ESPECIFICAS DA PROPOSTA COM MICROINVERSORES (opcao G)
B28: 20 | C28: RESPONDIDO: os microinversores sao DEYE SUN-S225G4-EU-Q0, 2,25 kW monofasico. A Deye e um dos maiores fabricantes do mundo e tem rede de assistencia estabelecida no Brasil. Isso resolve a principal duvida que havia sobre esta proposta. | D28: Pendente
B29: 21 | C29: CONSEQUENCIA 1 - CORRENTE: o sufixo Q0 indica 4 MPPTs por micro, e a linha G4 da Deye foi projetada para modulos de 600 a 700 W, com corrente por MPPT na casa de 20 A. Isso e folgado para os ~16 A de um modulo de 650 W. Ou seja: nesta proposta o risco de corte de corrente por MPPT NAO existe - diferente das propostas com inversor string e modulos de 605 a 620 W, onde a verificacao continua obrigatoria. CONFIRMAR na ficha tecnica do SUN-S225G4-EU-Q0. | D29: Pendente
B30: 22 | C30: CONSEQUENCIA 2 - EXPANSAO: 4 micros x 4 MPPTs = 16 canais para 10 modulos = 6 CANAIS LIVRES. Da para chegar a 16 modulos (10,4 kWp) sem comprar inversor, com DC/AC de 1,16. E a unica proposta do conjunto com folga real de expansao - e voce tem um consumo subindo 39% ao ano. | D30: Pendente
B31: 23 | C31: PERGUNTA QUE SOBROU: QUANTO CUSTA COM 3 MICROS EM VEZ DE 4? Tres micros dao 12 canais (10 usados, 2 livres) e 6,75 kW AC em vez de 9,0 kW. Duas vantagens: preco menor, e potencia homologada de 31 A em vez de 41 A, o que pode reduzir o custo do padrao de entrada. Vale so se voce NAO pretende passar de ~7,8 kWp no futuro. | D31: Pendente
B32: 24 | C32: EXIGIR A GARANTIA DA DEYE POR ESCRITO. A Deye pratica 10 anos de fabrica nos microinversores, com extensao opcional, mas o Yuri nao declarou nada. Sem estar no papel, nao vale. | D32: Pendente
B33: 25 | C33: RESPONDIDO: o modulo e ZNShine ZXNR-MD132-650, N-type, 650 W. A ZNShine e fabricante listada como Tier 1 pela Bloomberg NEF e atua desde os anos 1990. Com isso, os DOIS equipamentos desta proposta estao identificados e sao de fabricantes credenciados. | D33: Pendente
B34: 26 | C34: ESCLARECIMENTO IMPORTANTE SOBRE 'TIER 1': o selo Tier 1 da Bloomberg NEF mede BANCABILIDADE, ou seja, que bancos financiaram projetos com aquele fabricante. NAO e certificado de qualidade nem de eficiencia, e nao substitui o registro INMETRO. Exigir o INMETRO do modelo ZXNR-MD132-650 do mesmo jeito. | D34: Pendente
B35: 27 | C35: ESCLARECIMENTO SOBRE 'MONO': significa monocristalino, e nao monofacial. Se o modulo e bifacial ou nao precisa ser lido na ficha tecnica. Em telhado ceramico com modulo assentado proximo a telha o ganho bifacial e pequeno (1% a 2%), portanto isso quase nao muda a estimativa de geracao desta planilha. | D35: Pendente
B36: 28 | C36: AGORA SO FALTA PAPEL NESTA PROPOSTA: razao social e CNPJ da SunWash, garantias de modulo/inversor/instalacao por escrito em anos, escopo item a item, esclarecimento dos R$ 1.800 da regiao, e o tipo de telha considerado. Nenhuma pendencia tecnica restou. | D36: Pendente
B37: 29 | C37: PONTO A PESAR COM HONESTIDADE: a Deye domina o mercado brasileiro em inversor string e hibrido, mas a linha de MICROINVERSORES dela e mais recente no Brasil e tem menos historico de campo aqui do que os micros da Hoymiles ou APsystems. Nao e impedimento - e um dado a considerar, e reforca a exigencia da garantia por escrito. | D37: Pendente
B38: 30 | C38: QUAL A MARCA DO MODULO DE 650 W? O orcamento nao informa. 650 W e formato grande (cerca de 2,6 m2 por placa): confirmar que cabe na agua Sudeste e que o peso por m2 e compativel com o telhado. | D38: Pendente
B39: 31 | C39: QUANTOS MODULOS CADA MICROINVERSOR ACEITA? 4 micros de 2,25 kW dao 9 kW AC para 6,5 kWp de modulos (relacao 0,72). Se cada micro aceita 4 modulos, sao 16 canais para 10 modulos = 6 canais livres, o que e uma excelente folga de expansao. Se aceita menos, voce esta pagando por um micro desnecessario. Essa unica resposta muda a avaliacao da proposta. | D39: Pendente
... B42: 34 | C42: Vantagens tecnicas reais do microinversor no SEU caso: sombreamento nunca foi avaliado e o micro isola o problema por modulo; permite dividir os modulos em mais de uma agua do telhado (poderia recuperar parte dos 11% perdidos pela orientacao Sudeste); nao ha tensao alta de corrente continua no telhado; falha de um equipamento nao para o sistema todo. | D42: Pendente
C44: 1-quater) PERGUNTAS DA PROPOSTA SFERO (opcao H)
B45: 35 | C45: MARCA COM BARRA NAO E MARCA. A proposta diz 'Longi/ DAH Solar' e 'Solis/ Growatt', ou seja, um OU outro. Exigir por escrito qual modelo exato sera entregue ANTES de assinar - a diferenca entre Longi e DAH, e entre Solis e Growatt, e real em preco e em suporte. | D45: Pendente
B46: 36 | C46: 5,90 kWp COBRE SO 92% DO CENARIO 3. Pedir a versao com 12 modulos e 3 microinversores (7,08 kWp, DC/AC 0,94), que levaria a cobertura para ~110%, e comparar o preco. Com 2 micros de 2,5 kW nao da para so acrescentar modulos: 12 x 590 W daria DC/AC de 1,42, acima do limite. | D46: Pendente
B47: 37 | C47: 60% DE ENTRADA E RISCO ALTO. Sao R$ 11.240 pagos antes de qualquer equipamento chegar ao telhado. Negociar para 30-40% de entrada, ou exigir garantia contratual e nota fiscal do material no ato do pagamento. | D47: Pendente
B48: 38 | C48: A SFERO DIMENSIONOU COM 600 kWh/mes, e nao com os 381 kWh/mes reais da sua conta. Coincidentemente 600 e proximo do consumo COM o BYD (587). VOCE INFORMOU O CARRO PARA ELES? Se sim, e a unica empresa que considerou. Se nao, foi sorte - e vale confirmar de onde saiu esse numero. | D48: Pendente
B49: 39 | C49: PONTOS FORTES REAIS DA SFERO, que nenhuma outra tem: modulo Longi ou DAH (Tier 1 com rede no Brasil) E microinversor Solis ou Growatt (marcas estabelecidas); seguro All Risk de 1 ano cobrindo danos, furto e responsabilidade civil; garantia de performance e resultado em contrato desde o 1o ano; string box com protecoes e monitoramento WiFi ja no escopo; relacao DC/AC de 1,18, a melhor de todas. | D49: Pendente
C51: 1-quinquies) SOBRE A SUN COAST v2 (opcao I)
B52: 40 | C52: A Sun Coast CORRIGIU os dois defeitos apontados: a relacao DC/AC saiu de 1,56 para 0,91 e o inversor passou de 1 para 2 MPPTs, com 11 modulos em vez de 8. O preco marginal do acrescimo foi de R$ 2,10 por Wp, abaixo do preco medio dela - ou seja, foi um upgrade barato. Hoje tem o melhor R$/Wp de todos. | D52: Pendente
B53: 41 | C53: MAS AS MARCAS CONTINUAM SENDO TCL (modulo) E AUXSOL (inversor), ambas com pouquissima rede de assistencia no Brasil. Garantia de '10 a 25 anos' no inversor so vale se existir empresa para honrar em 2040. Exigir INMETRO, o representante no Brasil com CNPJ e o prazo de atendimento. | D53: Pendente
B54: 42 | C54: OS NUMEROS DE MARKETING SEGUEM INFLADOS: 'Retorno do investimento R$ 368.037,69' e 'Rendimento 40,69% ao ano' sobre um investimento de R$ 16.890. Meu calculo da cerca de R$ 219 mil de lucro em 20 anos, que ja e otimo. Ignore esses numeros e use a aba COMPARATIVO. | D54: Pendente
B55: 43 | C55: AUXSOL DE 7,5 kW SIGNIFICA 7,5 kW DECLARADOS NA HOMOLOGACAO = 34 A em 220 V. Isso pode exigir padrao de entrada maior (e mais caro) do que 6,82 kWp precisaria. Perguntar se um inversor de 6 kW nao serviria, com preco menor. | D55: Pendente
C57: 1-ter) DEMAIS BLOQUEADORES
B58: 44 | C58: SUN COAST: INVERSOR DE 3 kW PARA 4,68 kWp = RELACAO DC/AC DE 1,56. A faixa saudavel e 1,10 a 1,35. Nessa configuracao o inversor corta potencia (clipping) nas melhores horas do dia e a maioria dos fabricantes considera fora da garantia. Exigir do Alexandre o limite de sobrecarga do modelo AUXSOL cotado, por escrito, e a versao com inversor de 4 ou 5 kW. | D58: Pendente
B59: 45 | C59: SUN COAST: INVERSOR COM 1 MPPT UNICO. Os 8 modulos ficam numa unica string. Isso exige que todos estejam na MESMA agua, com mesma orientacao e inclinacao, e faz com que sombra em um unico modulo derrube a producao da string inteira. Se o telhado tiver mais de uma agua util, essa configuracao nao serve. | D59: Pendente
B60: 46 | C60: SUN COAST EXCLUI POR ESCRITO a adequacao do padrao de entrada, obras no telhado, eletrodutos e eletrocalhas, e o projeto estrutural com ART. E honesto declarar, mas o custo e seu: sao os R$ 2.500 (estimados) do padrao mais o que aparecer no telhado. Somar isso ao preco antes de comparar. | D60: Pendente
B61: 47 | C61: MODULO RONMA SOLAR - MARCA A INVESTIGAR. Praticamente sem presenca no Brasil. Exigir registro INMETRO do modelo exato, ficha tecnica e o nome/CNPJ de quem honra os 25 anos de garantia de eficiencia no Brasil. Garantia de 25 anos so vale se existir empresa para honrar. | D61: Pendente
B62: 48 | C62: TELHA: AGORA SAO DOIS CONTRA UM. William e Sun Coast cotaram TELHA COLONIAL; a TecSolarSP cotou FIBROCIMENTO. Se a telha for colonial, toda a estrutura das duas cotacoes da TecSolarSP esta errada (18 suportes pe em L de fibrocimento e hastes para madeira). Tirar uma foto do telhado resolve isso em 1 minuto. | D62: Pendente
B63: 49 | C63: MODULO TCL 620 W - MARCA A INVESTIGAR. A TCL/TCL Zhonghuan e gigante em wafer de silicio, mas a marca de MODULO tem pouca rede de assistencia no Brasil. Exigir: registro INMETRO do modelo exato, ficha tecnica, termos de garantia de produto e de performance, e QUEM honra a garantia no Brasil (importador ou representante com CNPJ). | D63: Pendente
B64: 50 | C64: INVERSOR AUXSOL - MARCA DE BAIXA PENETRACAO. O inversor e o componente que mais falha e o que sera trocado antes dos modulos. Por R$ 1.000 a mais a SunWash oferece HUAWEI, com garantia de fabrica maior, assistencia estabelecida e monitoramento maduro. RECOMENDACAO: pagar a diferenca e ficar com o Huawei. | D64: Pendente
B65: 51 | C65: INVERSOR DE 5 kW COM 6,20 kWp NAO DEIXA FOLGA DE EXPANSAO. O limite pratico de DC/AC de 1,35 da 6,75 kWp: nao cabe nem um modulo de 620 W a mais. Se a quilometragem do BYD crescer, sera preciso trocar o inversor e refazer a homologacao. Pedir a versao com inversor de 6 kW e comparar o preco. | D65: Pendente
B66: 52 | C66: SUNWASH PROMETE 700 kWh/mes PARA 6,20 kWp = 1.355 kWh por kWp ao ano. No seu telhado Sudeste o calculo da ~1.264. Diferenca de ~7%. Menos exagerado que a TecSolarSP, mas ainda otimista - exigir a simulacao com o azimute real. | D66: Pendente
B67: 53 | C67: O ACRESCIMO DE R$ 1.800 PELA REGIAO NAO FOI REPETIDO NO ORCAMENTO TCL. Confirmar por escrito se o preco de R$ 14.220,34 / R$ 15.220,34 e o valor FINAL entregue em Sao Paulo capital, ou se o acrescimo ainda incide. | D67: Pendente
B68: 54 | C68: 'ESTRUTURA, PROTECOES, CABOS E HOMOLOGACAO INCLUSOS' precisa virar lista item a item. Exigir: modelo da estrutura e para qual tipo de telha, DPS CC e CA, disjuntores, string box, bitola dos cabos, ART e quem protocola na Enel. | D68: Pendente
B69: 55 | C69: ASSISTENCIA TECNICA A 340 km. A SunWash anuncia atendimento para Ribeirao Preto ate 80 km e cobra R$ 1.800 para atender a sua regiao. Perguntar o prazo de atendimento em caso de falha e se ha equipe propria em Sao Paulo. | D69: Pendente
B70: 56 | C70: COTACOES VENCIDAS. As cotacoes Belenergy valem 3 dias e foram emitidas em 08/08 e 10/08/2026. Pedir revalidacao de preco antes de fechar. | D70: Pendente
C72: 2) DOCUMENTOS A EXIGIR DE CADA FORNECEDOR
B73: 57 | C73: Proposta comercial formal com razao social, CNPJ, escopo completo, prazo de execucao e forma de pagamento. | D73: Pendente
B74: 58 | C74: Relatorio de simulacao de geracao com azimute, inclinacao e sombreamento reais do telhado. | D74: Pendente
B75: 59 | C75: Ficha tecnica e registro INMETRO do modulo e do inversor. | D75: Pendente
B76: 60 | C76: Garantias por escrito: modulo (produto e performance), inversor, estrutura e mao de obra. | D76: Pendente
B77: 61 | C77: Responsabilidade pela homologacao na Enel, com ART emitida por profissional com CREA ou CFT. | D77: Pendente
B78: 62 | C78: Quem paga a adequacao do padrao de entrada e o aumento de carga, se a Enel exigir. | D78: Pendente
B79: 63 | C79: Garantia contra infiltracao no telhado apos a perfuracao para fixacao da estrutura. | D79: Pendente
B80: 64 | C80: Prazo de atendimento tecnico e distancia da equipe. | D80: Pendente
B81: 65 | C81: Acesso do proprietario ao monitoramento (app) e se ha mensalidade. | D81: Pendente
C83: 3) INSTALACAO ELETRICA E CARREGADOR DO BYD
B84: 66 | C84: Levantamento do padrao atual: numero de fases (hoje MONOFASICO), corrente do disjuntor geral e carga instalada. | D84: Pendente
B85: 67 | C85: Calculo de demanda somando residencia + inversor + carregador do veiculo, para saber se e preciso aumento de carga na Enel. | D85: Pendente
B86: 68 | C86: Circuito EXCLUSIVO para o carregador, com disjuntor dedicado e condutor dimensionado a 125% da corrente (NBR 5410, carga continua). | D86: Pendente
B87: 69 | C87: DPS no quadro do lado CA e DR/DDR conforme exigencia do fabricante do carregador. | D87: Pendente
B88: 70 | C88: Medicao da resistencia de aterramento. Inversor e carregador dependem de aterramento adequado. | D88: Pendente
B89: 71 | C89: Espaco livre no quadro de distribuicao para os novos disjuntores. | D89: Pendente
B90: 72 | C90: Definir o horario de carregamento. Telhado Sudeste gera mais de manha: carregar entre 9h e 14h aproveita a geracao direta e nao paga Fio B. | D90: Pendente
C92: 4) SO SE CONFIRMA COM INSPECAO PRESENCIAL - NAO ACEITE APENAS 'OK' NO WHATSAPP
B93: 73 | C93: Capacidade estrutural do telhado e das tercas para receber de 10 a 14 modulos. | D93: Pendente
B94: 74 | C94: Area util real da agua Sudeste e quantas placas realmente cabem. NAO foram enviadas fotos do telhado: esta analise nao avaliou area disponivel, sombras, chamines, caixa d'agua nem obstaculos. | D94: Pendente
B95: 75 | C95: Sombreamento ao longo do dia e do ano (arvores, caixa d'agua, muros, vizinhos). | D95: Pendente
B96: 76 | C96: Distancia real do telhado ao inversor e do inversor ao quadro, para definir a bitola dos cabos. | D96: Pendente
B97: 77 | C97: Estado do padrao de entrada, do ramal e do medidor. | D97: Pendente

Sheet NOVOS_ORCAMENTOS
A1: FORMULARIO PARA OS PROXIMOS ORCAMENTOS
A2: Preencha uma coluna por vendedor. Depois copie os valores para as colunas correspondentes da aba COMPARATIVO.
B4: DADO A COLETAR | C4: Bruno G4 | D4: Vendedor 6 | E4: Vendedor 7 | F4: POR QUE IMPORTA
B5: Empresa / razao social / CNPJ | F5: Sem CNPJ nao existe garantia exigivel.
B6: Contato | F6: Bruno G4: (11) 96861-7830
B7: Data da proposta e validade | F7: Cotacoes de material valem poucos dias.
B8: O PRECO E MATERIAL OU INSTALADO? | F8: Pergunta mais importante da lista. Nunca compare os dois tipos.
B9: Quantidade de modulos | F9: Base do dimensionamento.
B10: Potencia por modulo (W) | F10: Quantidade x potencia / 1000 = kWp.
B11: Fabricante, modelo e tecnologia do modulo | F11: N-type TOPCon degrada menos que PERC.
B12: Potencia total DC (kWp) | F12: Confira se fecha com quantidade x potencia.
B13: Fabricante e modelo exato do inversor | F13: Exigir o codigo, nao 'hibrido 6 kW'.
B14: Potencia AC do inversor (kW) | F14: Limita a injecao e a expansao futura.
B15: Corrente maxima por MPPT (A) | F15: Precisa ser maior que a corrente do modulo.
B16: Corrente de operacao do modulo - Impp (A) | F16: Se for maior que a do MPPT, perde geracao.
... B35: Tipo de telha que o orcamento considerou | F35: TecSolarSP disse fibrocimento, William disse colonial.
